Workbook

Sheet Inicio
A1: 🍇 FAST AÇAÍ — CMV Padrão para Franquias Próprias
A2: Matéria-prima, coberturas e embalagens têm o MESMO preço em todas as lojas (compra centralizada da franquia) — só os custos fixos mudam de loja para loja.
B3: 👉 Para mostrar aos sócios, use a aba RESUMO — mesmos produtos e preços do cardápio, sem fórmulas visíveis. As demais abas são a engenharia por trás dos números.
B5: Como usar (ordem recomendada)
B6: 1. Insumos | C6: Preencha os preços: Bases (Açaí/Cupuaçu) pelo valor da caixa de 9L produzida pela franqueadora; Coberturas por pacote (30g calculado sozinho).
B7: 2. Embalagens | C7: Preencha o valor da caixa de copos 200/300/500ml, tampas e canudo.
B8: 3. Ficha_Tecnica | C8: Já vem pronta com as receitas dos 58 itens do cardápio real (Açaí em Ondas + 9 receitas, Linha Premium, Linha Tradicional, Milkshakes, Bebidas) — ajuste só se mudar alguma receita.
B9: 4. Rateio | C9: Uma coluna por loja: preencha aluguel, energia, água, funcionários etc. de cada quiosque.
B10: 5. Configuracoes | C10: Escolha a 'Loja Selecionada' e ajuste margem, impostos, taxa de cartão e comissão.
B11: 6. Receitas | C11: Preço praticado (do cardápio) x custo real, CMV e margem de cada item — 100% automático.
B12: 7. Abas por categoria | C12: Açaí em Ondas, Linha Premium, Linha Tradicional, Toppings, Milkshakes e Bebidas — mesma informação da Receitas, organizada por seção do cardápio (tamanhos lado a lado) e pronta para mostrar aos sócios.
B13: 8. Precificacao / Dashboard / Simulador | C13: Calculadora rápida, visão gerencial e testes de variação de preço.
B15: Para replicar para outra loja
B16: Como os insumos são iguais para todas as lojas, você NÃO precisa duplicar o arquivo: só renomeie uma coluna em branco da aba Rateio com o nome do novo quiosque, preencha os custos fixos dele e selecione essa loja em Configurações.
B18: Legenda de cores
B19: Texto azul | C19: Célula de entrada — preencha com o valor da nota fiscal.
B20: Texto preto | C20: Fórmula — calculada automaticamente, evite editar.
B21: Texto verde | C21: Link com valor de outra aba.
B22: 🟢 🟡 🔴 | C22: Semáforo de margem: saudável / atenção / abaixo da meta (aba Receitas).

Sheet Açaí em Ondas
A1: 🍇 AÇAÍ EM ONDAS & RECEITAS FAST — Preço x Custo por Tamanho
A2: Compare o mesmo copo (P/M/G) lado a lado. Preço, custo, CMV e margem vêm da aba Receitas — não precisa mexer em fórmula nenhuma aqui.
A4: Produto | B4: 200ml | F4: 300ml | J4: 500ml
B5: Preço (R$) | C5: Custo Total (R$) | D5: CMV (%) | E5: Margem (%) | F5: Preço (R$) | G5: Custo Total (R$) | H5: CMV (%) | I5: Margem (%) | J5: Preço (R$) | K5: Custo Total (R$) | L5: CMV (%) | M5: Margem (%)
A6: Açaí em Ondas | B6: =IFERROR(INDEX(Receitas_PrecoPraticado,MATCH("Açaí em Ondas 200ml",Receitas_Produto,0)),"") -> 16.9 | C6: =IFERROR(INDEX(Receitas_CustoTotalUnit,MATCH("Açaí em Ondas 200ml",Receitas_Produto,0)),"") -> 11.718619 | D6: =IFERROR(INDEX(Receitas_CMV,MATCH("Açaí em Ondas 200ml",Receitas_Produto,0)),"") -> 0.25504976 | E6: =IFERROR(INDEX(Receitas_Margem,MATCH("Açaí em Ondas 200ml",Receitas_Produto,0)),"") -> 0.1015906 | F6: =IFERROR(INDEX(Receitas_PrecoPraticado,MATCH("Açaí em Ondas 300ml",Receitas_Produto,0)),"") -> 22.9 | G6: =IFERROR(INDEX(Receitas_CustoTotalUnit,MATCH("Açaí em Ondas 300ml",Receitas_Produto,0)),"") -> 13.406165 | H6: =IFERROR(INDEX(Receitas_CMV,MATCH("Açaí em Ondas 300ml",Receitas_Produto,0)),"") -> 0.26191648 | I6: =IFERROR(INDEX(Receitas_Margem,MATCH("Açaí em Ondas 300ml",Receitas_Produto,0)),"") -> 0.20957794 | J6: =IFERROR(INDEX(Receitas_PrecoPraticado,MATCH("Açaí em Ondas 500ml",Receitas_Produto,0)),"") -> 29.9 | K6: =IFERROR(INDEX(Receitas_CustoTotalUnit,MATCH("Açaí em Ondas 500ml",Receitas_Produto,0)),"") -> 16.911248 | L6: =IFERROR(INDEX(Receitas_CMV,MATCH("Açaí em Ondas 500ml",Receitas_Produto,0)),"") -> 0.31782508 | M6: =IFERROR(INDEX(Receitas_Margem,MATCH("Açaí em Ondas 500ml",Receitas_Produto,0)),"") -> 0.22940643
A7: Fast Classic | B7: =IFERROR(INDEX(Receitas_PrecoPraticado,MATCH("Fast Classic 200ml",Receitas_Produto,0)),"") -> 16.9 | C7: =IFERROR(INDEX(Receitas_CustoTotalUnit,MATCH("Fast Classic 200ml",Receitas_Produto,0)),"") -> 12.756248 | D7: =IFERROR(INDEX(Receitas_CMV,MATCH("Fast Classic 200ml",Receitas_Produto,0)),"") -> 0.31644792 | E7: =IFERROR(INDEX(Receitas_Margem,MATCH("Fast Classic 200ml",Receitas_Produto,0)),"") -> 0.040192447 | F7: =IFERROR(INDEX(Receitas_PrecoPraticado,MATCH("Fast Classic 300ml",Receitas_Produto,0)),"") -> 22.9 | G7: =IFERROR(INDEX(Receitas_CustoTotalUnit,MATCH("Fast Classic 300ml",Receitas_Produto,0)),"") -> 14.443794 | H7: =IFERROR(INDEX(Receitas_CMV,MATCH("Fast Classic 300ml",Receitas_Produto,0)),"") -> 0.30722778 | I7: =IFERROR(INDEX(Receitas_Margem,MATCH("Fast Classic 300ml",Receitas_Produto,0)),"") -> 0.16426664 | J7: =IFERROR(INDEX(Receitas_PrecoPraticado,MATCH("Fast Classic 500ml",Receitas_Produto,0)),"") -> 29.9 | K7: =IFERROR(INDEX(Receitas_CustoTotalUnit,MATCH("Fast Classic 500ml",Receitas_Produto,0)),"") -> 17.948877 | L7: =IFERROR(INDEX(Receitas_CMV,MATCH("Fast Classic 500ml",Receitas_Produto,0)),"") -> 0.35252839 | M7: =IFERROR(INDEX(Receitas_Margem,MATCH("Fast Classic 500ml",Receitas_Produto,0)),"") -> 0.19470313
A8: Power | B8: =IFERROR(INDEX(Receitas_PrecoPraticado,MATCH("Power 200ml",Receitas_Produto,0)),"") -> 16.9 | C8: =IFERROR(INDEX(Receitas_CustoTotalUnit,MATCH("Power 200ml",Receitas_Produto,0)),"") -> 12.409237 | D8: =IFERROR(INDEX(Receitas_CMV,MATCH("Power 200ml",Receitas_Produto,0)),"") -> 0.29591477 | E8: =IFERROR(INDEX(Receitas_Margem,MATCH("Power 200ml",Receitas_Produto,0)),"") -> 0.060725602 | F8: =IFERROR(INDEX(Receitas_PrecoPraticado,MATCH("Power 300ml",Receitas_Produto,0)),"") -> 22.9 | G8: =IFERROR(INDEX(Receitas_CustoTotalUnit,MATCH("Power 300ml",Receitas_Produto,0)),"") -> 14.096784 | H8: =IFERROR(INDEX(Receitas_CMV,MATCH("Power 300ml",Receitas_Produto,0)),"") -> 0.2920745 | I8: =IFERROR(INDEX(Receitas_Margem,MATCH("Power 300ml",Receitas_Produto,0)),"") -> 0.17941992 | J8: =IFERROR(INDEX(Receitas_PrecoPraticado,MATCH("Power 500ml",Receitas_Produto,0)),"") -> 29.9 | K8: =IFERROR(INDEX(Receitas_CustoTotalUnit,MATCH("Power 500ml",Receitas_Produto,0)),"") -> 17.601866 | L8: =IFERROR(INDEX(Receitas_CMV,MATCH("Power 500ml",Receitas_Produto,0)),"") -> 0.34092269 | M8: =IFERROR(INDEX(Receitas_Margem,MATCH("Power 500ml",Receitas_Produto,0)),"") -> 0.20630882
A9: Choco Nuts | B9: =IFERROR(INDEX(Receitas_PrecoPraticado,MATCH("Choco Nuts 200ml",Receitas_Produto,0)),"") -> 16.9 | C9: =IFERROR(INDEX(Receitas_CustoTotalUnit,MATCH("Choco Nuts 200ml",Receitas_Produto,0)),"") -> 13.116628 | D9: =IFERROR(INDEX(Receitas_CMV,MATCH("Choco Nuts 200ml",Receitas_Produto,0)),"") -> 0.33777222 | E9: =IFERROR(INDEX(Receitas_Margem,MATCH("Choco Nuts 200ml",Receitas_Produto,0)),"") -> 0.018868148 | F9: =IFERROR(INDEX(Receitas_PrecoPraticado,MATCH("Choco Nuts 300ml",Receitas_Produto,0)),"") -> 22.9 | G9: =IFERROR(INDEX(Receitas_CustoTotalUnit,MATCH("Choco Nuts 300ml",Receitas_Produto,0)),"") -> 14.804175 | H9: =IFERROR(INDEX(Receitas_CMV,MATCH("Choco Nuts 300ml",Receitas_Produto,0)),"") -> 0.32296493 | I9: =IFERROR(INDEX(Receitas_Margem,MATCH("Choco Nuts 300ml",Receitas_Produto,0)),"") -> 0.14852949 | J9: =IFERROR(INDEX(Receitas_PrecoPraticado,MATCH("Choco Nuts 500ml",Receitas_Produto,0)),"") -> 29.9 | K9: =IFERROR(INDEX(Receitas_CustoTotalUnit,MATCH("Choco Nuts 500ml",Receitas_Produto,0)),"") -> 18.309257 | L9: =IFERROR(INDEX(Receitas_CMV,MATCH("Choco Nuts 500ml",Receitas_Produto,0)),"") -> 0.36458125 | M9: =IFERROR(INDEX(Receitas_Margem,MATCH("Choco Nuts 500ml",Receitas_Produto,0)),"") -> 0.18265026
A10: Trupe Fast | B10: =IFERROR(INDEX(Receitas_PrecoPraticado,MATCH("Trupe Fast 200ml",Receitas_Produto,0)),"") -> 16.9 | C10: =IFERROR(INDEX(Receitas_CustoTotalUnit,MATCH("Trupe Fast 200ml",Receitas_Produto,0)),"") -> 11.343464 | D10: =IFERROR(INDEX(Receitas_CMV,MATCH("Trupe Fast 200ml",Receitas_Produto,0)),"") -> 0.23285126 | E10: =IFERROR(INDEX(Receitas_Margem,MATCH("Trupe Fast 200ml",Receitas_Produto,0)),"") -> 0.1237891 | F10: =IFERROR(INDEX(Receitas_PrecoPraticado,MATCH("Trupe Fast 300ml",Receitas_Produto,0)),"") -> 22.9 | G10: =IFERROR(INDEX(Receitas_CustoTotalUnit,MATCH("Trupe Fast 300ml",Receitas_Produto,0)),"") -> 13.031011 | H10: =IFERROR(INDEX(Receitas_CMV,MATCH("Trupe Fast 300ml",Receitas_Produto,0)),"") -> 0.24553418 | I10: =IFERROR(INDEX(Receitas_Margem,MATCH("Trupe Fast 300ml",Receitas_Produto,0)),"") -> 0.22596024 | J10: =IFERROR(INDEX(Receitas_PrecoPraticado,MATCH("Trupe Fast 500ml",Receitas_Produto,0)),"") -> 29.9 | K10: =IFERROR(INDEX(Receitas_CustoTotalUnit,MATCH("Trupe Fast 500ml",Receitas_Produto,0)),"") -> 16.536093 | L10: =IFERROR(INDEX(Receitas_CMV,MATCH("Trupe Fast 500ml",Receitas_Produto,0)),"") -> 0.3052781 | M10: =IFERROR(INDEX(Receitas_Margem,MATCH("Trupe Fast 500ml",Receitas_Produto,0)),"") -> 0.24195341
A11: Berry | B11: =IFERROR(INDEX(Receitas_PrecoPraticado,MATCH("Berry 200ml",Receitas_Produto,0)),"") -> 16.9 | C11: =IFERROR(INDEX(Receitas_CustoTotalUnit,MATCH("Berry 200ml",Receitas_Produto,0)),"") -> 11.853773 | D11: =IFERROR(INDEX(Receitas_CMV,MATCH("Berry 200ml",Receitas_Produto,0)),"") -> 0.26304708 | E11: =IFERROR(INDEX(Receitas_Margem,MATCH("Berry 200ml",Receitas_Produto,0)),"") -> 0.093593289 | F11: =IFERROR(INDEX(Receitas_PrecoPraticado,MATCH("Berry 300ml",Receitas_Produto,0)),"") -> 22.9 | G11: =IFERROR(INDEX(Receitas_CustoTotalUnit,MATCH("Berry 300ml",Receitas_Produto,0)),"") -> 13.54132 | H11: =IFERROR(INDEX(Receitas_CMV,MATCH("Berry 300ml",Receitas_Produto,0)),"") -> 0.26781843 | I11: =IFERROR(INDEX(Receitas_Margem,MATCH("Berry 300ml",Receitas_Produto,0)),"") -> 0.20367599 | J11: =IFERROR(INDEX(Receitas_PrecoPraticado,MATCH("Berry 500ml",Receitas_Produto,0)),"") -> 29.9 | K11: =IFERROR(INDEX(Receitas_CustoTotalUnit,MATCH("Berry 500ml",Receitas_Produto,0)),"") -> 17.046402 | L11: =IFERROR(INDEX(Receitas_CMV,MATCH("Berry 500ml",Receitas_Produto,0)),"") -> 0.3223453 | M11: =IFERROR(INDEX(Receitas_Margem,MATCH("Berry 500ml",Receitas_Produto,0)),"") -> 0.22488621
A12: Granola Fit | B12: =IFERROR(INDEX(Receitas_PrecoPraticado,MATCH("Granola Fit 200ml",Receitas_Produto,0)),"") -> 16.9 | C12: =IFERROR(INDEX(Receitas_CustoTotalUnit,MATCH("Granola Fit 200ml",Receitas_Produto,0)),"") -> 12.034083 | D12: =IFERROR(INDEX(Receitas_CMV,MATCH("Granola Fit 200ml",Receitas_Produto,0)),"") -> 0.27371627 | E12: =IFERROR(INDEX(Receitas_Margem,MATCH("Granola Fit 200ml",Receitas_Produto,0)),"") -> 0.082924101 | F12: =IFERROR(INDEX(Receitas_PrecoPraticado,MATCH("Granola Fit 300ml",Receitas_Produto,0)),"") -> 22.9 | G12: =IFERROR(INDEX(Receitas_CustoTotalUnit,MATCH("Granola Fit 300ml",Receitas_Produto,0)),"") -> 13.721629 | H12: =IFERROR(INDEX(Receitas_CMV,MATCH("Granola Fit 300ml",Receitas_Produto,0)),"") -> 0.2756922 | I12: =IFERROR(INDEX(Receitas_Margem,MATCH("Granola Fit 300ml",Receitas_Produto,0)),"") -> 0.19580222 | J12: =IFERROR(INDEX(Receitas_PrecoPraticado,MATCH("Granola Fit 500ml",Receitas_Produto,0)),"") -> 29.9 | K12: =IFERROR(INDEX(Receitas_CustoTotalUnit,MATCH("Granola Fit 500ml",Receitas_Produto,0)),"") -> 17.226712 | L12: =IFERROR(INDEX(Receitas_CMV,MATCH("Granola Fit 500ml",Receitas_Produto,0)),"") -> 0.32837571 | M12: =IFERROR(INDEX(Receitas_Margem,MATCH("Granola Fit 500ml",Receitas_Produto,0)),"") -> 0.2188558
A13: Fast Protein | B13: =IFERROR(INDEX(Receitas_PrecoPraticado,MATCH("Fast Protein 200ml",Receitas_Produto,0)),"") -> 16.9 | C13: =IFERROR(INDEX(Receitas_CustoTotalUnit,MATCH("Fast Protein 200ml",Receitas_Produto,0)),"") -> 11.762536 | D13: =IFERROR(INDEX(Receitas_CMV,MATCH("Fast Protein 200ml",Receitas_Produto,0)),"") -> 0.25764843 | E13: =IFERROR(INDEX(Receitas_Margem,MATCH("Fast Protein 200ml",Receitas_Produto,0)),"") -> 0.098991935 | F13: =IFERROR(INDEX(Receitas_PrecoPraticado,MATCH("Fast Protein 300ml",Receitas_Produto,0)),"") -> 22.9 | G13: =IFERROR(INDEX(Receitas_CustoTotalUnit,MATCH("Fast Protein 300ml",Receitas_Produto,0)),"") -> 13.450083 | H13: =IFERROR(INDEX(Receitas_CMV,MATCH("Fast Protein 300ml",Receitas_Produto,0)),"") -> 0.26383428 | I13: =IFERROR(INDEX(Receitas_Margem,MATCH("Fast Protein 300ml",Receitas_Produto,0)),"") -> 0.20766014 | J13: =IFERROR(INDEX(Receitas_PrecoPraticado,MATCH("Fast Protein 500ml",Receitas_Produto,0)),"") -> 29.9 | K13: =IFERROR(INDEX(Receitas_CustoTotalUnit,MATCH("Fast Protein 500ml",Receitas_Produto,0)),"") -> 16.955165 | L13: =IFERROR(INDEX(Receitas_CMV,MATCH("Fast Protein 500ml",Receitas_Produto,0)),"") -> 0.31929389 | M13: =IFERROR(INDEX(Receitas_Margem,MATCH("Fast Protein 500ml",Receitas_Produto,0)),"") -> 0.22793762
A14: Berry Protein | B14: =IFERROR(INDEX(Receitas_PrecoPraticado,MATCH("Berry Protein 200ml",Receitas_Produto,0)),"") -> 16.9 | C14: =IFERROR(INDEX(Receitas_CustoTotalUnit,MATCH("Berry Protein 200ml",Receitas_Produto,0)),"") -> 11.782401 | D14: =IFERROR(INDEX(Receitas_CMV,MATCH("Berry Protein 200ml",Receitas_Produto,0)),"") -> 0.25882389 | E14: =IFERROR(INDEX(Receitas_Margem,MATCH("Berry Protein 200ml",Receitas_Produto,0)),"") -> 0.09781648 | F14: =IFERROR(INDEX(Receitas_PrecoPraticado,MATCH("Berry Protein 300ml",Receitas_Produto,0)),"") -> 22.9 | G14: =IFERROR(INDEX(Receitas_CustoTotalUnit,MATCH("Berry Protein 300ml",Receitas_Produto,0)),"") -> 13.469948 | H14: =IFERROR(INDEX(Receitas_CMV,MATCH("Berry Protein 300ml",Receitas_Produto,0)),"") -> 0.26470175 | I14: =IFERROR(INDEX(Receitas_Margem,MATCH("Berry Protein 300ml",Receitas_Produto,0)),"") -> 0.20679267 | J14: =IFERROR(INDEX(Receitas_PrecoPraticado,MATCH("Berry Protein 500ml",Receitas_Produto,0)),"") -> 29.9 | K14: =IFERROR(INDEX(Receitas_CustoTotalUnit,MATCH("Berry Protein 500ml",Receitas_Produto,0)),"") -> 16.97503 | L14: =IFERROR(INDEX(Receitas_CMV,MATCH("Berry Protein 500ml",Receitas_Produto,0)),"") -> 0.31995828 | M14: =IFERROR(INDEX(Receitas_Margem,MATCH("Berry Protein 500ml",Receitas_Produto,0)),"") -> 0.22727323
A15: Nuts Protein | B15: =IFERROR(INDEX(Receitas_PrecoPraticado,MATCH("Nuts Protein 200ml",Receitas_Produto,0)),"") -> 16.9 | C15: =IFERROR(INDEX(Receitas_CustoTotalUnit,MATCH("Nuts Protein 200ml",Receitas_Produto,0)),"") -> 10.724907 | D15: =IFERROR(INDEX(Receitas_CMV,MATCH("Nuts Protein 200ml",Receitas_Produto,0)),"") -> 0.19625028 | E15: =IFERROR(INDEX(Receitas_Margem,MATCH("Nuts Protein 200ml",Receitas_Produto,0)),"") -> 0.16039009 | F15: =IFERROR(INDEX(Receitas_PrecoPraticado,MATCH("Nuts Protein 300ml",Receitas_Produto,0)),"") -> 22.9 | G15: =IFERROR(INDEX(Receitas_CustoTotalUnit,MATCH("Nuts Protein 300ml",Receitas_Produto,0)),"") -> 12.412454 | H15: =IFERROR(INDEX(Receitas_CMV,MATCH("Nuts Protein 300ml",Receitas_Produto,0)),"") -> 0.21852297 | I15: =IFERROR(INDEX(Receitas_Margem,MATCH("Nuts Protein 300ml",Receitas_Produto,0)),"") -> 0.25297145 | J15: =IFERROR(INDEX(Receitas_PrecoPraticado,MATCH("Nuts Protein 500ml",Receitas_Produto,0)),"") -> 29.9 | K15: =IFERROR(INDEX(Receitas_CustoTotalUnit,MATCH("Nuts Protein 500ml",Receitas_Produto,0)),"") -> 15.917536 | L15: =IFERROR(INDEX(Receitas_CMV,MATCH("Nuts Protein 500ml",Receitas_Produto,0)),"") -> 0.28459059 | M15: =IFERROR(INDEX(Receitas_Margem,MATCH("Nuts Protein 500ml",Receitas_Produto,0)),"") -> 0.26264093

Sheet Configuracoes
A1: ⚙️ CONFIGURAÇÕES — Parâmetros Globais de Precificação
A2: Edite apenas as células em AZUL. Estes parâmetros valem para TODAS as lojas — o que muda de loja para loja são os custos fixos, na aba Rateio. Escolha a loja ativa no campo 'Loja Selecionada' abaixo.
A4: Parâmetro | B4: Valor | C4: Observação
A5: Margem Bruta Desejada (%) | B5: 0.65 | C5: Referência de mercado para redes de açaí (60% a 70%).
A6: Margem Líquida Desejada (%) | B6: 0.15 | C6: Meta de lucro líquido após impostos, taxas e comissões.
A7: Impostos (%) | B7: 0.06 | C7: Alíquota efetiva estimada. Ajuste ao seu regime tributário.
A8: Taxa Cartão (%) | B8: 0.025 | C8: Taxa média de cartão/maquininha sobre o valor da venda.
A9: Comissão (%) | B9: 0.12 | C9: Comissão média de apps de delivery. Zere se vender só no balcão.
A10: Perdas (%) | B10: 0.03 | C10: Perda média de insumos (validade, erro de preparo), aplicada a todos os produtos.
A11: Desconto Máximo Permitido (%) | B11: 0.1 | C11: Limite de desconto em promoções sem corroer a margem mínima.
A12: Loja Ativa
A13: Loja Selecionada | B13: Loja 1 | C13: Define de qual loja (aba Rateio) vêm os custos fixos usados no CMV e no preço sugerido.

Sheet Insumos
A1: 🍇 INSUMOS — Preencha os Preços de Acordo com a Nota Fiscal
A2: BASES (Açaí/Cupuaçu): produzidas pela franqueadora e enviadas ao quiosque em caixa de calda pronta (padrão 9L) — confirme a Quantidade Comprada (ml da caixa) e digite o Valor Pago = valor cobrado pela caixa. COBERTURAS (30g): informe o valor pago e o peso do pacote comprado — o custo da porção de 30g é calculado sozinho na última coluna.
A4: Ingrediente | B4: Categoria | C4: Fornecedor | D4: Unidade | E4: Porção Padrão | F4: Quantidade Comprada | G4: Valor Pago (R$) | H4: Frete (R$) | I4: Valor Final (R$) | J4: Custo por g/ml/un (R$) | K4: Status | L4: Custo da Porção 30g (R$)
A5: Açaí | B5: Bases (Produção Própria) | D5: ml | E5: Caixa de 9L | F5: 9000 | G5: 148.5 | H5: 0 | I5: =IF(AND($G5="",$H5=""),"",SUM($G5:$H5)) -> 148.5 | J5: =IF($B5="","",IF($B5="Embalagens",IFERROR(INDEX(Embalagens_CustoUnit,MATCH($A5,Embalagens_Nome,0)),0),IFERROR($I5/$F5,0))) -> 0.0165 | K5: Ativo | L5: =IF($B5="Coberturas (30g)",IF($D5="un",$J5,$J5*30),"")
A6: Cupuaçu | B6: Bases (Produção Própria) | D6: ml | E6: Caixa de 9L | F6: 9000 | G6: 148.5 | H6: 0 | I6: =IF(AND($G6="",$H6=""),"",SUM($G6:$H6)) -> 148.5 | J6: =IF($B6="","",IF($B6="Embalagens",IFERROR(INDEX(Embalagens_CustoUnit,MATCH($A6,Embalagens_Nome,0)),0),IFERROR($I6/$F6,0))) -> 0.0165 | K6: Ativo | L6: =IF($B6="Coberturas (30g)",IF($D6="un",$J6,$J6*30),"")
A7: Leite Integral (Milkshake) | B7: Bases (Produção Própria) | D7: ml | E7: Caixa de 1L | F7: 1000 | H7: 0 | I7: =IF(AND($G7="",$H7=""),"",SUM($G7:$H7)) -> 0 | J7: =IF($B7="","",IF($B7="Embalagens",IFERROR(INDEX(Embalagens_CustoUnit,MATCH($A7,Embalagens_Nome,0)),0),IFERROR($I7/$F7,0))) -> 0 | K7: Ativo | L7: =IF($B7="Coberturas (30g)",IF($D7="un",$J7,$J7*30),"")
A8: Leite em pó | B8: Coberturas (30g) | D8: g | E8: 30g | F8: 1000 | G8: 33.55 | I8: =IF(AND($G8="",$H8=""),"",SUM($G8:$H8)) -> 33.55 | J8: =IF($B8="","",IF($B8="Embalagens",IFERROR(INDEX(Embalagens_CustoUnit,MATCH($A8,Embalagens_Nome,0)),0),IFERROR($I8/$F8,0))) -> 0.03355 | K8: Ativo | L8: =IF($B8="Coberturas (30g)",IF($D8="un",$J8,$J8*30),"") -> 1.0065
A9: Banana | B9: Coberturas (30g) | D9: g | E9: 30g | F9: 390000 | G9: 900 | I9: =IF(AND($G9="",$H9=""),"",SUM($G9:$H9)) -> 900 | J9: =IF($B9="","",IF($B9="Embalagens",IFERROR(INDEX(Embalagens_CustoUnit,MATCH($A9,Embalagens_Nome,0)),0),IFERROR($I9/$F9,0))) -> 0.0023076923 | K9: Ativo | L9: =IF($B9="Coberturas (30g)",IF($D9="un",$J9,$J9*30),"") -> 0.069230769
A10: Morango | B10: Coberturas (30g) | D10: g | E10: 30g | F10: 5000 | G10: 82.5 | I10: =IF(AND($G10="",$H10=""),"",SUM($G10:$H10)) -> 82.5 | J10: =IF($B10="","",IF($B10="Embalagens",IFERROR(INDEX(Embalagens_CustoUnit,MATCH($A10,Embalagens_Nome,0)),0),IFERROR($I10/$F10,0))) -> 0.0165 | K10: Ativo | L10: =IF($B10="Coberturas (30g)",IF($D10="un",$J10,$J10*30),"") -> 0.495
A11: Granola | B11: Coberturas (30g) | D11: g | E11: 30g | F11: 1000 | G11: 20 | I11: =IF(AND($G11="",$H11=""),"",SUM($G11:$H11)) -> 20 | J11: =IF($B11="","",IF($B11="Embalagens",IFERROR(INDEX(Embalagens_CustoUnit,MATCH($A11,Embalagens_Nome,0)),0),IFERROR($I11/$F11,0))) -> 0.02 | K11: Ativo | L11: =IF($B11="Coberturas (30g)",IF($D11="un",$J11,$J11*30),"") -> 0.6
A12: Leite condensado | B12: Coberturas (30g) | D12: g | E12: 30g | F12: 1000 | G12: 12.13 | I12: =IF(AND($G12="",$H12=""),"",SUM($G12:$H12)) -> 12.13 | J12: =IF($B12="","",IF($B12="Embalagens",IFERROR(INDEX(Embalagens_CustoUnit,MATCH($A12,Embalagens_Nome,0)),0),IFERROR($I12/$F12,0))) -> 0.01213 | K12: Ativo | L12: =IF($B12="Coberturas (30g)",IF($D12="un",$J12,$J12*30),"") -> 0.3639
A13: Paçoca | B13: Coberturas (30g) | D13: g | E13: 30g | F13: 1000 | G13: 22.33 | I13: =IF(AND($G13="",$H13=""),"",SUM($G13:$H13)) -> 22.33 | J13: =IF($B13="","",IF($B13="Embalagens",IFERROR(INDEX(Embalagens_CustoUnit,MATCH($A13,Embalagens_Nome,0)),0),IFERROR($I13/$F13,0))) -> 0.02233 | K13: Ativo | L13: =IF($B13="Coberturas (30g)",IF($D13="un",$J13,$J13*30),"") -> 0.6699
A14: Aveia | B14: Coberturas (30g) | D14: g | E14: 30g | F14: 1000 | I14: =IF(AND($G14="",$H14=""),"",SUM($G14:$H14)) | J14: =IF($B14="","",IF($B14="Embalagens",IFERROR(INDEX(Embalagens_CustoUnit,MATCH($A14,Embalagens_Nome,0)),0),IFERROR($I14/$F14,0))) -> 0 | K14: Ativo | L14: =IF($B14="Coberturas (30g)",IF($D14="un",$J14,$J14*30),"") -> 0
A15: Ovomaltine | B15: Coberturas (30g) | D15: g | E15: 30g | F15: 1000 | G15: 53.2 | I15: =IF(AND($G15="",$H15=""),"",SUM($G15:$H15)) -> 53.2 | J15: =IF($B15="","",IF($B15="Embalagens",IFERROR(INDEX(Embalagens_CustoUnit,MATCH($A15,Embalagens_Nome,0)),0),IFERROR($I15/$F15,0))) -> 0.0532 | K15: Ativo | L15: =IF($B15="Coberturas (30g)",IF($D15="un",$J15,$J15*30),"") -> 1.596
A16: Amendoim Granulado | B16: Coberturas (30g) | D16: g | E16: 30g | F16: 1000 | G16: 20.34 | I16: =IF(AND($G16="",$H16=""),"",SUM($G16:$H16)) -> 20.34 | J16: =IF($B16="","",IF($B16="Embalagens",IFERROR(INDEX(Embalagens_CustoUnit,MATCH($A16,Embalagens_Nome,0)),0),IFERROR($I16/$F16,0))) -> 0.02034 | K16: Ativo | L16: =IF($B16="Coberturas (30g)",IF($D16="un",$J16,$J16*30),"") -> 0.6102
A17: Pastilha de Chocolate | B17: Coberturas (30g) | D17: g | E17: 30g | F17: 1000 | G17: 29.59 | I17: =IF(AND($G17="",$H17=""),"",SUM($G17:$H17)) -> 29.59 | J17: =IF($B17="","",IF($B17="Embalagens",IFERROR(INDEX(Embalagens_CustoUnit,MATCH($A17,Embalagens_Nome,0)),0),IFERROR($I17/$F17,0))) -> 0.02959 | K17: Ativo | L17: =IF($B17="Coberturas (30g)",IF($D17="un",$J17,$J17*30),"") -> 0.8877
A18: Calda de Morango | B18: Coberturas (30g) | D18: ml | E18: 30ml | F18: 1000 | I18: =IF(AND($G18="",$H18=""),"",SUM($G18:$H18)) | J18: =IF($B18="","",IF($B18="Embalagens",IFERROR(INDEX(Embalagens_CustoUnit,MATCH($A18,Embalagens_Nome,0)),0),IFERROR($I18/$F18,0))) -> 0 | K18: Ativo | L18: =IF($B18="Coberturas (30g)",IF($D18="un",$J18,$J18*30),"") -> 0
A19: Calda de Maracujá | B19: Coberturas (30g) | D19: ml | E19: 30ml | F19: 1000 | I19: =IF(AND($G19="",$H19=""),"",SUM($G19:$H19)) | J19: =IF($B19="","",IF($B19="Embalagens",IFERROR(INDEX(Embalagens_CustoUnit,MATCH($A19,Embalagens_Nome,0)),0),IFERROR($I19/$F19,0))) -> 0 | K19: Ativo | L19: =IF($B19="Coberturas (30g)",IF($D19="un",$J19,$J19*30),"") -> 0
A20: Calda de Avelã | B20: Coberturas (30g) | D20: ml | E20: 30ml | I20: =IF(AND($G20="",$H20=""),"",SUM($G20:$H20)) | J20: =IF($B20="","",IF($B20="Embalagens",IFERROR(INDEX(Embalagens_CustoUnit,MATCH($A20,Embalagens_Nome,0)),0),IFERROR($I20/$F20,0))) -> 0 | K20: Ativo | L20: =IF($B20="Coberturas (30g)",IF($D20="un",$J20,$J20*30),"") -> 0
A21: Mel | B21: Coberturas (30g) | D21: ml | E21: 30ml | F21: 1000 | I21: =IF(AND($G21="",$H21=""),"",SUM($G21:$H21)) | J21: =IF($B21="","",IF($B21="Embalagens",IFERROR(INDEX(Embalagens_CustoUnit,MATCH($A21,Embalagens_Nome,0)),0),IFERROR($I21/$F21,0))) -> 0 | K21: Ativo | L21: =IF($B21="Coberturas (30g)",IF($D21="un",$J21,$J21*30),"") -> 0
A22: Whey Protein | B22: Coberturas (30g) | D22: g | E22: 30g | F22: 1000 | I22: =IF(AND($G22="",$H22=""),"",SUM($G22:$H22)) | J22: =IF($B22="","",IF($B22="Embalagens",IFERROR(INDEX(Embalagens_CustoUnit,MATCH($A22,Embalagens_Nome,0)),0),IFERROR($I22/$F22,0))) -> 0 | K22: Ativo | L22: =IF($B22="Coberturas (30g)",IF($D22="un",$J22,$J22*30),"") -> 0
A23: Nutella | B23: Coberturas (30g) | D23: g | E23: 30g | F23: 1000 | I23: =IF(AND($G23="",$H23=""),"",SUM($G23:$H23)) | J23: =IF($B23="","",IF($B23="Embalagens",IFERROR(INDEX(Embalagens_CustoUnit,MATCH($A23,Embalagens_Nome,0)),0),IFERROR($I23/$F23,0))) -> 0 | K23: Ativo | L23: =IF($B23="Coberturas (30g)",IF($D23="un",$J23,$J23*30),"") -> 0
A24: Pasta de Amendoim | B24: Coberturas (30g) | D24: g | E24: 30g | F24: 1000 | I24: =IF(AND($G24="",$H24=""),"",SUM($G24:$H24)) | J24: =IF($B24="","",IF($B24="Embalagens",IFERROR(INDEX(Embalagens_CustoUnit,MATCH($A24,Embalagens_Nome,0)),0),IFERROR($I24/$F24,0))) -> 0 | K24: Ativo | L24: =IF($B24="Coberturas (30g)",IF($D24="un",$J24,$J24*30),"") -> 0
A25: Canudo Wafer | B25: Coberturas (30g) | D25: un | E25: 1 unidade | F25: 1000 | I25: =IF(AND($G25="",$H25=""),"",SUM($G25:$H25)) | J25: =IF($B25="","",IF($B25="Embalagens",IFERROR(INDEX(Embalagens_CustoUnit,MATCH($A25,Embalagens_Nome,0)),0),IFERROR($I25/$F25,0))) -> 0 | K25: Ativo | L25: =IF($B25="Coberturas (30g)",IF($D25="un",$J25,$J25*30),"") -> 0
A26: Copo 200ml | B26: Embalagens | D26: un | E26: ver aba Embalagens | F26: 1 | G26: 0.1668 | I26: =IF(AND($G26="",$H26=""),"",SUM($G26:$H26)) -> 0.1668 | J26: =IF($B26="","",IF($B26="Embalagens",IFERROR(INDEX(Embalagens_CustoUnit,MATCH($A26,Embalagens_Nome,0)),0),IFERROR($I26/$F26,0))) -> 0.1668 | K26: Ativo | L26: =IF($B26="Coberturas (30g)",IF($D26="un",$J26,$J26*30),"")
A27: Copo 300ml | B27: Embalagens | D27: un | E27: ver aba Embalagens | F27: 1 | G27: 0.15372 | I27: =IF(AND($G27="",$H27=""),"",SUM($G27:$H27)) -> 0.15372 | J27: =IF($B27="","",IF($B27="Embalagens",IFERROR(INDEX(Embalagens_CustoUnit,MATCH($A27,Embalagens_Nome,0)),0),IFERROR($I27/$F27,0))) -> 0.15372 | K27: Ativo | L27: =IF($B27="Coberturas (30g)",IF($D27="un",$J27,$J27*30),"")
A28: Copo 500ml | B28: Embalagens | D28: un | E28: ver aba Embalagens | F28: 1 | G28: 0.24365 | I28: =IF(AND($G28="",$H28=""),"",SUM($G28:$H28)) -> 0.24365 | J28: =IF($B28="","",IF($B28="Embalagens",IFERROR(INDEX(Embalagens_CustoUnit,MATCH($A28,Embalagens_Nome,0)),0),IFERROR($I28/$F28,0))) -> 0.24365 | K28: Ativo | L28: =IF($B28="Coberturas (30g)",IF($D28="un",$J28,$J28*30),"")
A29: Tampa 200ml | B29: Embalagens | D29: un | E29: ver aba Embalagens | F29: 1 | G29: 0.0823 | I29: =IF(AND($G29="",$H29=""),"",SUM($G29:$H29)) -> 0.0823 | J29: =IF($B29="","",IF($B29="Embalagens",IFERROR(INDEX(Embalagens_CustoUnit,MATCH($A29,Embalagens_Nome,0)),0),IFERROR($I29/$F29,0))) -> 0.0823 | K29: Ativo | L29: =IF($B29="Coberturas (30g)",IF($D29="un",$J29,$J29*30),"")
A30: Tampa 300ml | B30: Embalagens | D30: un | E30: ver aba Embalagens | F30: 1 | G30: 0.0823 | I30: =IF(AND($G30="",$H30=""),"",SUM($G30:$H30)) -> 0.0823 | J30: =IF($B30="","",IF($B30="Embalagens",IFERROR(INDEX(Embalagens_CustoUnit,MATCH($A30,Embalagens_Nome,0)),0),IFERROR($I30/$F30,0))) -> 0.0823 | K30: Ativo | L30: =IF($B30="Coberturas (30g)",IF($D30="un",$J30,$J30*30),"")
A31: Tampa 500ml | B31: Embalagens | D31: un | E31: ver aba Embalagens | F31: 1 | G31: 0.0923 | I31: =IF(AND($G31="",$H31=""),"",SUM($G31:$H31)) -> 0.0923 | J31: =IF($B31="","",IF($B31="Embalagens",IFERROR(INDEX(Embalagens_CustoUnit,MATCH($A31,Embalagens_Nome,0)),0),IFERROR($I31/$F31,0))) -> 0.0923 | K31: Ativo | L31: =IF($B31="Coberturas (30g)",IF($D31="un",$J31,$J31*30),"")
A32: Copo Milkshake | B32: Embalagens | D32: un | E32: ver aba Embalagens | I32: =IF(AND($G32="",$H32=""),"",SUM($G32:$H32)) | J32: =IF($B32="","",IF($B32="Embalagens",IFERROR(INDEX(Embalagens_CustoUnit,MATCH($A32,Embalagens_Nome,0)),0),IFERROR($I32/$F32,0))) -> 0 | K32: Ativo | L32: =IF($B32="Coberturas (30g)",IF($D32="un",$J32,$J32*30),"")
A33: Tampa Milkshake | B33: Embalagens | D33: un | E33: ver aba Embalagens | I33: =IF(AND($G33="",$H33=""),"",SUM($G33:$H33)) | J33: =IF($B33="","",IF($B33="Embalagens",IFERROR(INDEX(Embalagens_CustoUnit,MATCH($A33,Embalagens_Nome,0)),0),IFERROR($I33/$F33,0))) -> 0 | K33: Ativo | L33: =IF($B33="Coberturas (30g)",IF($D33="un",$J33,$J33*30),"")
A34: Canudo | B34: Embalagens | D34: un | E34: ver aba Embalagens | I34: =IF(AND($G34="",$H34=""),"",SUM($G34:$H34)) | J34: =IF($B34="","",IF($B34="Embalagens",IFERROR(INDEX(Embalagens_CustoUnit,MATCH($A34,Embalagens_Nome,0)),0),IFERROR($I34/$F34,0))) -> 0 | K34: Ativo | L34: =IF($B34="Coberturas (30g)",IF($D34="un",$J34,$J34*30),"")
A35: Açaí Zero Açúcar 250ml | B35: Linha Premium (Comprada) | D35: un | E35: 1 pote | F35: 1 | G35: 12 | H35: 0 | I35: =IF(AND($G35="",$H35=""),"",SUM($G35:$H35)) -> 12 | J35: =IF($B35="","",IF($B35="Embalagens",IFERROR(INDEX(Embalagens_CustoUnit,MATCH($A35,Embalagens_Nome,0)),0),IFERROR($I35/$F35,0))) -> 12 | K35: Ativo | L35: =IF($B35="Coberturas (30g)",IF($D35="un",$J35,$J35*30),"")
A36: Açaí Zero Açúcar 500ml | B36: Linha Premium (Comprada) | D36: un | E36: 1 pote | F36: 1 | G36: 16 | H36: 0 | I36: =IF(AND($G36="",$H36=""),"",SUM($G36:$H36)) -> 16 | J36: =IF($B36="","",IF($B36="Embalagens",IFERROR(INDEX(Embalagens_CustoUnit,MATCH($A36,Embalagens_Nome,0)),0),IFERROR($I36/$F36,0))) -> 16 | K36: Ativo | L36: =IF($B36="Coberturas (30g)",IF($D36="un",$J36,$J36*30),"")
A37: Açaí Puro 250ml | B37: Linha Premium (Comprada) | D37: un | E37: 1 pote | F37: 1 | G37: 10 | H37: 0 | I37: =IF(AND($G37="",$H37=""),"",SUM($G37:$H37)) -> 10 | J37: =IF($B37="","",IF($B37="Embalagens",IFERROR(INDEX(Embalagens_CustoUnit,MATCH($A37,Embalagens_Nome,0)),0),IFERROR($I37/$F37,0))) -> 10 | K37: Ativo | L37: =IF($B37="Coberturas (30g)",IF($D37="un",$J37,$J37*30),"")
A38: Açaí Puro 500ml | B38: Linha Premium (Comprada) | D38: un | E38: 1 pote | F38: 1 | G38: 15 | H38: 0 | I38: =IF(AND($G38="",$H38=""),"",SUM($G38:$H38)) -> 15 | J38: =IF($B38="","",IF($B38="Embalagens",IFERROR(INDEX(Embalagens_CustoUnit,MATCH($A38,Embalagens_Nome,0)),0),IFERROR($I38/$F38,0))) -> 15 | K38: Ativo | L38: =IF($B38="Coberturas (30g)",IF($D38="un",$J38,$J38*30),"")
A39: Açaí Banana 250ml | B39: Linha Premium (Comprada) | D39: un | E39: 1 pote | F39: 1 | G39: 10 | H39: 0 | I39: =IF(AND($G39="",$H39=""),"",SUM($G39:$H39)) -> 10 | J39: =IF($B39="","",IF($B39="Embalagens",IFERROR(INDEX(Embalagens_CustoUnit,MATCH($A39,Embalagens_Nome,0)),0),IFERROR($I39/$F39,0))) -> 10 | K39: Ativo | L39: =IF($B39="Coberturas (30g)",IF($D39="un",$J39,$J39*30),"")
A40: Açaí Banana 500ml | B40: Linha Premium (Comprada) | D40: un | E40: 1 pote | F40: 1 | G40: 15 | H40: 0 | I40: =IF(AND($G40="",$H40=""),"",SUM($G40:$H40)) -> 15 | J40: =IF($B40="","",IF($B40="Embalagens",IFERROR(INDEX(Embalagens_CustoUnit,MATCH($A40,Embalagens_Nome,0)),0),IFERROR($I40/$F40,0))) -> 15 | K40: Ativo | L40: =IF($B40="Coberturas (30g)",IF($D40="un",$J40,$J40*30),"")
A41: Açaí Morango 250ml | B41: Linha Premium (Comprada) | D41: un | E41: 1 pote | F41: 1 | G41: 10 | H41: 0 | I41: =IF(AND($G41="",$H41=""),"",SUM($G41:$H41)) -> 10 | J41: =IF($B41="","",IF($B41="Embalagens",IFERROR(INDEX(Embalagens_CustoUnit,MATCH($A41,Embalagens_Nome,0)),0),IFERROR($I41/$F41,0))) -> 10 | K41: Ativo | L41: =IF($B41="Coberturas (30g)",IF($D41="un",$J41,$J41*30),"")
A42: Açaí Morango 500ml | B42: Linha Premium (Comprada) | D42: un | E42: 1 pote | F42: 1 | G42: 15 | H42: 0 | I42: =IF(AND($G42="",$H42=""),"",SUM($G42:$H42)) -> 15 | J42: =IF($B42="","",IF($B42="Embalagens",IFERROR(INDEX(Embalagens_CustoUnit,MATCH($A42,Embalagens_Nome,0)),0),IFERROR($I42/$F42,0))) -> 15 | K42: Ativo | L42: =IF($B42="Coberturas (30g)",IF($D42="un",$J42,$J42*30),"")
A43: Colher | B43: Consumíveis | D43: un | E43: 1 unidade | F43: 1 | G43: 0.0938 | I43: =IF(AND($G43="",$H43=""),"",SUM($G43:$H43)) -> 0.0938 | J43: =IF($B43="","",IF($B43="Embalagens",IFERROR(INDEX(Embalagens_CustoUnit,MATCH($A43,Embalagens_Nome,0)),0),IFERROR($I43/$F43,0))) -> 0.0938 | K43: Ativo | L43: =IF($B43="Coberturas (30g)",IF($D43="un",$J43,$J43*30),"")
A44: Guardanapo | B44: Consumíveis | D44: un | E44: 1 unidade | I44: =IF(AND($G44="",$H44=""),"",SUM($G44:$H44)) | J44: =IF($B44="","",IF($B44="Embalagens",IFERROR(INDEX(Embalagens_CustoUnit,MATCH($A44,Embalagens_Nome,0)),0),IFERROR($I44/$F44,0))) -> 0 | K44: Ativo | L44: =IF($B44="Coberturas (30g)",IF($D44="un",$J44,$J44*30),"")
A45: Sacola | B45: Consumíveis | D45: un | E45: 1 unidade | I45: =IF(AND($G45="",$H45=""),"",SUM($G45:$H45)) | J45: =IF($B45="","",IF($B45="Embalagens",IFERROR(INDEX(Embalagens_CustoUnit,MATCH($A45,Embalagens_Nome,0)),0),IFERROR($I45/$F45,0))) -> 0 | K45: Ativo | L45: =IF($B45="Coberturas (30g)",IF($D45="un",$J45,$J45*30),"")
A46: Água sem Gás 500ml | B46: Bebidas | D46: un | E46: 1 unidade | I46: =IF(AND($G46="",$H46=""),"",SUM($G46:$H46)) | J46: =IF($B46="","",IF($B46="Embalagens",IFERROR(INDEX(Embalagens_CustoUnit,MATCH($A46,Embalagens_Nome,0)),0),IFERROR($I46/$F46,0))) -> 0 | K46: Ativo | L46: =IF($B46="Coberturas (30g)",IF($D46="un",$J46,$J46*30),"")
A47: Água com Gás 500ml | B47: Bebidas | D47: un | E47: 1 unidade | I47: =IF(AND($G47="",$H47=""),"",SUM($G47:$H47)) | J47: =IF($B47="","",IF($B47="Embalagens",IFERROR(INDEX(Embalagens_CustoUnit,MATCH($A47,Embalagens_Nome,0)),0),IFERROR($I47/$F47,0))) -> 0 | K47: Ativo | L47: =IF($B47="Coberturas (30g)",IF($D47="un",$J47,$J47*30),"")
A48: Água de Coco 200ml | B48: Bebidas | D48: un | E48: 1 unidade | I48: =IF(AND($G48="",$H48=""),"",SUM($G48:$H48)) | J48: =IF($B48="","",IF($B48="Embalagens",IFERROR(INDEX(Embalagens_CustoUnit,MATCH($A48,Embalagens_Nome,0)),0),IFERROR($I48/$F48,0))) -> 0 | K48: Ativo | L48: =IF($B48="Coberturas (30g)",IF($D48="un",$J48,$J48*30),"")
A49: Refrigerante Lata 350ml | B49: Bebidas | D49: un | E49: 1 unidade | I49: =IF(AND($G49="",$H49=""),"",SUM($G49:$H49)) | J49: =IF($B49="","",IF($B49="Embalagens",IFERROR(INDEX(Embalagens_CustoUnit,MATCH($A49,Embalagens_Nome,0)),0),IFERROR($I49/$F49,0))) -> 0 | K49: Ativo | L49: =IF($B49="Coberturas (30g)",IF($D49="un",$J49,$J49*30),"")
A50: Refrigerante 600ml | B50: Bebidas | D50: un | E50: 1 unidade | I50: =IF(AND($G50="",$H50=""),"",SUM($G50:$H50)) | J50: =IF($B50="","",IF($B50="Embalagens",IFERROR(INDEX(Embalagens_CustoUnit,MATCH($A50,Embalagens_Nome,0)),0),IFERROR($I50/$F50,0))) -> 0 | K50: Ativo | L50: =IF($B50="Coberturas (30g)",IF($D50="un",$J50,$J50*30),"")
A51: Isotônico 500ml | B51: Bebidas | D51: un | E51: 1 unidade | I51: =IF(AND($G51="",$H51=""),"",SUM($G51:$H51)) | J51: =IF($B51="","",IF($B51="Embalagens",IFERROR(INDEX(Embalagens_CustoUnit,MATCH($A51,Embalagens_Nome,0)),0),IFERROR($I51/$F51,0))) -> 0 | K51: Ativo | L51: =IF($B51="Coberturas (30g)",IF($D51="un",$J51,$J51*30),"")
A52: Suco Natural 300ml | B52: Bebidas | D52: un | E52: 1 unidade | I52: =IF(AND($G52="",$H52=""),"",SUM($G52:$H52)) | J52: =IF($B52="","",IF($B52="Embalagens",IFERROR(INDEX(Embalagens_CustoUnit,MATCH($A52,Embalagens_Nome,0)),0),IFERROR($I52/$F52,0))) -> 0 | K52: Ativo | L52: =IF($B52="Coberturas (30g)",IF($D52="un",$J52,$J52*30),"")
A53: Suco de Açaí 200ml | B53: Bebidas | D53: un | E53: 1 unidade | I53: =IF(AND($G53="",$H53=""),"",SUM($G53:$H53)) | J53: =IF($B53="","",IF($B53="Embalagens",IFERROR(INDEX(Embalagens_CustoUnit,MATCH($A53,Embalagens_Nome,0)),0),IFERROR($I53/$F53,0))) -> 0 | K53: Ativo | L53: =IF($B53="Coberturas (30g)",IF($D53="un",$J53,$J53*30),"")
A54: Álcool 70% | B54: Limpeza | D54: ml | E54: — | I54: =IF(AND($G54="",$H54=""),"",SUM($G54:$H54)) | J54: =IF($B54="","",IF($B54="Embalagens",IFERROR(INDEX(Embalagens_CustoUnit,MATCH($A54,Embalagens_Nome,0)),0),IFERROR($I54/$F54,0))) -> 0 | K54: Ativo | L54: =IF($B54="Coberturas (30g)",IF($D54="un",$J54,$J54*30),"")
A55: Detergente | B55: Limpeza | D55: ml | E55: — | I55: =IF(AND($G55="",$H55=""),"",SUM($G55:$H55)) | J55: =IF($B55="","",IF($B55="Embalagens",IFERROR(INDEX(Embalagens_CustoUnit,MATCH($A55,Embalagens_Nome,0)),0),IFERROR($I55/$F55,0))) -> 0 | K55: Ativo | L55: =IF($B55="Coberturas (30g)",IF($D55="un",$J55,$J55*30),"")
I56: =IF(AND($G56="",$H56=""),"",SUM($G56:$H56)) | J56: =IF($B56="","",IF($B56="Embalagens",IFERROR(INDEX(Embalagens_CustoUnit,MATCH($A56,Embalagens_Nome,0)),0),IFERROR($I56/$F56,0))) | K56: Ativo | L56: =IF($B56="Coberturas (30g)",IF($D56="un",$J56,$J56*30),"")
I57: =IF(AND($G57="",$H57=""),"",SUM($G57:$H57)) | J57: =IF($B57="","",IF($B57="Embalagens",IFERROR(INDEX(Embalagens_CustoUnit,MATCH($A57,Embalagens_Nome,0)),0),IFERROR($I57/$F57,0))) | K57: Ativo | L57: =IF($B57="Coberturas (30g)",IF($D57="un",$J57,$J57*30),"")
I58: =IF(AND($G58="",$H58=""),"",SUM($G58:$H58)) | J58: =IF($B58="","",IF($B58="Embalagens",IFERROR(INDEX(Embalagens_CustoUnit,MATCH($A58,Embalagens_Nome,0)),0),IFERROR($I58/$F58,0))) | K58: Ativo | L58: =IF($B58="Coberturas (30g)",IF($D58="un",$J58,$J58*30),"")
I59: =IF(AND($G59="",$H59=""),"",SUM($G59:$H59)) | J59: =IF($B59="","",IF($B59="Embalagens",IFERROR(INDEX(Embalagens_CustoUnit,MATCH($A59,Embalagens_Nome,0)),0),IFERROR($I59/$F59,0))) | K59: Ativo | L59: =IF($B59="Coberturas (30g)",IF($D59="un",$J59,$J59*30),"")
I60: =IF(AND($G60="",$H60=""),"",SUM($G60:$H60)) | J60: =IF($B60="","",IF($B60="Embalagens",IFERROR(INDEX(Embalagens_CustoUnit,MATCH($A60,Embalagens_Nome,0)),0),IFERROR($I60/$F60,0))) | K60: Ativo | L60: =IF($B60="Coberturas (30g)",IF($D60="un",$J60,$J60*30),"")
I61: =IF(AND($G61="",$H61=""),"",SUM($G61:$H61)) | J61: =IF($B61="","",IF($B61="Embalagens",IFERROR(INDEX(Embalagens_CustoUnit,MATCH($A61,Embalagens_Nome,0)),0),IFERROR($I61/$F61,0))) | K61: Ativo | L61: =IF($B61="Coberturas (30g)",IF($D61="un",$J61,$J61*30),"")
I62: =IF(AND($G62="",$H62=""),"",SUM($G62:$H62)) | J62: =IF($B62="","",IF($B62="Embalagens",IFERROR(INDEX(Embalagens_CustoUnit,MATCH($A62,Embalagens_Nome,0)),0),IFERROR($I62/$F62,0))) | K62: Ativo | L62: =IF($B62="Coberturas (30g)",IF($D62="un",$J62,$J62*30),"")
I63: =IF(AND($G63="",$H63=""),"",SUM($G63:$H63)) | J63: =IF($B63="","",IF($B63="Embalagens",IFERROR(INDEX(Embalagens_CustoUnit,MATCH($A63,Embalagens_Nome,0)),0),IFERROR($I63/$F63,0))) | K63: Ativo | L63: =IF($B63="Coberturas (30g)",IF($D63="un",$J63,$J63*30),"")
I64: =IF(AND($G64="",$H64=""),"",SUM($G64:$H64)) | J64: =IF($B64="","",IF($B64="Embalagens",IFERROR(INDEX(Embalagens_CustoUnit,MATCH($A64,Embalagens_Nome,0)),0),IFERROR($I64/$F64,0))) | K64: Ativo | L64: =IF($B64="Coberturas (30g)",IF($D64="un",$J64,$J64*30),"")
I65: =IF(AND($G65="",$H65=""),"",SUM($G65:$H65)) | J65: =IF($B65="","",IF($B65="Embalagens",IFERROR(INDEX(Embalagens_CustoUnit,MATCH($A65,Embalagens_Nome,0)),0),IFERROR($I65/$F65,0))) | K65: Ativo | L65: =IF($B65="Coberturas (30g)",IF($D65="un",$J65,$J65*30),"")
I66: =IF(AND($G66="",$H66=""),"",SUM($G66:$H66)) | J66: =IF($B66="","",IF($B66="Embalagens",IFERROR(INDEX(Embalagens_CustoUnit,MATCH($A66,Embalagens_Nome,0)),0),IFERROR($I66/$F66,0))) | K66: Ativo | L66: =IF($B66="Coberturas (30g)",IF($D66="un",$J66,$J66*30),"")
I67: =IF(AND($G67="",$H67=""),"",SUM($G67:$H67)) | J67: =IF($B67="","",IF($B67="Embalagens",IFERROR(INDEX(Embalagens_CustoUnit,MATCH($A67,Embalagens_Nome,0)),0),IFERROR($I67/$F67,0))) | K67: Ativo | L67: =IF($B67="Coberturas (30g)",IF($D67="un",$J67,$J67*30),"")
... I85: =IF(AND($G85="",$H85=""),"",SUM($G85:$H85)) | J85: =IF($B85="","",IF($B85="Embalagens",IFERROR(INDEX(Embalagens_CustoUnit,MATCH($A85,Embalagens_Nome,0)),0),IFERROR($I85/$F85,0))) | K85: Ativo | L85: =IF($B85="Coberturas (30g)",IF($D85="un",$J85,$J85*30),"")

Sheet Embalagens
A1: 📦 EMBALAGENS — Copos 200/300/500ml, Tampas e Canudo
A2: Preencha Quantidade e Valor conforme a nota fiscal da caixa/pacote comprado (ex.: caixa com 1000 copos por R$ 175). O Custo Unitário é calculado sozinho e alimenta a aba Insumos.
A4: Nome | B4: Fornecedor | C4: Quantidade (un/caixa) | D4: Valor da Caixa (R$) | E4: Custo Unitário (R$)
A5: Copo 200ml | C5: 1 | D5: 0.1668 | E5: =IFERROR($D5/$C5,0) -> 0.1668
A6: Copo 300ml | C6: 1 | D6: 0.15372 | E6: =IFERROR($D6/$C6,0) -> 0.15372
A7: Copo 500ml | C7: 1 | D7: 0.24365 | E7: =IFERROR($D7/$C7,0) -> 0.24365
A8: Tampa 200ml | C8: 1 | D8: 0.0823 | E8: =IFERROR($D8/$C8,0) -> 0.0823
A9: Tampa 300ml | C9: 1 | D9: 0.0823 | E9: =IFERROR($D9/$C9,0) -> 0.0823
A10: Tampa 500ml | C10: 1 | D10: 0.0923 | E10: =IFERROR($D10/$C10,0) -> 0.0923
A11: Copo Milkshake | E11: =IFERROR($D11/$C11,0) -> 0
A12: Tampa Milkshake | E12: =IFERROR($D12/$C12,0) -> 0
A13: Canudo | E13: =IFERROR($D13/$C13,0) -> 0
E14: =IFERROR($D14/$C14,0) -> 0
E15: =IFERROR($D15/$C15,0) -> 0
E16: =IFERROR($D16/$C16,0) -> 0
E17: =IFERROR($D17/$C17,0) -> 0
E18: =IFERROR($D18/$C18,0) -> 0
E19: =IFERROR($D19/$C19,0) -> 0
E20: =IFERROR($D20/$C20,0) -> 0
E21: =IFERROR($D21/$C21,0) -> 0
E22: =IFERROR($D22/$C22,0) -> 0
E23: =IFERROR($D23/$C23,0) -> 0
E24: =IFERROR($D24/$C24,0) -> 0
E25: =IFERROR($D25/$C25,0) -> 0

Sheet Ficha_Tecnica
A1: 📋 FICHA TÉCNICA — Composição e Custo de Cada Produto
A2: Um ingrediente por linha. Açaí/Cupuaçu/Leite em ML; coberturas em múltiplos de 30g; embalagens em unidades. Para um NOVO PRODUTO, adicione linhas abaixo — nenhuma fórmula precisa ser alterada.
A4: Nome do Produto | B4: Categoria (auto) | C4: Ingrediente | D4: Quantidade Utilizada | E4: Unidade (auto) | F4: Custo Unitário (R$) | G4: Custo Total (R$) | H4: Qtd g/ml (aux.) | I4: Flag Açaí | J4: Flag Banana | K4: Flag Whey | L4: Flag Embalagem
A5: Açaí em Ondas 200ml | B5: =IF($C5="","",IFERROR(INDEX(Insumos_Categoria,MATCH($C5,Insumos_Ingrediente,0)),"")) -> Bases (Produção Própria) | C5: Açaí | D5: 170 | E5: =IF($C5="","",IFERROR(INDEX(Insumos_Unidade,MATCH($C5,Insumos_Ingrediente,0)),"")) -> ml | F5: =IFERROR(INDEX(Insumos_CustoUnit,MATCH($C5,Insumos_Ingrediente,0)),0) -> 0.0165 | G5: =$D5*$F5 -> 2.805 | H5: =IF(OR($E5="g",$E5="ml"),$D5,0) -> 170 | I5: =IF($C5="Açaí",1,0) -> 1 | J5: =IF($C5="Banana",1,0) -> 0 | K5: =IF($C5="Whey Protein",1,0) -> 0 | L5: =IF(ISNUMBER(SEARCH("Copo",$C5)),1,0) -> 0
A6: Açaí em Ondas 200ml | B6: =IF($C6="","",IFERROR(INDEX(Insumos_Categoria,MATCH($C6,Insumos_Ingrediente,0)),"")) -> Coberturas (30g) | C6: Banana | D6: 30 | E6: =IF($C6="","",IFERROR(INDEX(Insumos_Unidade,MATCH($C6,Insumos_Ingrediente,0)),"")) -> g | F6: =IFERROR(INDEX(Insumos_CustoUnit,MATCH($C6,Insumos_Ingrediente,0)),0) -> 0.0023076923 | G6: =$D6*$F6 -> 0.069230769 | H6: =IF(OR($E6="g",$E6="ml"),$D6,0) -> 30 | I6: =IF($C6="Açaí",1,0) -> 0 | J6: =IF($C6="Banana",1,0) -> 1 | K6: =IF($C6="Whey Protein",1,0) -> 0 | L6: =IF(ISNUMBER(SEARCH("Copo",$C6)),1,0) -> 0
A7: Açaí em Ondas 200ml | B7: =IF($C7="","",IFERROR(INDEX(Insumos_Categoria,MATCH($C7,Insumos_Ingrediente,0)),"")) -> Coberturas (30g) | C7: Granola | D7: 30 | E7: =IF($C7="","",IFERROR(INDEX(Insumos_Unidade,MATCH($C7,Insumos_Ingrediente,0)),"")) -> g | F7: =IFERROR(INDEX(Insumos_CustoUnit,MATCH($C7,Insumos_Ingrediente,0)),0) -> 0.02 | G7: =$D7*$F7 -> 0.6 | H7: =IF(OR($E7="g",$E7="ml"),$D7,0) -> 30 | I7: =IF($C7="Açaí",1,0) -> 0 | J7: =IF($C7="Banana",1,0) -> 0 | K7: =IF($C7="Whey Protein",1,0) -> 0 | L7: =IF(ISNUMBER(SEARCH("Copo",$C7)),1,0) -> 0
A8: Açaí em Ondas 200ml | B8: =IF($C8="","",IFERROR(INDEX(Insumos_Categoria,MATCH($C8,Insumos_Ingrediente,0)),"")) -> Coberturas (30g) | C8: Leite condensado | D8: 30 | E8: =IF($C8="","",IFERROR(INDEX(Insumos_Unidade,MATCH($C8,Insumos_Ingrediente,0)),"")) -> g | F8: =IFERROR(INDEX(Insumos_CustoUnit,MATCH($C8,Insumos_Ingrediente,0)),0) -> 0.01213 | G8: =$D8*$F8 -> 0.3639 | H8: =IF(OR($E8="g",$E8="ml"),$D8,0) -> 30 | I8: =IF($C8="Açaí",1,0) -> 0 | J8: =IF($C8="Banana",1,0) -> 0 | K8: =IF($C8="Whey Protein",1,0) -> 0 | L8: =IF(ISNUMBER(SEARCH("Copo",$C8)),1,0) -> 0
A9: Açaí em Ondas 200ml | B9: =IF($C9="","",IFERROR(INDEX(Insumos_Categoria,MATCH($C9,Insumos_Ingrediente,0)),"")) -> Embalagens | C9: Copo 200ml | D9: 1 | E9: =IF($C9="","",IFERROR(INDEX(Insumos_Unidade,MATCH($C9,Insumos_Ingrediente,0)),"")) -> un | F9: =IFERROR(INDEX(Insumos_CustoUnit,MATCH($C9,Insumos_Ingrediente,0)),0) -> 0.1668 | G9: =$D9*$F9 -> 0.1668 | H9: =IF(OR($E9="g",$E9="ml"),$D9,0) -> 0 | I9: =IF($C9="Açaí",1,0) -> 0 | J9: =IF($C9="Banana",1,0) -> 0 | K9: =IF($C9="Whey Protein",1,0) -> 0 | L9: =IF(ISNUMBER(SEARCH("Copo",$C9)),1,0) -> 1
A10: Açaí em Ondas 200ml | B10: =IF($C10="","",IFERROR(INDEX(Insumos_Categoria,MATCH($C10,Insumos_Ingrediente,0)),"")) -> Embalagens | C10: Tampa 200ml | D10: 1 | E10: =IF($C10="","",IFERROR(INDEX(Insumos_Unidade,MATCH($C10,Insumos_Ingrediente,0)),"")) -> un | F10: =IFERROR(INDEX(Insumos_CustoUnit,MATCH($C10,Insumos_Ingrediente,0)),0) -> 0.0823 | G10: =$D10*$F10 -> 0.0823 | H10: =IF(OR($E10="g",$E10="ml"),$D10,0) -> 0 | I10: =IF($C10="Açaí",1,0) -> 0 | J10: =IF($C10="Banana",1,0) -> 0 | K10: =IF($C10="Whey Protein",1,0) -> 0 | L10: =IF(ISNUMBER(SEARCH("Copo",$C10)),1,0) -> 0
A11: Açaí em Ondas 200ml | B11: =IF($C11="","",IFERROR(INDEX(Insumos_Categoria,MATCH($C11,Insumos_Ingrediente,0)),"")) -> Consumíveis | C11: Colher | D11: 1 | E11: =IF($C11="","",IFERROR(INDEX(Insumos_Unidade,MATCH($C11,Insumos_Ingrediente,0)),"")) -> un | F11: =IFERROR(INDEX(Insumos_CustoUnit,MATCH($C11,Insumos_Ingrediente,0)),0) -> 0.0938 | G11: =$D11*$F11 -> 0.0938 | H11: =IF(OR($E11="g",$E11="ml"),$D11,0) -> 0 | I11: =IF($C11="Açaí",1,0) -> 0 | J11: =IF($C11="Banana",1,0) -> 0 | K11: =IF($C11="Whey Protein",1,0) -> 0 | L11: =IF(ISNUMBER(SEARCH("Copo",$C11)),1,0) -> 0
A12: Açaí em Ondas 200ml | B12: =IF($C12="","",IFERROR(INDEX(Insumos_Categoria,MATCH($C12,Insumos_Ingrediente,0)),"")) -> Consumíveis | C12: Guardanapo | D12: 1 | E12: =IF($C12="","",IFERROR(INDEX(Insumos_Unidade,MATCH($C12,Insumos_Ingrediente,0)),"")) -> un | F12: =IFERROR(INDEX(Insumos_CustoUnit,MATCH($C12,Insumos_Ingrediente,0)),0) -> 0 | G12: =$D12*$F12 -> 0 | H12: =IF(OR($E12="g",$E12="ml"),$D12,0) -> 0 | I12: =IF($C12="Açaí",1,0) -> 0 | J12: =IF($C12="Banana",1,0) -> 0 | K12: =IF($C12="Whey Protein",1,0) -> 0 | L12: =IF(ISNUMBER(SEARCH("Copo",$C12)),1,0) -> 0
A13: Açaí em Ondas 300ml | B13: =IF($C13="","",IFERROR(INDEX(Insumos_Categoria,MATCH($C13,Insumos_Ingrediente,0)),"")) -> Bases (Produção Própria) | C13: Açaí | D13: 270 | E13: =IF($C13="","",IFERROR(INDEX(Insumos_Unidade,MATCH($C13,Insumos_Ingrediente,0)),"")) -> ml | F13: =IFERROR(INDEX(Insumos_CustoUnit,MATCH($C13,Insumos_Ingrediente,0)),0) -> 0.0165 | G13: =$D13*$F13 -> 4.455 | H13: =IF(OR($E13="g",$E13="ml"),$D13,0) -> 270 | I13: =IF($C13="Açaí",1,0) -> 1 | J13: =IF($C13="Banana",1,0) -> 0 | K13: =IF($C13="Whey Protein",1,0) -> 0 | L13: =IF(ISNUMBER(SEARCH("Copo",$C13)),1,0) -> 0
A14: Açaí em Ondas 300ml | B14: =IF($C14="","",IFERROR(INDEX(Insumos_Categoria,MATCH($C14,Insumos_Ingrediente,0)),"")) -> Coberturas (30g) | C14: Banana | D14: 30 | E14: =IF($C14="","",IFERROR(INDEX(Insumos_Unidade,MATCH($C14,Insumos_Ingrediente,0)),"")) -> g | F14: =IFERROR(INDEX(Insumos_CustoUnit,MATCH($C14,Insumos_Ingrediente,0)),0) -> 0.0023076923 | G14: =$D14*$F14 -> 0.069230769 | H14: =IF(OR($E14="g",$E14="ml"),$D14,0) -> 30 | I14: =IF($C14="Açaí",1,0) -> 0 | J14: =IF($C14="Banana",1,0) -> 1 | K14: =IF($C14="Whey Protein",1,0) -> 0 | L14: =IF(ISNUMBER(SEARCH("Copo",$C14)),1,0) -> 0
A15: Açaí em Ondas 300ml | B15: =IF($C15="","",IFERROR(INDEX(Insumos_Categoria,MATCH($C15,Insumos_Ingrediente,0)),"")) -> Coberturas (30g) | C15: Granola | D15: 30 | E15: =IF($C15="","",IFERROR(INDEX(Insumos_Unidade,MATCH($C15,Insumos_Ingrediente,0)),"")) -> g | F15: =IFERROR(INDEX(Insumos_CustoUnit,MATCH($C15,Insumos_Ingrediente,0)),0) -> 0.02 | G15: =$D15*$F15 -> 0.6 | H15: =IF(OR($E15="g",$E15="ml"),$D15,0) -> 30 | I15: =IF($C15="Açaí",1,0) -> 0 | J15: =IF($C15="Banana",1,0) -> 0 | K15: =IF($C15="Whey Protein",1,0) -> 0 | L15: =IF(ISNUMBER(SEARCH("Copo",$C15)),1,0) -> 0
A16: Açaí em Ondas 300ml | B16: =IF($C16="","",IFERROR(INDEX(Insumos_Categoria,MATCH($C16,Insumos_Ingrediente,0)),"")) -> Coberturas (30g) | C16: Leite condensado | D16: 30 | E16: =IF($C16="","",IFERROR(INDEX(Insumos_Unidade,MATCH($C16,Insumos_Ingrediente,0)),"")) -> g | F16: =IFERROR(INDEX(Insumos_CustoUnit,MATCH($C16,Insumos_Ingrediente,0)),0) -> 0.01213 | G16: =$D16*$F16 -> 0.3639 | H16: =IF(OR($E16="g",$E16="ml"),$D16,0) -> 30 | I16: =IF($C16="Açaí",1,0) -> 0 | J16: =IF($C16="Banana",1,0) -> 0 | K16: =IF($C16="Whey Protein",1,0) -> 0 | L16: =IF(ISNUMBER(SEARCH("Copo",$C16)),1,0) -> 0
... A373: Suco de Açaí 200ml | B373: =IF($C373="","",IFERROR(INDEX(Insumos_Categoria,MATCH($C373,Insumos_Ingrediente,0)),"")) -> Consumíveis | C373: Guardanapo | D373: 1 | E373: =IF($C373="","",IFERROR(INDEX(Insumos_Unidade,MATCH($C373,Insumos_Ingrediente,0)),"")) -> un | F373: =IFERROR(INDEX(Insumos_CustoUnit,MATCH($C373,Insumos_Ingrediente,0)),0) -> 0 | G373: =$D373*$F373 -> 0 | H373: =IF(OR($E373="g",$E373="ml"),$D373,0) -> 0 | I373: =IF($C373="Açaí",1,0) -> 0 | J373: =IF($C373="Banana",1,0) -> 0 | K373: =IF($C373="Whey Protein",1,0) -> 0 | L373: =IF(ISNUMBER(SEARCH("Copo",$C373)),1,0) -> 0
B374: =IF($C374="","",IFERROR(INDEX(Insumos_Categoria,MATCH($C374,Insumos_Ingrediente,0)),"")) | E374: =IF($C374="","",IFERROR(INDEX(Insumos_Unidade,MATCH($C374,Insumos_Ingrediente,0)),"")) | F374: =IFERROR(INDEX(Insumos_CustoUnit,MATCH($C374,Insumos_Ingrediente,0)),0) -> 0 | G374: =$D374*$F374 -> 0 | H374: =IF(OR($E374="g",$E374="ml"),$D374,0) -> 0 | I374: =IF($C374="Açaí",1,0) -> 0 | J374: =IF($C374="Banana",1,0) -> 0 | K374: =IF($C374="Whey Protein",1,0) -> 0 | L374: =IF(ISNUMBER(SEARCH("Copo",$C374)),1,0) -> 0
B375: =IF($C375="","",IFERROR(INDEX(Insumos_Categoria,MATCH($C375,Insumos_Ingrediente,0)),"")) | E375: =IF($C375="","",IFERROR(INDEX(Insumos_Unidade,MATCH($C375,Insumos_Ingrediente,0)),"")) | F375: =IFERROR(INDEX(Insumos_CustoUnit,MATCH($C375,Insumos_Ingrediente,0)),0) -> 0 | G375: =$D375*$F375 -> 0 | H375: =IF(OR($E375="g",$E375="ml"),$D375,0) -> 0 | I375: =IF($C375="Açaí",1,0) -> 0 | J375: =IF($C375="Banana",1,0) -> 0 | K375: =IF($C375="Whey Protein",1,0) -> 0 | L375: =IF(ISNUMBER(SEARCH("Copo",$C375)),1,0) -> 0
B376: =IF($C376="","",IFERROR(INDEX(Insumos_Categoria,MATCH($C376,Insumos_Ingrediente,0)),"")) | E376: =IF($C376="","",IFERROR(INDEX(Insumos_Unidade,MATCH($C376,Insumos_Ingrediente,0)),"")) | F376: =IFERROR(INDEX(Insumos_CustoUnit,MATCH($C376,Insumos_Ingrediente,0)),0) -> 0 | G376: =$D376*$F376 -> 0 | H376: =IF(OR($E376="g",$E376="ml"),$D376,0) -> 0 | I376: =IF($C376="Açaí",1,0) -> 0 | J376: =IF($C376="Banana",1,0) -> 0 | K376: =IF($C376="Whey Protein",1,0) -> 0 | L376: =IF(ISNUMBER(SEARCH("Copo",$C376)),1,0) -> 0
B377: =IF($C377="","",IFERROR(INDEX(Insumos_Categoria,MATCH($C377,Insumos_Ingrediente,0)),"")) | E377: =IF($C377="","",IFERROR(INDEX(Insumos_Unidade,MATCH($C377,Insumos_Ingrediente,0)),"")) | F377: =IFERROR(INDEX(Insumos_CustoUnit,MATCH($C377,Insumos_Ingrediente,0)),0) -> 0 | G377: =$D377*$F377 -> 0 | H377: =IF(OR($E377="g",$E377="ml"),$D377,0) -> 0 | I377: =IF($C377="Açaí",1,0) -> 0 | J377: =IF($C377="Banana",1,0) -> 0 | K377: =IF($C377="Whey Protein",1,0) -> 0 | L377: =IF(ISNUMBER(SEARCH("Copo",$C377)),1,0) -> 0
B378: =IF($C378="","",IFERROR(INDEX(Insumos_Categoria,MATCH($C378,Insumos_Ingrediente,0)),"")) | E378: =IF($C378="","",IFERROR(INDEX(Insumos_Unidade,MATCH($C378,Insumos_Ingrediente,0)),"")) | F378: =IFERROR(INDEX(Insumos_CustoUnit,MATCH($C378,Insumos_Ingrediente,0)),0) -> 0 | G378: =$D378*$F378 -> 0 | H378: =IF(OR($E378="g",$E378="ml"),$D378,0) -> 0 | I378: =IF($C378="Açaí",1,0) -> 0 | J378: =IF($C378="Banana",1,0) -> 0 | K378: =IF($C378="Whey Protein",1,0) -> 0 | L378: =IF(ISNUMBER(SEARCH("Copo",$C378)),1,0) -> 0
B379: =IF($C379="","",IFERROR(INDEX(Insumos_Categoria,MATCH($C379,Insumos_Ingrediente,0)),"")) | E379: =IF($C379="","",IFERROR(INDEX(Insumos_Unidade,MATCH($C379,Insumos_Ingrediente,0)),"")) | F379: =IFERROR(INDEX(Insumos_CustoUnit,MATCH($C379,Insumos_Ingrediente,0)),0) -> 0 | G379: =$D379*$F379 -> 0 | H379: =IF(OR($E379="g",$E379="ml"),$D379,0) -> 0 | I379: =IF($C379="Açaí",1,0) -> 0 | J379: =IF($C379="Banana",1,0) -> 0 | K379: =IF($C379="Whey Protein",1,0) -> 0 | L379: =IF(ISNUMBER(SEARCH("Copo",$C379)),1,0) -> 0
B380: =IF($C380="","",IFERROR(INDEX(Insumos_Categoria,MATCH($C380,Insumos_Ingrediente,0)),"")) | E380: =IF($C380="","",IFERROR(INDEX(Insumos_Unidade,MATCH($C380,Insumos_Ingrediente,0)),"")) | F380: =IFERROR(INDEX(Insumos_CustoUnit,MATCH($C380,Insumos_Ingrediente,0)),0) -> 0 | G380: =$D380*$F380 -> 0 | H380: =IF(OR($E380="g",$E380="ml"),$D380,0) -> 0 | I380: =IF($C380="Açaí",1,0) -> 0 | J380: =IF($C380="Banana",1,0) -> 0 | K380: =IF($C380="Whey Protein",1,0) -> 0 | L380: =IF(ISNUMBER(SEARCH("Copo",$C380)),1,0) -> 0
B381: =IF($C381="","",IFERROR(INDEX(Insumos_Categoria,MATCH($C381,Insumos_Ingrediente,0)),"")) | E381: =IF($C381="","",IFERROR(INDEX(Insumos_Unidade,MATCH($C381,Insumos_Ingrediente,0)),"")) | F381: =IFERROR(INDEX(Insumos_CustoUnit,MATCH($C381,Insumos_Ingrediente,0)),0) -> 0 | G381: =$D381*$F381 -> 0 | H381: =IF(OR($E381="g",$E381="ml"),$D381,0) -> 0 | I381: =IF($C381="Açaí",1,0) -> 0 | J381: =IF($C381="Banana",1,0) -> 0 | K381: =IF($C381="Whey Protein",1,0) -> 0 | L381: =IF(ISNUMBER(SEARCH("Copo",$C381)),1,0) -> 0
B382: =IF($C382="","",IFERROR(INDEX(Insumos_Categoria,MATCH($C382,Insumos_Ingrediente,0)),"")) | E382: =IF($C382="","",IFERROR(INDEX(Insumos_Unidade,MATCH($C382,Insumos_Ingrediente,0)),"")) | F382: =IFERROR(INDEX(Insumos_CustoUnit,MATCH($C382,Insumos_Ingrediente,0)),0) -> 0 | G382: =$D382*$F382 -> 0 | H382: =IF(OR($E382="g",$E382="ml"),$D382,0) -> 0 | I382: =IF($C382="Açaí",1,0) -> 0 | J382: =IF($C382="Banana",1,0) -> 0 | K382: =IF($C382="Whey Protein",1,0) -> 0 | L382: =IF(ISNUMBER(SEARCH("Copo",$C382)),1,0) -> 0
B383: =IF($C383="","",IFERROR(INDEX(Insumos_Categoria,MATCH($C383,Insumos_Ingrediente,0)),"")) | E383: =IF($C383="","",IFERROR(INDEX(Insumos_Unidade,MATCH($C383,Insumos_Ingrediente,0)),"")) | F383: =IFERROR(INDEX(Insumos_CustoUnit,MATCH($C383,Insumos_Ingrediente,0)),0) -> 0 | G383: =$D383*$F383 -> 0 | H383: =IF(OR($E383="g",$E383="ml"),$D383,0) -> 0 | I383: =IF($C383="Açaí",1,0) -> 0 | J383: =IF($C383="Banana",1,0) -> 0 | K383: =IF($C383="Whey Protein",1,0) -> 0 | L383: =IF(ISNUMBER(SEARCH("Copo",$C383)),1,0) -> 0
B384: =IF($C384="","",IFERROR(INDEX(Insumos_Categoria,MATCH($C384,Insumos_Ingrediente,0)),"")) | E384: =IF($C384="","",IFERROR(INDEX(Insumos_Unidade,MATCH($C384,Insumos_Ingrediente,0)),"")) | F384: =IFERROR(INDEX(Insumos_CustoUnit,MATCH($C384,Insumos_Ingrediente,0)),0) -> 0 | G384: =$D384*$F384 -> 0 | H384: =IF(OR($E384="g",$E384="ml"),$D384,0) -> 0 | I384: =IF($C384="Açaí",1,0) -> 0 | J384: =IF($C384="Banana",1,0) -> 0 | K384: =IF($C384="Whey Protein",1,0) -> 0 | L384: =IF(ISNUMBER(SEARCH("Copo",$C384)),1,0) -> 0
B385: =IF($C385="","",IFERROR(INDEX(Insumos_Categoria,MATCH($C385,Insumos_Ingrediente,0)),"")) | E385: =IF($C385="","",IFERROR(INDEX(Insumos_Unidade,MATCH($C385,Insumos_Ingrediente,0)),"")) | F385: =IFERROR(INDEX(Insumos_CustoUnit,MATCH($C385,Insumos_Ingrediente,0)),0) -> 0 | G385: =$D385*$F385 -> 0 | H385: =IF(OR($E385="g",$E385="ml"),$D385,0) -> 0 | I385: =IF($C385="Açaí",1,0) -> 0 | J385: =IF($C385="Banana",1,0) -> 0 | K385: =IF($C385="Whey Protein",1,0) -> 0 | L385: =IF(ISNUMBER(SEARCH("Copo",$C385)),1,0) -> 0
... B480: =IF($C480="","",IFERROR(INDEX(Insumos_Categoria,MATCH($C480,Insumos_Ingrediente,0)),"")) | E480: =IF($C480="","",IFERROR(INDEX(Insumos_Unidade,MATCH($C480,Insumos_Ingrediente,0)),"")) | F480: =IFERROR(INDEX(Insumos_CustoUnit,MATCH($C480,Insumos_Ingrediente,0)),0) -> 0 | G480: =$D480*$F480 -> 0 | H480: =IF(OR($E480="g",$E480="ml"),$D480,0) -> 0 | I480: =IF($C480="Açaí",1,0) -> 0 | J480: =IF($C480="Banana",1,0) -> 0 | K480: =IF($C480="Whey Protein",1,0) -> 0 | L480: =IF(ISNUMBER(SEARCH("Copo",$C480)),1,0) -> 0

Sheet Receitas
A1: 🧾 RECEITAS — Preço do Cardápio x Custo Real de Cada Produto
A2: 'Preço Praticado' já vem preenchido com o valor do seu cardápio — pode ajustar se mudar. As demais colunas calculam sozinhas, usando a loja selecionada em Configurações (célula B13).
A4: Produto | B4: Grupo (Cardápio) | C4: Preço Praticado (R$) | D4: Peso Total (g/ml) | E4: Custo Insumos (R$) | F4: Custo Insumos c/ Perdas (R$) | G4: Custo Fixo Rateado (R$) | H4: Custo Total Unitário (R$) | I4: Preço Sugerido (R$) | J4: CMV Real (%) | K4: Margem Real (%) | L4: Lucro Líquido Real (R$) | M4: Praticado − Sugerido (R$) | N4: Status
A5: Açaí em Ondas 200ml | B5: Açaí em Ondas & Receitas Fast | C5: 16.9 | D5: =IF($A5="","",SUMIFS(FichaTecnica_QtdGML,FichaTecnica_Produto,$A5)) -> 260 | E5: =IF($A5="","",SUMIFS(FichaTecnica_CustoTotal,FichaTecnica_Produto,$A5)) -> 4.1810308 | F5: =IF($A5="","",IFERROR($E5/(1-Perdas),$E5)) -> 4.310341 | G5: =IF($A5="","",IFERROR(INDEX(Rateio_CustoFixoPorVendaLinha,MATCH(LojaSelecionada,Rateio_LojasHeader,0)),0)) -> 7.4082778 | H5: =IF($A5="","",$F5+$G5) -> 11.718619 | I5: =IF($A5="","",IFERROR($H5/(1-MargemLiquidaDesejada-Impostos-TaxaCartao-Comissao),"Ajustar parâmetros")) -> 18.168401 | J5: =IF(OR($A5="",$C5=""),"",IFERROR($F5/$C5,"")) -> 0.25504976 | K5: =IF(OR($A5="",$C5=""),"",IFERROR(($C5-$H5-$C5*(Impostos+TaxaCartao+Comissao))/$C5,"")) -> 0.1015906 | L5: =IF(OR($A5="",$C5=""),"",$C5-$H5-$C5*(Impostos+TaxaCartao+Comissao)) -> 1.7168812 | M5: =IF(OR($A5="",$C5="",NOT(ISNUMBER($I5))),"",$C5-$I5) -> -1.2684012 | N5: =IF(OR($A5="",$K5=""),"",IF($K5>=MargemLiquidaDesejada,"🟢 Margem Saudável",IF($K5>=MargemLiquidaDesejada*0.8,"🟡 Atenção","🔴 Abaixo da Meta"))) -> 🔴 Abaixo da Meta
A6: Açaí em Ondas 300ml | B6: Açaí em Ondas & Receitas Fast | C6: 22.9 | D6: =IF($A6="","",SUMIFS(FichaTecnica_QtdGML,FichaTecnica_Produto,$A6)) -> 360 | E6: =IF($A6="","",SUMIFS(FichaTecnica_CustoTotal,FichaTecnica_Produto,$A6)) -> 5.8179508 | F6: =IF($A6="","",IFERROR($E6/(1-Perdas),$E6)) -> 5.9978874 | G6: =IF($A6="","",IFERROR(INDEX(Rateio_CustoFixoPorVendaLinha,MATCH(LojaSelecionada,Rateio_LojasHeader,0)),0)) -> 7.4082778 | H6: =IF($A6="","",$F6+$G6) -> 13.406165 | I6: =IF($A6="","",IFERROR($H6/(1-MargemLiquidaDesejada-Impostos-TaxaCartao-Comissao),"Ajustar parâmetros")) -> 20.784752 | J6: =IF(OR($A6="",$C6=""),"",IFERROR($F6/$C6,"")) -> 0.26191648 | K6: =IF(OR($A6="",$C6=""),"",IFERROR(($C6-$H6-$C6*(Impostos+TaxaCartao+Comissao))/$C6,"")) -> 0.20957794 | L6: =IF(OR($A6="",$C6=""),"",$C6-$H6-$C6*(Impostos+TaxaCartao+Comissao)) -> 4.7993348 | M6: =IF(OR($A6="",$C6="",NOT(ISNUMBER($I6))),"",$C6-$I6) -> 2.1152478 | N6: =IF(OR($A6="",$K6=""),"",IF($K6>=MargemLiquidaDesejada,"🟢 Margem Saudável",IF($K6>=MargemLiquidaDesejada*0.8,"🟡 Atenção","🔴 Abaixo da Meta"))) -> 🟢 Margem Saudável
A7: Açaí em Ondas 500ml | B7: Açaí em Ondas & Receitas Fast | C7: 29.9 | D7: =IF($A7="","",SUMIFS(FichaTecnica_QtdGML,FichaTecnica_Produto,$A7)) -> 560 | E7: =IF($A7="","",SUMIFS(FichaTecnica_CustoTotal,FichaTecnica_Produto,$A7)) -> 9.2178808 | F7: =IF($A7="","",IFERROR($E7/(1-Perdas),$E7)) -> 9.5029699 | G7: =IF($A7="","",IFERROR(INDEX(Rateio_CustoFixoPorVendaLinha,MATCH(LojaSelecionada,Rateio_LojasHeader,0)),0)) -> 7.4082778 | H7: =IF($A7="","",$F7+$G7) -> 16.911248 | I7: =IF($A7="","",IFERROR($H7/(1-MargemLiquidaDesejada-Impostos-TaxaCartao-Comissao),"Ajustar parâmetros")) -> 26.218989 | J7: =IF(OR($A7="",$C7=""),"",IFERROR($F7/$C7,"")) -> 0.31782508 | K7: =IF(OR($A7="",$C7=""),"",IFERROR(($C7-$H7-$C7*(Impostos+TaxaCartao+Comissao))/$C7,"")) -> 0.22940643 | L7: =IF(OR($A7="",$C7=""),"",$C7-$H7-$C7*(Impostos+TaxaCartao+Comissao)) -> 6.8592524 | M7: =IF(OR($A7="",$C7="",NOT(ISNUMBER($I7))),"",$C7-$I7) -> 3.6810114 | N7: =IF(OR($A7="",$K7=""),"",IF($K7>=MargemLiquidaDesejada,"🟢 Margem Saudável",IF($K7>=MargemLiquidaDesejada*0.8,"🟡 Atenção","🔴 Abaixo da Meta"))) -> 🟢 Margem Saudável
A8: Fast Classic 200ml | B8: Açaí em Ondas & Receitas Fast | C8: 16.9 | D8: =IF($A8="","",SUMIFS(FichaTecnica_QtdGML,FichaTecnica_Produto,$A8)) -> 290 | E8: =IF($A8="","",SUMIFS(FichaTecnica_CustoTotal,FichaTecnica_Produto,$A8)) -> 5.1875308 | F8: =IF($A8="","",IFERROR($E8/(1-Perdas),$E8)) -> 5.3479699 | G8: =IF($A8="","",IFERROR(INDEX(Rateio_CustoFixoPorVendaLinha,MATCH(LojaSelecionada,Rateio_LojasHeader,0)),0)) -> 7.4082778 | H8: =IF($A8="","",$F8+$G8) -> 12.756248 | I8: =IF($A8="","",IFERROR($H8/(1-MargemLiquidaDesejada-Impostos-TaxaCartao-Comissao),"Ajustar parâmetros")) -> 19.777128 | J8: =IF(OR($A8="",$C8=""),"",IFERROR($F8/$C8,"")) -> 0.31644792 | K8: =IF(OR($A8="",$C8=""),"",IFERROR(($C8-$H8-$C8*(Impostos+TaxaCartao+Comissao))/$C8,"")) -> 0.040192447 | L8: =IF(OR($A8="",$C8=""),"",$C8-$H8-$C8*(Impostos+TaxaCartao+Comissao)) -> 0.67925236 | M8: =IF(OR($A8="",$C8="",NOT(ISNUMBER($I8))),"",$C8-$I8) -> -2.8771281 | N8: =IF(OR($A8="",$K8=""),"",IF($K8>=MargemLiquidaDesejada,"🟢 Margem Saudável",IF($K8>=MargemLiquidaDesejada*0.8,"🟡 Atenção","🔴 Abaixo da Meta"))) -> 🔴 Abaixo da Meta
A9: Fast Classic 300ml | B9: Açaí em Ondas & Receitas Fast | C9: 22.9 | D9: =IF($A9="","",SUMIFS(FichaTecnica_QtdGML,FichaTecnica_Produto,$A9)) -> 390 | E9: =IF($A9="","",SUMIFS(FichaTecnica_CustoTotal,FichaTecnica_Produto,$A9)) -> 6.8244508 | F9: =IF($A9="","",IFERROR($E9/(1-Perdas),$E9)) -> 7.0355163 | G9: =IF($A9="","",IFERROR(INDEX(Rateio_CustoFixoPorVendaLinha,MATCH(LojaSelecionada,Rateio_LojasHeader,0)),0)) -> 7.4082778 | H9: =IF($A9="","",$F9+$G9) -> 14.443794 | I9: =IF($A9="","",IFERROR($H9/(1-MargemLiquidaDesejada-Impostos-TaxaCartao-Comissao),"Ajustar parâmetros")) -> 22.393479 | J9: =IF(OR($A9="",$C9=""),"",IFERROR($F9/$C9,"")) -> 0.30722778 | K9: =IF(OR($A9="",$C9=""),"",IFERROR(($C9-$H9-$C9*(Impostos+TaxaCartao+Comissao))/$C9,"")) -> 0.16426664 | L9: =IF(OR($A9="",$C9=""),"",$C9-$H9-$C9*(Impostos+TaxaCartao+Comissao)) -> 3.761706 | M9: =IF(OR($A9="",$C9="",NOT(ISNUMBER($I9))),"",$C9-$I9) -> 0.50652088 | N9: =IF(OR($A9="",$K9=""),"",IF($K9>=MargemLiquidaDesejada,"🟢 Margem Saudável",IF($K9>=MargemLiquidaDesejada*0.8,"🟡 Atenção","🔴 Abaixo da Meta"))) -> 🟢 Margem Saudável
A10: Fast Classic 500ml | B10: Açaí em Ondas & Receitas Fast | C10: 29.9 | D10: =IF($A10="","",SUMIFS(FichaTecnica_QtdGML,FichaTecnica_Produto,$A10)) -> 590 | E10: =IF($A10="","",SUMIFS(FichaTecnica_CustoTotal,FichaTecnica_Produto,$A10)) -> 10.224381 | F10: =IF($A10="","",IFERROR($E10/(1-Perdas),$E10)) -> 10.540599 | G10: =IF($A10="","",IFERROR(INDEX(Rateio_CustoFixoPorVendaLinha,MATCH(LojaSelecionada,Rateio_LojasHeader,0)),0)) -> 7.4082778 | H10: =IF($A10="","",$F10+$G10) -> 17.948877 | I10: =IF($A10="","",IFERROR($H10/(1-MargemLiquidaDesejada-Impostos-TaxaCartao-Comissao),"Ajustar parâmetros")) -> 27.827716 | J10: =IF(OR($A10="",$C10=""),"",IFERROR($F10/$C10,"")) -> 0.35252839 | K10: =IF(OR($A10="",$C10=""),"",IFERROR(($C10-$H10-$C10*(Impostos+TaxaCartao+Comissao))/$C10,"")) -> 0.19470313 | L10: =IF(OR($A10="",$C10=""),"",$C10-$H10-$C10*(Impostos+TaxaCartao+Comissao)) -> 5.8216235 | M10: =IF(OR($A10="",$C10="",NOT(ISNUMBER($I10))),"",$C10-$I10) -> 2.0722845 | N10: =IF(OR($A10="",$K10=""),"",IF($K10>=MargemLiquidaDesejada,"🟢 Margem Saudável",IF($K10>=MargemLiquidaDesejada*0.8,"🟡 Atenção","🔴 Abaixo da Meta"))) -> 🟢 Margem Saudável
A11: Power 200ml | B11: Açaí em Ondas & Receitas Fast | C11: 16.9 | D11: =IF($A11="","",SUMIFS(FichaTecnica_QtdGML,FichaTecnica_Produto,$A11)) -> 290 | E11: =IF($A11="","",SUMIFS(FichaTecnica_CustoTotal,FichaTecnica_Produto,$A11)) -> 4.8509308 | F11: =IF($A11="","",IFERROR($E11/(1-Perdas),$E11)) -> 5.0009596 | G11: =IF($A11="","",IFERROR(INDEX(Rateio_CustoFixoPorVendaLinha,MATCH(LojaSelecionada,Rateio_LojasHeader,0)),0)) -> 7.4082778 | H11: =IF($A11="","",$F11+$G11) -> 12.409237 | I11: =IF($A11="","",IFERROR($H11/(1-MargemLiquidaDesejada-Impostos-TaxaCartao-Comissao),"Ajustar parâmetros")) -> 19.239128 | J11: =IF(OR($A11="",$C11=""),"",IFERROR($F11/$C11,"")) -> 0.29591477 | K11: =IF(OR($A11="",$C11=""),"",IFERROR(($C11-$H11-$C11*(Impostos+TaxaCartao+Comissao))/$C11,"")) -> 0.060725602 | L11: =IF(OR($A11="",$C11=""),"",$C11-$H11-$C11*(Impostos+TaxaCartao+Comissao)) -> 1.0262627 | M11: =IF(OR($A11="",$C11="",NOT(ISNUMBER($I11))),"",$C11-$I11) -> -2.3391276 | N11: =IF(OR($A11="",$K11=""),"",IF($K11>=MargemLiquidaDesejada,"🟢 Margem Saudável",IF($K11>=MargemLiquidaDesejada*0.8,"🟡 Atenção","🔴 Abaixo da Meta"))) -> 🔴 Abaixo da Meta
A12: Power 300ml | B12: Açaí em Ondas & Receitas Fast | C12: 22.9 | D12: =IF($A12="","",SUMIFS(FichaTecnica_QtdGML,FichaTecnica_Produto,$A12)) -> 390 | E12: =IF($A12="","",SUMIFS(FichaTecnica_CustoTotal,FichaTecnica_Produto,$A12)) -> 6.4878508 | F12: =IF($A12="","",IFERROR($E12/(1-Perdas),$E12)) -> 6.6885059 | G12: =IF($A12="","",IFERROR(INDEX(Rateio_CustoFixoPorVendaLinha,MATCH(LojaSelecionada,Rateio_LojasHeader,0)),0)) -> 7.4082778 | H12: =IF($A12="","",$F12+$G12) -> 14.096784 | I12: =IF($A12="","",IFERROR($H12/(1-MargemLiquidaDesejada-Impostos-TaxaCartao-Comissao),"Ajustar parâmetros")) -> 21.855479 | J12: =IF(OR($A12="",$C12=""),"",IFERROR($F12/$C12,"")) -> 0.2920745 | K12: =IF(OR($A12="",$C12=""),"",IFERROR(($C12-$H12-$C12*(Impostos+TaxaCartao+Comissao))/$C12,"")) -> 0.17941992 | L12: =IF(OR($A12="",$C12=""),"",$C12-$H12-$C12*(Impostos+TaxaCartao+Comissao)) -> 4.1087163 | M12: =IF(OR($A12="",$C12="",NOT(ISNUMBER($I12))),"",$C12-$I12) -> 1.0445214 | N12: =IF(OR($A12="",$K12=""),"",IF($K12>=MargemLiquidaDesejada,"🟢 Margem Saudável",IF($K12>=MargemLiquidaDesejada*0.8,"🟡 Atenção","🔴 Abaixo da Meta"))) -> 🟢 Margem Saudável
A13: Power 500ml | B13: Açaí em Ondas & Receitas Fast | C13: 29.9 | D13: =IF($A13="","",SUMIFS(FichaTecnica_QtdGML,FichaTecnica_Produto,$A13)) -> 590 | E13: =IF($A13="","",SUMIFS(FichaTecnica_CustoTotal,FichaTecnica_Produto,$A13)) -> 9.8877808 | F13: =IF($A13="","",IFERROR($E13/(1-Perdas),$E13)) -> 10.193588 | G13: =IF($A13="","",IFERROR(INDEX(Rateio_CustoFixoPorVendaLinha,MATCH(LojaSelecionada,Rateio_LojasHeader,0)),0)) -> 7.4082778 | H13: =IF($A13="","",$F13+$G13) -> 17.601866 | I13: =IF($A13="","",IFERROR($H13/(1-MargemLiquidaDesejada-Impostos-TaxaCartao-Comissao),"Ajustar parâmetros")) -> 27.289715 | J13: =IF(OR($A13="",$C13=""),"",IFERROR($F13/$C13,"")) -> 0.34092269 | K13: =IF(OR($A13="",$C13=""),"",IFERROR(($C13-$H13-$C13*(Impostos+TaxaCartao+Comissao))/$C13,"")) -> 0.20630882 | L13: =IF(OR($A13="",$C13=""),"",$C13-$H13-$C13*(Impostos+TaxaCartao+Comissao)) -> 6.1686338 | M13: =IF(OR($A13="",$C13="",NOT(ISNUMBER($I13))),"",$C13-$I13) -> 2.610285 | N13: =IF(OR($A13="",$K13=""),"",IF($K13>=MargemLiquidaDesejada,"🟢 Margem Saudável",IF($K13>=MargemLiquidaDesejada*0.8,"🟡 Atenção","🔴 Abaixo da Meta"))) -> 🟢 Margem Saudável
A14: Choco Nuts 200ml | B14: Açaí em Ondas & Receitas Fast | C14: 16.9 | D14: =IF($A14="","",SUMIFS(FichaTecnica_QtdGML,FichaTecnica_Produto,$A14)) -> 290 | E14: =IF($A14="","",SUMIFS(FichaTecnica_CustoTotal,FichaTecnica_Produto,$A14)) -> 5.5371 | F14: =IF($A14="","",IFERROR($E14/(1-Perdas),$E14)) -> 5.7083505 | G14: =IF($A14="","",IFERROR(INDEX(Rateio_CustoFixoPorVendaLinha,MATCH(LojaSelecionada,Rateio_LojasHeader,0)),0)) -> 7.4082778 | H14: =IF($A14="","",$F14+$G14) -> 13.116628 | I14: =IF($A14="","",IFERROR($H14/(1-MargemLiquidaDesejada-Impostos-TaxaCartao-Comissao),"Ajustar parâmetros")) -> 20.335858 | J14: =IF(OR($A14="",$C14=""),"",IFERROR($F14/$C14,"")) -> 0.33777222 | K14: =IF(OR($A14="",$C14=""),"",IFERROR(($C14-$H14-$C14*(Impostos+TaxaCartao+Comissao))/$C14,"")) -> 0.018868148 | L14: =IF(OR($A14="",$C14=""),"",$C14-$H14-$C14*(Impostos+TaxaCartao+Comissao)) -> 0.31887171 | M14: =IF(OR($A14="",$C14="",NOT(ISNUMBER($I14))),"",$C14-$I14) -> -3.4358578 | N14: =IF(OR($A14="",$K14=""),"",IF($K14>=MargemLiquidaDesejada,"🟢 Margem Saudável",IF($K14>=MargemLiquidaDesejada*0.8,"🟡 Atenção","🔴 Abaixo da Meta"))) -> 🔴 Abaixo da Meta
A15: Choco Nuts 300ml | B15: Açaí em Ondas & Receitas Fast | C15: 22.9 | D15: =IF($A15="","",SUMIFS(FichaTecnica_QtdGML,FichaTecnica_Produto,$A15)) -> 390 | E15: =IF($A15="","",SUMIFS(FichaTecnica_CustoTotal,FichaTecnica_Produto,$A15)) -> 7.17402 | F15: =IF($A15="","",IFERROR($E15/(1-Perdas),$E15)) -> 7.3958969 | G15: =IF($A15="","",IFERROR(INDEX(Rateio_CustoFixoPorVendaLinha,MATCH(LojaSelecionada,Rateio_LojasHeader,0)),0)) -> 7.4082778 | H15: =IF($A15="","",$F15+$G15) -> 14.804175 | I15: =IF($A15="","",IFERROR($H15/(1-MargemLiquidaDesejada-Impostos-TaxaCartao-Comissao),"Ajustar parâmetros")) -> 22.952209 | J15: =IF(OR($A15="",$C15=""),"",IFERROR($F15/$C15,"")) -> 0.32296493 | K15: =IF(OR($A15="",$C15=""),"",IFERROR(($C15-$H15-$C15*(Impostos+TaxaCartao+Comissao))/$C15,"")) -> 0.14852949 | L15: =IF(OR($A15="",$C15=""),"",$C15-$H15-$C15*(Impostos+TaxaCartao+Comissao)) -> 3.4013253 | M15: =IF(OR($A15="",$C15="",NOT(ISNUMBER($I15))),"",$C15-$I15) -> -0.052208814 | N15: =IF(OR($A15="",$K15=""),"",IF($K15>=MargemLiquidaDesejada,"🟢 Margem Saudável",IF($K15>=MargemLiquidaDesejada*0.8,"🟡 Atenção","🔴 Abaixo da Meta"))) -> 🟡 Atenção
A16: Choco Nuts 500ml | B16: Açaí em Ondas & Receitas Fast | C16: 29.9 | D16: =IF($A16="","",SUMIFS(FichaTecnica_QtdGML,FichaTecnica_Produto,$A16)) -> 590 | E16: =IF($A16="","",SUMIFS(FichaTecnica_CustoTotal,FichaTecnica_Produto,$A16)) -> 10.57395 | F16: =IF($A16="","",IFERROR($E16/(1-Perdas),$E16)) -> 10.900979 | G16: =IF($A16="","",IFERROR(INDEX(Rateio_CustoFixoPorVendaLinha,MATCH(LojaSelecionada,Rateio_LojasHeader,0)),0)) -> 7.4082778 | H16: =IF($A16="","",$F16+$G16) -> 18.309257 | I16: =IF($A16="","",IFERROR($H16/(1-MargemLiquidaDesejada-Impostos-TaxaCartao-Comissao),"Ajustar parâmetros")) -> 28.386445 | J16: =IF(OR($A16="",$C16=""),"",IFERROR($F16/$C16,"")) -> 0.36458125 | K16: =IF(OR($A16="",$C16=""),"",IFERROR(($C16-$H16-$C16*(Impostos+TaxaCartao+Comissao))/$C16,"")) -> 0.18265026 | L16: =IF(OR($A16="",$C16=""),"",$C16-$H16-$C16*(Impostos+TaxaCartao+Comissao)) -> 5.4612428 | M16: =IF(OR($A16="",$C16="",NOT(ISNUMBER($I16))),"",$C16-$I16) -> 1.5135548 | N16: =IF(OR($A16="",$K16=""),"",IF($K16>=MargemLiquidaDesejada,"🟢 Margem Saudável",IF($K16>=MargemLiquidaDesejada*0.8,"🟡 Atenção","🔴 Abaixo da Meta"))) -> 🟢 Margem Saudável
... A34: Nuts Protein 500ml | B34: Açaí em Ondas & Receitas Fast | C34: 29.9 | D34: =IF($A34="","",SUMIFS(FichaTecnica_QtdGML,FichaTecnica_Produto,$A34)) -> 560 | E34: =IF($A34="","",SUMIFS(FichaTecnica_CustoTotal,FichaTecnica_Produto,$A34)) -> 8.2539808 | F34: =IF($A34="","",IFERROR($E34/(1-Perdas),$E34)) -> 8.5092585 | G34: =IF($A34="","",IFERROR(INDEX(Rateio_CustoFixoPorVendaLinha,MATCH(LojaSelecionada,Rateio_LojasHeader,0)),0)) -> 7.4082778 | H34: =IF($A34="","",$F34+$G34) -> 15.917536 | I34: =IF($A34="","",IFERROR($H34/(1-MargemLiquidaDesejada-Impostos-TaxaCartao-Comissao),"Ajustar parâmetros")) -> 24.678351 | J34: =IF(OR($A34="",$C34=""),"",IFERROR($F34/$C34,"")) -> 0.28459059 | K34: =IF(OR($A34="",$C34=""),"",IFERROR(($C34-$H34-$C34*(Impostos+TaxaCartao+Comissao))/$C34,"")) -> 0.26264093 | L34: =IF(OR($A34="",$C34=""),"",$C34-$H34-$C34*(Impostos+TaxaCartao+Comissao)) -> 7.8529637 | M34: =IF(OR($A34="",$C34="",NOT(ISNUMBER($I34))),"",$C34-$I34) -> 5.2216491 | N34: =IF(OR($A34="",$K34=""),"",IF($K34>=MargemLiquidaDesejada,"🟢 Margem Saudável",IF($K34>=MargemLiquidaDesejada*0.8,"🟡 Atenção","🔴 Abaixo da Meta"))) -> 🟢 Margem Saudável
A35: Açaí Zero Açúcar 250ml | B35: Linha Premium | C35: 23 | D35: 250 | E35: =IF($A35="","",SUMIFS(FichaTecnica_CustoTotal,FichaTecnica_Produto,$A35)) -> 12.0938 | F35: =IF($A35="","",IFERROR($E35/(1-Perdas),$E35)) -> 12.467835 | G35: =IF($A35="","",IFERROR(INDEX(Rateio_CustoFixoPorVendaLinha,MATCH(LojaSelecionada,Rateio_LojasHeader,0)),0)) -> 7.4082778 | H35: =IF($A35="","",$F35+$G35) -> 19.876113 | I35: =IF($A35="","",IFERROR($H35/(1-MargemLiquidaDesejada-Impostos-TaxaCartao-Comissao),"Ajustar parâmetros")) -> 30.815679 | J35: =IF(OR($A35="",$C35=""),"",IFERROR($F35/$C35,"")) -> 0.54207978 | K35: =IF(OR($A35="",$C35=""),"",IFERROR(($C35-$H35-$C35*(Impostos+TaxaCartao+Comissao))/$C35,"")) -> -0.069178819 | L35: =IF(OR($A35="",$C35=""),"",$C35-$H35-$C35*(Impostos+TaxaCartao+Comissao)) -> -1.5911128 | M35: =IF(OR($A35="",$C35="",NOT(ISNUMBER($I35))),"",$C35-$I35) -> -7.8156788 | N35: =IF(OR($A35="",$K35=""),"",IF($K35>=MargemLiquidaDesejada,"🟢 Margem Saudável",IF($K35>=MargemLiquidaDesejada*0.8,"🟡 Atenção","🔴 Abaixo da Meta"))) -> 🔴 Abaixo da Meta
A36: Açaí Zero Açúcar 500ml | B36: Linha Premium | C36: 38 | D36: 500 | E36: =IF($A36="","",SUMIFS(FichaTecnica_CustoTotal,FichaTecnica_Produto,$A36)) -> 16.0938 | F36: =IF($A36="","",IFERROR($E36/(1-Perdas),$E36)) -> 16.591546 | G36: =IF($A36="","",IFERROR(INDEX(Rateio_CustoFixoPorVendaLinha,MATCH(LojaSelecionada,Rateio_LojasHeader,0)),0)) -> 7.4082778 | H36: =IF($A36="","",$F36+$G36) -> 23.999824 | I36: =IF($A36="","",IFERROR($H36/(1-MargemLiquidaDesejada-Impostos-TaxaCartao-Comissao),"Ajustar parâmetros")) -> 37.20903 | J36: =IF(OR($A36="",$C36=""),"",IFERROR($F36/$C36,"")) -> 0.43661964 | K36: =IF(OR($A36="",$C36=""),"",IFERROR(($C36-$H36-$C36*(Impostos+TaxaCartao+Comissao))/$C36,"")) -> 0.16342568 | L36: =IF(OR($A36="",$C36=""),"",$C36-$H36-$C36*(Impostos+TaxaCartao+Comissao)) -> 6.2101758 | M36: =IF(OR($A36="",$C36="",NOT(ISNUMBER($I36))),"",$C36-$I36) -> 0.79097028 | N36: =IF(OR($A36="",$K36=""),"",IF($K36>=MargemLiquidaDesejada,"🟢 Margem Saudável",IF($K36>=MargemLiquidaDesejada*0.8,"🟡 Atenção","🔴 Abaixo da Meta"))) -> 🟢 Margem Saudável
A37: Açaí Puro 250ml | B37: Linha Premium | C37: 18 | D37: 250 | E37: =IF($A37="","",SUMIFS(FichaTecnica_CustoTotal,FichaTecnica_Produto,$A37)) -> 10.0938 | F37: =IF($A37="","",IFERROR($E37/(1-Perdas),$E37)) -> 10.405979 | G37: =IF($A37="","",IFERROR(INDEX(Rateio_CustoFixoPorVendaLinha,MATCH(LojaSelecionada,Rateio_LojasHeader,0)),0)) -> 7.4082778 | H37: =IF($A37="","",$F37+$G37) -> 17.814257 | I37: =IF($A37="","",IFERROR($H37/(1-MargemLiquidaDesejada-Impostos-TaxaCartao-Comissao),"Ajustar parâmetros")) -> 27.619003 | J37: =IF(OR($A37="",$C37=""),"",IFERROR($F37/$C37,"")) -> 0.57810997 | K37: =IF(OR($A37="",$C37=""),"",IFERROR(($C37-$H37-$C37*(Impostos+TaxaCartao+Comissao))/$C37,"")) -> -0.19468095 | L37: =IF(OR($A37="",$C37=""),"",$C37-$H37-$C37*(Impostos+TaxaCartao+Comissao)) -> -3.5042572 | M37: =IF(OR($A37="",$C37="",NOT(ISNUMBER($I37))),"",$C37-$I37) -> -9.6190033 | N37: =IF(OR($A37="",$K37=""),"",IF($K37>=MargemLiquidaDesejada,"🟢 Margem Saudável",IF($K37>=MargemLiquidaDesejada*0.8,"🟡 Atenção","🔴 Abaixo da Meta"))) -> 🔴 Abaixo da Meta
A38: Açaí Puro 500ml | B38: Linha Premium | C38: 27.5 | D38: 500 | E38: =IF($A38="","",SUMIFS(FichaTecnica_CustoTotal,FichaTecnica_Produto,$A38)) -> 15.0938 | F38: =IF($A38="","",IFERROR($E38/(1-Perdas),$E38)) -> 15.560619 | G38: =IF($A38="","",IFERROR(INDEX(Rateio_CustoFixoPorVendaLinha,MATCH(LojaSelecionada,Rateio_LojasHeader,0)),0)) -> 7.4082778 | H38: =IF($A38="","",$F38+$G38) -> 22.968896 | I38: =IF($A38="","",IFERROR($H38/(1-MargemLiquidaDesejada-Impostos-TaxaCartao-Comissao),"Ajustar parâmetros")) -> 35.610692 | J38: =IF(OR($A38="",$C38=""),"",IFERROR($F38/$C38,"")) -> 0.56584067 | K38: =IF(OR($A38="",$C38=""),"",IFERROR(($C38-$H38-$C38*(Impostos+TaxaCartao+Comissao))/$C38,"")) -> -0.040232594 | L38: =IF(OR($A38="",$C38=""),"",$C38-$H38-$C38*(Impostos+TaxaCartao+Comissao)) -> -1.1063963 | M38: =IF(OR($A38="",$C38="",NOT(ISNUMBER($I38))),"",$C38-$I38) -> -8.110692 | N38: =IF(OR($A38="",$K38=""),"",IF($K38>=MargemLiquidaDesejada,"🟢 Margem Saudável",IF($K38>=MargemLiquidaDesejada*0.8,"🟡 Atenção","🔴 Abaixo da Meta"))) -> 🔴 Abaixo da Meta
A39: Açaí Banana 250ml | B39: Linha Premium | C39: 18 | D39: 250 | E39: =IF($A39="","",SUMIFS(FichaTecnica_CustoTotal,FichaTecnica_Produto,$A39)) -> 10.0938 | F39: =IF($A39="","",IFERROR($E39/(1-Perdas),$E39)) -> 10.405979 | G39: =IF($A39="","",IFERROR(INDEX(Rateio_CustoFixoPorVendaLinha,MATCH(LojaSelecionada,Rateio_LojasHeader,0)),0)) -> 7.4082778 | H39: =IF($A39="","",$F39+$G39) -> 17.814257 | I39: =IF($A39="","",IFERROR($H39/(1-MargemLiquidaDesejada-Impostos-TaxaCartao-Comissao),"Ajustar parâmetros")) -> 27.619003 | J39: =IF(OR($A39="",$C39=""),"",IFERROR($F39/$C39,"")) -> 0.57810997 | K39: =IF(OR($A39="",$C39=""),"",IFERROR(($C39-$H39-$C39*(Impostos+TaxaCartao+Comissao))/$C39,"")) -> -0.19468095 | L39: =IF(OR($A39="",$C39=""),"",$C39-$H39-$C39*(Impostos+TaxaCartao+Comissao)) -> -3.5042572 | M39: =IF(OR($A39="",$C39="",NOT(ISNUMBER($I39))),"",$C39-$I39) -> -9.6190033 | N39: =IF(OR($A39="",$K39=""),"",IF($K39>=MargemLiquidaDesejada,"🟢 Margem Saudável",IF($K39>=MargemLiquidaDesejada*0.8,"🟡 Atenção","🔴 Abaixo da Meta"))) -> 🔴 Abaixo da Meta
A40: Açaí Banana 500ml | B40: Linha Premium | C40: 27.5 | D40: 500 | E40: =IF($A40="","",SUMIFS(FichaTecnica_CustoTotal,FichaTecnica_Produto,$A40)) -> 15.0938 | F40: =IF($A40="","",IFERROR($E40/(1-Perdas),$E40)) -> 15.560619 | G40: =IF($A40="","",IFERROR(INDEX(Rateio_CustoFixoPorVendaLinha,MATCH(LojaSelecionada,Rateio_LojasHeader,0)),0)) -> 7.4082778 | H40: =IF($A40="","",$F40+$G40) -> 22.968896 | I40: =IF($A40="","",IFERROR($H40/(1-MargemLiquidaDesejada-Impostos-TaxaCartao-Comissao),"Ajustar parâmetros")) -> 35.610692 | J40: =IF(OR($A40="",$C40=""),"",IFERROR($F40/$C40,"")) -> 0.56584067 | K40: =IF(OR($A40="",$C40=""),"",IFERROR(($C40-$H40-$C40*(Impostos+TaxaCartao+Comissao))/$C40,"")) -> -0.040232594 | L40: =IF(OR($A40="",$C40=""),"",$C40-$H40-$C40*(Impostos+TaxaCartao+Comissao)) -> -1.1063963 | M40: =IF(OR($A40="",$C40="",NOT(ISNUMBER($I40))),"",$C40-$I40) -> -8.110692 | N40: =IF(OR($A40="",$K40=""),"",IF($K40>=MargemLiquidaDesejada,"🟢 Margem Saudável",IF($K40>=MargemLiquidaDesejada*0.8,"🟡 Atenção","🔴 Abaixo da Meta"))) -> 🔴 Abaixo da Meta
A41: Açaí Morango 250ml | B41: Linha Premium | C41: 18 | D41: 250 | E41: =IF($A41="","",SUMIFS(FichaTecnica_CustoTotal,FichaTecnica_Produto,$A41)) -> 10.0938 | F41: =IF($A41="","",IFERROR($E41/(1-Perdas),$E41)) -> 10.405979 | G41: =IF($A41="","",IFERROR(INDEX(Rateio_CustoFixoPorVendaLinha,MATCH(LojaSelecionada,Rateio_LojasHeader,0)),0)) -> 7.4082778 | H41: =IF($A41="","",$F41+$G41) -> 17.814257 | I41: =IF($A41="","",IFERROR($H41/(1-MargemLiquidaDesejada-Impostos-TaxaCartao-Comissao),"Ajustar parâmetros")) -> 27.619003 | J41: =IF(OR($A41="",$C41=""),"",IFERROR($F41/$C41,"")) -> 0.57810997 | K41: =IF(OR($A41="",$C41=""),"",IFERROR(($C41-$H41-$C41*(Impostos+TaxaCartao+Comissao))/$C41,"")) -> -0.19468095 | L41: =IF(OR($A41="",$C41=""),"",$C41-$H41-$C41*(Impostos+TaxaCartao+Comissao)) -> -3.5042572 | M41: =IF(OR($A41="",$C41="",NOT(ISNUMBER($I41))),"",$C41-$I41) -> -9.6190033 | N41: =IF(OR($A41="",$K41=""),"",IF($K41>=MargemLiquidaDesejada,"🟢 Margem Saudável",IF($K41>=MargemLiquidaDesejada*0.8,"🟡 Atenção","🔴 Abaixo da Meta"))) -> 🔴 Abaixo da Meta
A42: Açaí Morango 500ml | B42: Linha Premium | C42: 27.5 | D42: 500 | E42: =IF($A42="","",SUMIFS(FichaTecnica_CustoTotal,FichaTecnica_Produto,$A42)) -> 15.0938 | F42: =IF($A42="","",IFERROR($E42/(1-Perdas),$E42)) -> 15.560619 | G42: =IF($A42="","",IFERROR(INDEX(Rateio_CustoFixoPorVendaLinha,MATCH(LojaSelecionada,Rateio_LojasHeader,0)),0)) -> 7.4082778 | H42: =IF($A42="","",$F42+$G42) -> 22.968896 | I42: =IF($A42="","",IFERROR($H42/(1-MargemLiquidaDesejada-Impostos-TaxaCartao-Comissao),"Ajustar parâmetros")) -> 35.610692 | J42: =IF(OR($A42="",$C42=""),"",IFERROR($F42/$C42,"")) -> 0.56584067 | K42: =IF(OR($A42="",$C42=""),"",IFERROR(($C42-$H42-$C42*(Impostos+TaxaCartao+Comissao))/$C42,"")) -> -0.040232594 | L42: =IF(OR($A42="",$C42=""),"",$C42-$H42-$C42*(Impostos+TaxaCartao+Comissao)) -> -1.1063963 | M42: =IF(OR($A42="",$C42="",NOT(ISNUMBER($I42))),"",$C42-$I42) -> -8.110692 | N42: =IF(OR($A42="",$K42=""),"",IF($K42>=MargemLiquidaDesejada,"🟢 Margem Saudável",IF($K42>=MargemLiquidaDesejada*0.8,"🟡 Atenção","🔴 Abaixo da Meta"))) -> 🔴 Abaixo da Meta
A43: Açaí Tradicional 200ml | B43: Linha Tradicional | C43: 16.9 | D43: =IF($A43="","",SUMIFS(FichaTecnica_QtdGML,FichaTecnica_Produto,$A43)) -> 170 | E43: =IF($A43="","",SUMIFS(FichaTecnica_CustoTotal,FichaTecnica_Produto,$A43)) -> 3.1479 | F43: =IF($A43="","",IFERROR($E43/(1-Perdas),$E43)) -> 3.2452577 | G43: =IF($A43="","",IFERROR(INDEX(Rateio_CustoFixoPorVendaLinha,MATCH(LojaSelecionada,Rateio_LojasHeader,0)),0)) -> 7.4082778 | H43: =IF($A43="","",$F43+$G43) -> 10.653536 | I43: =IF($A43="","",IFERROR($H43/(1-MargemLiquidaDesejada-Impostos-TaxaCartao-Comissao),"Ajustar parâmetros")) -> 16.517109 | J43: =IF(OR($A43="",$C43=""),"",IFERROR($F43/$C43,"")) -> 0.19202708 | K43: =IF(OR($A43="",$C43=""),"",IFERROR(($C43-$H43-$C43*(Impostos+TaxaCartao+Comissao))/$C43,"")) -> 0.16461328 | L43: =IF(OR($A43="",$C43=""),"",$C43-$H43-$C43*(Impostos+TaxaCartao+Comissao)) -> 2.7819645 | M43: =IF(OR($A43="",$C43="",NOT(ISNUMBER($I43))),"",$C43-$I43) -> 0.38289068 | N43: =IF(OR($A43="",$K43=""),"",IF($K43>=MargemLiquidaDesejada,"🟢 Margem Saudável",IF($K43>=MargemLiquidaDesejada*0.8,"🟡 Atenção","🔴 Abaixo da Meta"))) -> 🟢 Margem Saudável
A44: Açaí Tradicional 300ml | B44: Linha Tradicional | C44: 22.9 | D44: =IF($A44="","",SUMIFS(FichaTecnica_QtdGML,FichaTecnica_Produto,$A44)) -> 270 | E44: =IF($A44="","",SUMIFS(FichaTecnica_CustoTotal,FichaTecnica_Produto,$A44)) -> 4.78482 | F44: =IF($A44="","",IFERROR($E44/(1-Perdas),$E44)) -> 4.9328041 | G44: =IF($A44="","",IFERROR(INDEX(Rateio_CustoFixoPorVendaLinha,MATCH(LojaSelecionada,Rateio_LojasHeader,0)),0)) -> 7.4082778 | H44: =IF($A44="","",$F44+$G44) -> 12.341082 | I44: =IF($A44="","",IFERROR($H44/(1-MargemLiquidaDesejada-Impostos-TaxaCartao-Comissao),"Ajustar parâmetros")) -> 19.13346 | J44: =IF(OR($A44="",$C44=""),"",IFERROR($F44/$C44,"")) -> 0.21540629 | K44: =IF(OR($A44="",$C44=""),"",IFERROR(($C44-$H44-$C44*(Impostos+TaxaCartao+Comissao))/$C44,"")) -> 0.25608813 | L44: =IF(OR($A44="",$C44=""),"",$C44-$H44-$C44*(Impostos+TaxaCartao+Comissao)) -> 5.8644181 | M44: =IF(OR($A44="",$C44="",NOT(ISNUMBER($I44))),"",$C44-$I44) -> 3.7665397 | N44: =IF(OR($A44="",$K44=""),"",IF($K44>=MargemLiquidaDesejada,"🟢 Margem Saudável",IF($K44>=MargemLiquidaDesejada*0.8,"🟡 Atenção","🔴 Abaixo da Meta"))) -> 🟢 Margem Saudável
A45: Açaí Tradicional 500ml | B45: Linha Tradicional | C45: 29.9 | D45: =IF($A45="","",SUMIFS(FichaTecnica_QtdGML,FichaTecnica_Produto,$A45)) -> 470 | E45: =IF($A45="","",SUMIFS(FichaTecnica_CustoTotal,FichaTecnica_Produto,$A45)) -> 8.18475 | F45: =IF($A45="","",IFERROR($E45/(1-Perdas),$E45)) -> 8.4378866 | G45: =IF($A45="","",IFERROR(INDEX(Rateio_CustoFixoPorVendaLinha,MATCH(LojaSelecionada,Rateio_LojasHeader,0)),0)) -> 7.4082778 | H45: =IF($A45="","",$F45+$G45) -> 15.846164 | I45: =IF($A45="","",IFERROR($H45/(1-MargemLiquidaDesejada-Impostos-TaxaCartao-Comissao),"Ajustar parâmetros")) -> 24.567697 | J45: =IF(OR($A45="",$C45=""),"",IFERROR($F45/$C45,"")) -> 0.28220357 | K45: =IF(OR($A45="",$C45=""),"",IFERROR(($C45-$H45-$C45*(Impostos+TaxaCartao+Comissao))/$C45,"")) -> 0.26502795 | L45: =IF(OR($A45="",$C45=""),"",$C45-$H45-$C45*(Impostos+TaxaCartao+Comissao)) -> 7.9243356 | M45: =IF(OR($A45="",$C45="",NOT(ISNUMBER($I45))),"",$C45-$I45) -> 5.3323033 | N45: =IF(OR($A45="",$K45=""),"",IF($K45>=MargemLiquidaDesejada,"🟢 Margem Saudável",IF($K45>=MargemLiquidaDesejada*0.8,"🟡 Atenção","🔴 Abaixo da Meta"))) -> 🟢 Margem Saudável
A46: Cupuaçu Tradicional 200ml | B46: Linha Tradicional | C46: 16.9 | D46: =IF($A46="","",SUMIFS(FichaTecnica_QtdGML,FichaTecnica_Produto,$A46)) -> 170 | E46: =IF($A46="","",SUMIFS(FichaTecnica_CustoTotal,FichaTecnica_Produto,$A46)) -> 3.1479 | F46: =IF($A46="","",IFERROR($E46/(1-Perdas),$E46)) -> 3.2452577 | G46: =IF($A46="","",IFERROR(INDEX(Rateio_CustoFixoPorVendaLinha,MATCH(LojaSelecionada,Rateio_LojasHeader,0)),0)) -> 7.4082778 | H46: =IF($A46="","",$F46+$G46) -> 10.653536 | I46: =IF($A46="","",IFERROR($H46/(1-MargemLiquidaDesejada-Impostos-TaxaCartao-Comissao),"Ajustar parâmetros")) -> 16.517109 | J46: =IF(OR($A46="",$C46=""),"",IFERROR($F46/$C46,"")) -> 0.19202708 | K46: =IF(OR($A46="",$C46=""),"",IFERROR(($C46-$H46-$C46*(Impostos+TaxaCartao+Comissao))/$C46,"")) -> 0.16461328 | L46: =IF(OR($A46="",$C46=""),"",$C46-$H46-$C46*(Impostos+TaxaCartao+Comissao)) -> 2.7819645 | M46: =IF(OR($A46="",$C46="",NOT(ISNUMBER($I46))),"",$C46-$I46) -> 0.38289068 | N46: =IF(OR($A46="",$K46=""),"",IF($K46>=MargemLiquidaDesejada,"🟢 Margem Saudável",IF($K46>=MargemLiquidaDesejada*0.8,"🟡 Atenção","🔴 Abaixo da Meta"))) -> 🟢 Margem Saudável
A47: Cupuaçu Tradicional 300ml | B47: Linha Tradicional | C47: 22.9 | D47: =IF($A47="","",SUMIFS(FichaTecnica_QtdGML,FichaTecnica_Produto,$A47)) -> 270 | E47: =IF($A47="","",SUMIFS(FichaTecnica_CustoTotal,FichaTecnica_Produto,$A47)) -> 4.78482 | F47: =IF($A47="","",IFERROR($E47/(1-Perdas),$E47)) -> 4.9328041 | G47: =IF($A47="","",IFERROR(INDEX(Rateio_CustoFixoPorVendaLinha,MATCH(LojaSelecionada,Rateio_LojasHeader,0)),0)) -> 7.4082778 | H47: =IF($A47="","",$F47+$G47) -> 12.341082 | I47: =IF($A47="","",IFERROR($H47/(1-MargemLiquidaDesejada-Impostos-TaxaCartao-Comissao),"Ajustar parâmetros")) -> 19.13346 | J47: =IF(OR($A47="",$C47=""),"",IFERROR($F47/$C47,"")) -> 0.21540629 | K47: =IF(OR($A47="",$C47=""),"",IFERROR(($C47-$H47-$C47*(Impostos+TaxaCartao+Comissao))/$C47,"")) -> 0.25608813 | L47: =IF(OR($A47="",$C47=""),"",$C47-$H47-$C47*(Impostos+TaxaCartao+Comissao)) -> 5.8644181 | M47: =IF(OR($A47="",$C47="",NOT(ISNUMBER($I47))),"",$C47-$I47) -> 3.7665397 | N47: =IF(OR($A47="",$K47=""),"",IF($K47>=MargemLiquidaDesejada,"🟢 Margem Saudável",IF($K47>=MargemLiquidaDesejada*0.8,"🟡 Atenção","🔴 Abaixo da Meta"))) -> 🟢 Margem Saudável
A48: Cupuaçu Tradicional 500ml | B48: Linha Tradicional | C48: 29.9 | D48: =IF($A48="","",SUMIFS(FichaTecnica_QtdGML,FichaTecnica_Produto,$A48)) -> 470 | E48: =IF($A48="","",SUMIFS(FichaTecnica_CustoTotal,FichaTecnica_Produto,$A48)) -> 8.18475 | F48: =IF($A48="","",IFERROR($E48/(1-Perdas),$E48)) -> 8.4378866 | G48: =IF($A48="","",IFERROR(INDEX(Rateio_CustoFixoPorVendaLinha,MATCH(LojaSelecionada,Rateio_LojasHeader,0)),0)) -> 7.4082778 | H48: =IF($A48="","",$F48+$G48) -> 15.846164 | I48: =IF($A48="","",IFERROR($H48/(1-MargemLiquidaDesejada-Impostos-TaxaCartao-Comissao),"Ajustar parâmetros")) -> 24.567697 | J48: =IF(OR($A48="",$C48=""),"",IFERROR($F48/$C48,"")) -> 0.28220357 | K48: =IF(OR($A48="",$C48=""),"",IFERROR(($C48-$H48-$C48*(Impostos+TaxaCartao+Comissao))/$C48,"")) -> 0.26502795 | L48: =IF(OR($A48="",$C48=""),"",$C48-$H48-$C48*(Impostos+TaxaCartao+Comissao)) -> 7.9243356 | M48: =IF(OR($A48="",$C48="",NOT(ISNUMBER($I48))),"",$C48-$I48) -> 5.3323033 | N48: =IF(OR($A48="",$K48=""),"",IF($K48>=MargemLiquidaDesejada,"🟢 Margem Saudável",IF($K48>=MargemLiquidaDesejada*0.8,"🟡 Atenção","🔴 Abaixo da Meta"))) -> 🟢 Margem Saudável
A49: Milkshake Morango | B49: Milkshakes | C49: 18 | D49: =IF($A49="","",SUMIFS(FichaTecnica_QtdGML,FichaTecnica_Produto,$A49)) -> 510 | E49: =IF($A49="","",SUMIFS(FichaTecnica_CustoTotal,FichaTecnica_Produto,$A49)) -> 2.8389 | F49: =IF($A49="","",IFERROR($E49/(1-Perdas),$E49)) -> 2.926701 | G49: =IF($A49="","",IFERROR(INDEX(Rateio_CustoFixoPorVendaLinha,MATCH(LojaSelecionada,Rateio_LojasHeader,0)),0)) -> 7.4082778 | H49: =IF($A49="","",$F49+$G49) -> 10.334979 | I49: =IF($A49="","",IFERROR($H49/(1-MargemLiquidaDesejada-Impostos-TaxaCartao-Comissao),"Ajustar parâmetros")) -> 16.023223 | J49: =IF(OR($A49="",$C49=""),"",IFERROR($F49/$C49,"")) -> 0.1625945 | K49: =IF(OR($A49="",$C49=""),"",IFERROR(($C49-$H49-$C49*(Impostos+TaxaCartao+Comissao))/$C49,"")) -> 0.22083451 | L49: =IF(OR($A49="",$C49=""),"",$C49-$H49-$C49*(Impostos+TaxaCartao+Comissao)) -> 3.9750212 | M49: =IF(OR($A49="",$C49="",NOT(ISNUMBER($I49))),"",$C49-$I49) -> 1.976777 | N49: =IF(OR($A49="",$K49=""),"",IF($K49>=MargemLiquidaDesejada,"🟢 Margem Saudável",IF($K49>=MargemLiquidaDesejada*0.8,"🟡 Atenção","🔴 Abaixo da Meta"))) -> 🟢 Margem Saudável
A50: Milkshake Maracujá | B50: Milkshakes | C50: 18 | D50: =IF($A50="","",SUMIFS(FichaTecnica_QtdGML,FichaTecnica_Produto,$A50)) -> 510 | E50: =IF($A50="","",SUMIFS(FichaTecnica_CustoTotal,FichaTecnica_Produto,$A50)) -> 2.8389 | F50: =IF($A50="","",IFERROR($E50/(1-Perdas),$E50)) -> 2.926701 | G50: =IF($A50="","",IFERROR(INDEX(Rateio_CustoFixoPorVendaLinha,MATCH(LojaSelecionada,Rateio_LojasHeader,0)),0)) -> 7.4082778 | H50: =IF($A50="","",$F50+$G50) -> 10.334979 | I50: =IF($A50="","",IFERROR($H50/(1-MargemLiquidaDesejada-Impostos-TaxaCartao-Comissao),"Ajustar parâmetros")) -> 16.023223 | J50: =IF(OR($A50="",$C50=""),"",IFERROR($F50/$C50,"")) -> 0.1625945 | K50: =IF(OR($A50="",$C50=""),"",IFERROR(($C50-$H50-$C50*(Impostos+TaxaCartao+Comissao))/$C50,"")) -> 0.22083451 | L50: =IF(OR($A50="",$C50=""),"",$C50-$H50-$C50*(Impostos+TaxaCartao+Comissao)) -> 3.9750212 | M50: =IF(OR($A50="",$C50="",NOT(ISNUMBER($I50))),"",$C50-$I50) -> 1.976777 | N50: =IF(OR($A50="",$K50=""),"",IF($K50>=MargemLiquidaDesejada,"🟢 Margem Saudável",IF($K50>=MargemLiquidaDesejada*0.8,"🟡 Atenção","🔴 Abaixo da Meta"))) -> 🟢 Margem Saudável
A51: Milkshake Leite em Pó com Nutella | B51: Milkshakes | C51: 20 | D51: =IF($A51="","",SUMIFS(FichaTecnica_QtdGML,FichaTecnica_Produto,$A51)) -> 540 | E51: =IF($A51="","",SUMIFS(FichaTecnica_CustoTotal,FichaTecnica_Produto,$A51)) -> 3.8454 | F51: =IF($A51="","",IFERROR($E51/(1-Perdas),$E51)) -> 3.9643299 | G51: =IF($A51="","",IFERROR(INDEX(Rateio_CustoFixoPorVendaLinha,MATCH(LojaSelecionada,Rateio_LojasHeader,0)),0)) -> 7.4082778 | H51: =IF($A51="","",$F51+$G51) -> 11.372608 | I51: =IF($A51="","",IFERROR($H51/(1-MargemLiquidaDesejada-Impostos-TaxaCartao-Comissao),"Ajustar parâmetros")) -> 17.63195 | J51: =IF(OR($A51="",$C51=""),"",IFERROR($F51/$C51,"")) -> 0.19821649 | K51: =IF(OR($A51="",$C51=""),"",IFERROR(($C51-$H51-$C51*(Impostos+TaxaCartao+Comissao))/$C51,"")) -> 0.22636962 | L51: =IF(OR($A51="",$C51=""),"",$C51-$H51-$C51*(Impostos+TaxaCartao+Comissao)) -> 4.5273923 | M51: =IF(OR($A51="",$C51="",NOT(ISNUMBER($I51))),"",$C51-$I51) -> 2.3680501 | N51: =IF(OR($A51="",$K51=""),"",IF($K51>=MargemLiquidaDesejada,"🟢 Margem Saudável",IF($K51>=MargemLiquidaDesejada*0.8,"🟡 Atenção","🔴 Abaixo da Meta"))) -> 🟢 Margem Saudável
A52: Milkshake Crocante com Ovomaltine | B52: Milkshakes | C52: 20 | D52: =IF($A52="","",SUMIFS(FichaTecnica_QtdGML,FichaTecnica_Produto,$A52)) -> 510 | E52: =IF($A52="","",SUMIFS(FichaTecnica_CustoTotal,FichaTecnica_Produto,$A52)) -> 4.4349 | F52: =IF($A52="","",IFERROR($E52/(1-Perdas),$E52)) -> 4.5720619 | G52: =IF($A52="","",IFERROR(INDEX(Rateio_CustoFixoPorVendaLinha,MATCH(LojaSelecionada,Rateio_LojasHeader,0)),0)) -> 7.4082778 | H52: =IF($A52="","",$F52+$G52) -> 11.98034 | I52: =IF($A52="","",IFERROR($H52/(1-MargemLiquidaDesejada-Impostos-TaxaCartao-Comissao),"Ajustar parâmetros")) -> 18.57417 | J52: =IF(OR($A52="",$C52=""),"",IFERROR($F52/$C52,"")) -> 0.22860309 | K52: =IF(OR($A52="",$C52=""),"",IFERROR(($C52-$H52-$C52*(Impostos+TaxaCartao+Comissao))/$C52,"")) -> 0.19598302 | L52: =IF(OR($A52="",$C52=""),"",$C52-$H52-$C52*(Impostos+TaxaCartao+Comissao)) -> 3.9196604 | M52: =IF(OR($A52="",$C52="",NOT(ISNUMBER($I52))),"",$C52-$I52) -> 1.42583 | N52: =IF(OR($A52="",$K52=""),"",IF($K52>=MargemLiquidaDesejada,"🟢 Margem Saudável",IF($K52>=MargemLiquidaDesejada*0.8,"🟡 Atenção","🔴 Abaixo da Meta"))) -> 🟢 Margem Saudável
A53: Power Shake | B53: Milkshakes | C53: 22 | D53: =IF($A53="","",SUMIFS(FichaTecnica_QtdGML,FichaTecnica_Produto,$A53)) -> 540 | E53: =IF($A53="","",SUMIFS(FichaTecnica_CustoTotal,FichaTecnica_Produto,$A53)) -> 4.1088 | F53: =IF($A53="","",IFERROR($E53/(1-Perdas),$E53)) -> 4.2358763 | G53: =IF($A53="","",IFERROR(INDEX(Rateio_CustoFixoPorVendaLinha,MATCH(LojaSelecionada,Rateio_LojasHeader,0)),0)) -> 7.4082778 | H53: =IF($A53="","",$F53+$G53) -> 11.644154 | I53: =IF($A53="","",IFERROR($H53/(1-MargemLiquidaDesejada-Impostos-TaxaCartao-Comissao),"Ajustar parâmetros")) -> 18.052952 | J53: =IF(OR($A53="",$C53=""),"",IFERROR($F53/$C53,"")) -> 0.19253983 | K53: =IF(OR($A53="",$C53=""),"",IFERROR(($C53-$H53-$C53*(Impostos+TaxaCartao+Comissao))/$C53,"")) -> 0.26572027 | L53: =IF(OR($A53="",$C53=""),"",$C53-$H53-$C53*(Impostos+TaxaCartao+Comissao)) -> 5.8458459 | M53: =IF(OR($A53="",$C53="",NOT(ISNUMBER($I53))),"",$C53-$I53) -> 3.947048 | N53: =IF(OR($A53="",$K53=""),"",IF($K53>=MargemLiquidaDesejada,"🟢 Margem Saudável",IF($K53>=MargemLiquidaDesejada*0.8,"🟡 Atenção","🔴 Abaixo da Meta"))) -> 🟢 Margem Saudável
A54: Protein Shake | B54: Milkshakes | C54: 24 | D54: =IF($A54="","",SUMIFS(FichaTecnica_QtdGML,FichaTecnica_Produto,$A54)) -> 510 | E54: =IF($A54="","",SUMIFS(FichaTecnica_CustoTotal,FichaTecnica_Produto,$A54)) -> 2.8389 | F54: =IF($A54="","",IFERROR($E54/(1-Perdas),$E54)) -> 2.926701 | G54: =IF($A54="","",IFERROR(INDEX(Rateio_CustoFixoPorVendaLinha,MATCH(LojaSelecionada,Rateio_LojasHeader,0)),0)) -> 7.4082778 | H54: =IF($A54="","",$F54+$G54) -> 10.334979 | I54: =IF($A54="","",IFERROR($H54/(1-MargemLiquidaDesejada-Impostos-TaxaCartao-Comissao),"Ajustar parâmetros")) -> 16.023223 | J54: =IF(OR($A54="",$C54=""),"",IFERROR($F54/$C54,"")) -> 0.12194588 | K54: =IF(OR($A54="",$C54=""),"",IFERROR(($C54-$H54-$C54*(Impostos+TaxaCartao+Comissao))/$C54,"")) -> 0.36437588 | L54: =IF(OR($A54="",$C54=""),"",$C54-$H54-$C54*(Impostos+TaxaCartao+Comissao)) -> 8.7450212 | M54: =IF(OR($A54="",$C54="",NOT(ISNUMBER($I54))),"",$C54-$I54) -> 7.976777 | N54: =IF(OR($A54="",$K54=""),"",IF($K54>=MargemLiquidaDesejada,"🟢 Margem Saudável",IF($K54>=MargemLiquidaDesejada*0.8,"🟡 Atenção","🔴 Abaixo da Meta"))) -> 🟢 Margem Saudável
... A62: Suco de Açaí 200ml | B62: Bebidas | C62: 6 | D62: =IF($A62="","",SUMIFS(FichaTecnica_QtdGML,FichaTecnica_Produto,$A62)) -> 0 | E62: =IF($A62="","",SUMIFS(FichaTecnica_CustoTotal,FichaTecnica_Produto,$A62)) -> 0 | F62: =IF($A62="","",IFERROR($E62/(1-Perdas),$E62)) -> 0 | G62: =IF($A62="","",IFERROR(INDEX(Rateio_CustoFixoPorVendaLinha,MATCH(LojaSelecionada,Rateio_LojasHeader,0)),0)) -> 7.4082778 | H62: =IF($A62="","",$F62+$G62) -> 7.4082778 | I62: =IF($A62="","",IFERROR($H62/(1-MargemLiquidaDesejada-Impostos-TaxaCartao-Comissao),"Ajustar parâmetros")) -> 11.485702 | J62: =IF(OR($A62="",$C62=""),"",IFERROR($F62/$C62,"")) -> 0 | K62: =IF(OR($A62="",$C62=""),"",IFERROR(($C62-$H62-$C62*(Impostos+TaxaCartao+Comissao))/$C62,"")) -> -0.43971296 | L62: =IF(OR($A62="",$C62=""),"",$C62-$H62-$C62*(Impostos+TaxaCartao+Comissao)) -> -2.6382778 | M62: =IF(OR($A62="",$C62="",NOT(ISNUMBER($I62))),"",$C62-$I62) -> -5.485702 | N62: =IF(OR($A62="",$K62=""),"",IF($K62>=MargemLiquidaDesejada,"🟢 Margem Saudável",IF($K62>=MargemLiquidaDesejada*0.8,"🟡 Atenção","🔴 Abaixo da Meta"))) -> 🔴 Abaixo da Meta
D63: =IF($A63="","",SUMIFS(FichaTecnica_QtdGML,FichaTecnica_Produto,$A63)) | E63: =IF($A63="","",SUMIFS(FichaTecnica_CustoTotal,FichaTecnica_Produto,$A63)) | F63: =IF($A63="","",IFERROR($E63/(1-Perdas),$E63)) | G63: =IF($A63="","",IFERROR(INDEX(Rateio_CustoFixoPorVendaLinha,MATCH(LojaSelecionada,Rateio_LojasHeader,0)),0)) | H63: =IF($A63="","",$F63+$G63) | I63: =IF($A63="","",IFERROR($H63/(1-MargemLiquidaDesejada-Impostos-TaxaCartao-Comissao),"Ajustar parâmetros")) | J63: =IF(OR($A63="",$C63=""),"",IFERROR($F63/$C63,"")) | K63: =IF(OR($A63="",$C63=""),"",IFERROR(($C63-$H63-$C63*(Impostos+TaxaCartao+Comissao))/$C63,"")) | L63: =IF(OR($A63="",$C63=""),"",$C63-$H63-$C63*(Impostos+TaxaCartao+Comissao)) | M63: =IF(OR($A63="",$C63="",NOT(ISNUMBER($I63))),"",$C63-$I63) | N63: =IF(OR($A63="",$K63=""),"",IF($K63>=MargemLiquidaDesejada,"🟢 Margem Saudável",IF($K63>=MargemLiquidaDesejada*0.8,"🟡 Atenção","🔴 Abaixo da Meta")))
D64: =IF($A64="","",SUMIFS(FichaTecnica_QtdGML,FichaTecnica_Produto,$A64)) | E64: =IF($A64="","",SUMIFS(FichaTecnica_CustoTotal,FichaTecnica_Produto,$A64)) | F64: =IF($A64="","",IFERROR($E64/(1-Perdas),$E64)) | G64: =IF($A64="","",IFERROR(INDEX(Rateio_CustoFixoPorVendaLinha,MATCH(LojaSelecionada,Rateio_LojasHeader,0)),0)) | H64: =IF($A64="","",$F64+$G64) | I64: =IF($A64="","",IFERROR($H64/(1-MargemLiquidaDesejada-Impostos-TaxaCartao-Comissao),"Ajustar parâmetros")) | J64: =IF(OR($A64="",$C64=""),"",IFERROR($F64/$C64,"")) | K64: =IF(OR($A64="",$C64=""),"",IFERROR(($C64-$H64-$C64*(Impostos+TaxaCartao+Comissao))/$C64,"")) | L64: =IF(OR($A64="",$C64=""),"",$C64-$H64-$C64*(Impostos+TaxaCartao+Comissao)) | M64: =IF(OR($A64="",$C64="",NOT(ISNUMBER($I64))),"",$C64-$I64) | N64: =IF(OR($A64="",$K64=""),"",IF($K64>=MargemLiquidaDesejada,"🟢 Margem Saudável",IF($K64>=MargemLiquidaDesejada*0.8,"🟡 Atenção","🔴 Abaixo da Meta")))
D65: =IF($A65="","",SUMIFS(FichaTecnica_QtdGML,FichaTecnica_Produto,$A65)) | E65: =IF($A65="","",SUMIFS(FichaTecnica_CustoTotal,FichaTecnica_Produto,$A65)) | F65: =IF($A65="","",IFERROR($E65/(1-Perdas),$E65)) | G65: =IF($A65="","",IFERROR(INDEX(Rateio_CustoFixoPorVendaLinha,MATCH(LojaSelecionada,Rateio_LojasHeader,0)),0)) | H65: =IF($A65="","",$F65+$G65) | I65: =IF($A65="","",IFERROR($H65/(1-MargemLiquidaDesejada-Impostos-TaxaCartao-Comissao),"Ajustar parâmetros")) | J65: =IF(OR($A65="",$C65=""),"",IFERROR($F65/$C65,"")) | K65: =IF(OR($A65="",$C65=""),"",IFERROR(($C65-$H65-$C65*(Impostos+TaxaCartao+Comissao))/$C65,"")) | L65: =IF(OR($A65="",$C65=""),"",$C65-$H65-$C65*(Impostos+TaxaCartao+Comissao)) | M65: =IF(OR($A65="",$C65="",NOT(ISNUMBER($I65))),"",$C65-$I65) | N65: =IF(OR($A65="",$K65=""),"",IF($K65>=MargemLiquidaDesejada,"🟢 Margem Saudável",IF($K65>=MargemLiquidaDesejada*0.8,"🟡 Atenção","🔴 Abaixo da Meta")))
D66: =IF($A66="","",SUMIFS(FichaTecnica_QtdGML,FichaTecnica_Produto,$A66)) | E66: =IF($A66="","",SUMIFS(FichaTecnica_CustoTotal,FichaTecnica_Produto,$A66)) | F66: =IF($A66="","",IFERROR($E66/(1-Perdas),$E66)) | G66: =IF($A66="","",IFERROR(INDEX(Rateio_CustoFixoPorVendaLinha,MATCH(LojaSelecionada,Rateio_LojasHeader,0)),0)) | H66: =IF($A66="","",$F66+$G66) | I66: =IF($A66="","",IFERROR($H66/(1-MargemLiquidaDesejada-Impostos-TaxaCartao-Comissao),"Ajustar parâmetros")) | J66: =IF(OR($A66="",$C66=""),"",IFERROR($F66/$C66,"")) | K66: =IF(OR($A66="",$C66=""),"",IFERROR(($C66-$H66-$C66*(Impostos+TaxaCartao+Comissao))/$C66,"")) | L66: =IF(OR($A66="",$C66=""),"",$C66-$H66-$C66*(Impostos+TaxaCartao+Comissao)) | M66: =IF(OR($A66="",$C66="",NOT(ISNUMBER($I66))),"",$C66-$I66) | N66: =IF(OR($A66="",$K66=""),"",IF($K66>=MargemLiquidaDesejada,"🟢 Margem Saudável",IF($K66>=MargemLiquidaDesejada*0.8,"🟡 Atenção","🔴 Abaixo da Meta")))
D67: =IF($A67="","",SUMIFS(FichaTecnica_QtdGML,FichaTecnica_Produto,$A67)) | E67: =IF($A67="","",SUMIFS(FichaTecnica_CustoTotal,FichaTecnica_Produto,$A67)) | F67: =IF($A67="","",IFERROR($E67/(1-Perdas),$E67)) | G67: =IF($A67="","",IFERROR(INDEX(Rateio_CustoFixoPorVendaLinha,MATCH(LojaSelecionada,Rateio_LojasHeader,0)),0)) | H67: =IF($A67="","",$F67+$G67) | I67: =IF($A67="","",IFERROR($H67/(1-MargemLiquidaDesejada-Impostos-TaxaCartao-Comissao),"Ajustar parâmetros")) | J67: =IF(OR($A67="",$C67=""),"",IFERROR($F67/$C67,"")) | K67: =IF(OR($A67="",$C67=""),"",IFERROR(($C67-$H67-$C67*(Impostos+TaxaCartao+Comissao))/$C67,"")) | L67: =IF(OR($A67="",$C67=""),"",$C67-$H67-$C67*(Impostos+TaxaCartao+Comissao)) | M67: =IF(OR($A67="",$C67="",NOT(ISNUMBER($I67))),"",$C67-$I67) | N67: =IF(OR($A67="",$K67=""),"",IF($K67>=MargemLiquidaDesejada,"🟢 Margem Saudável",IF($K67>=MargemLiquidaDesejada*0.8,"🟡 Atenção","🔴 Abaixo da Meta")))
D68: =IF($A68="","",SUMIFS(FichaTecnica_QtdGML,FichaTecnica_Produto,$A68)) | E68: =IF($A68="","",SUMIFS(FichaTecnica_CustoTotal,FichaTecnica_Produto,$A68)) | F68: =IF($A68="","",IFERROR($E68/(1-Perdas),$E68)) | G68: =IF($A68="","",IFERROR(INDEX(Rateio_CustoFixoPorVendaLinha,MATCH(LojaSelecionada,Rateio_LojasHeader,0)),0)) | H68: =IF($A68="","",$F68+$G68) | I68: =IF($A68="","",IFERROR($H68/(1-MargemLiquidaDesejada-Impostos-TaxaCartao-Comissao),"Ajustar parâmetros")) | J68: =IF(OR($A68="",$C68=""),"",IFERROR($F68/$C68,"")) | K68: =IF(OR($A68="",$C68=""),"",IFERROR(($C68-$H68-$C68*(Impostos+TaxaCartao+Comissao))/$C68,"")) | L68: =IF(OR($A68="",$C68=""),"",$C68-$H68-$C68*(Impostos+TaxaCartao+Comissao)) | M68: =IF(OR($A68="",$C68="",NOT(ISNUMBER($I68))),"",$C68-$I68) | N68: =IF(OR($A68="",$K68=""),"",IF($K68>=MargemLiquidaDesejada,"🟢 Margem Saudável",IF($K68>=MargemLiquidaDesejada*0.8,"🟡 Atenção","🔴 Abaixo da Meta")))
D69: =IF($A69="","",SUMIFS(FichaTecnica_QtdGML,FichaTecnica_Produto,$A69)) | E69: =IF($A69="","",SUMIFS(FichaTecnica_CustoTotal,FichaTecnica_Produto,$A69)) | F69: =IF($A69="","",IFERROR($E69/(1-Perdas),$E69)) | G69: =IF($A69="","",IFERROR(INDEX(Rateio_CustoFixoPorVendaLinha,MATCH(LojaSelecionada,Rateio_LojasHeader,0)),0)) | H69: =IF($A69="","",$F69+$G69) | I69: =IF($A69="","",IFERROR($H69/(1-MargemLiquidaDesejada-Impostos-TaxaCartao-Comissao),"Ajustar parâmetros")) | J69: =IF(OR($A69="",$C69=""),"",IFERROR($F69/$C69,"")) | K69: =IF(OR($A69="",$C69=""),"",IFERROR(($C69-$H69-$C69*(Impostos+TaxaCartao+Comissao))/$C69,"")) | L69: =IF(OR($A69="",$C69=""),"",$C69-$H69-$C69*(Impostos+TaxaCartao+Comissao)) | M69: =IF(OR($A69="",$C69="",NOT(ISNUMBER($I69))),"",$C69-$I69) | N69: =IF(OR($A69="",$K69=""),"",IF($K69>=MargemLiquidaDesejada,"🟢 Margem Saudável",IF($K69>=MargemLiquidaDesejada*0.8,"🟡 Atenção","🔴 Abaixo da Meta")))
D70: =IF($A70="","",SUMIFS(FichaTecnica_QtdGML,FichaTecnica_Produto,$A70)) | E70: =IF($A70="","",SUMIFS(FichaTecnica_CustoTotal,FichaTecnica_Produto,$A70)) | F70: =IF($A70="","",IFERROR($E70/(1-Perdas),$E70)) | G70: =IF($A70="","",IFERROR(INDEX(Rateio_CustoFixoPorVendaLinha,MATCH(LojaSelecionada,Rateio_LojasHeader,0)),0)) | H70: =IF($A70="","",$F70+$G70) | I70: =IF($A70="","",IFERROR($H70/(1-MargemLiquidaDesejada-Impostos-TaxaCartao-Comissao),"Ajustar parâmetros")) | J70: =IF(OR($A70="",$C70=""),"",IFERROR($F70/$C70,"")) | K70: =IF(OR($A70="",$C70=""),"",IFERROR(($C70-$H70-$C70*(Impostos+TaxaCartao+Comissao))/$C70,"")) | L70: =IF(OR($A70="",$C70=""),"",$C70-$H70-$C70*(Impostos+TaxaCartao+Comissao)) | M70: =IF(OR($A70="",$C70="",NOT(ISNUMBER($I70))),"",$C70-$I70) | N70: =IF(OR($A70="",$K70=""),"",IF($K70>=MargemLiquidaDesejada,"🟢 Margem Saudável",IF($K70>=MargemLiquidaDesejada*0.8,"🟡 Atenção","🔴 Abaixo da Meta")))
D71: =IF($A71="","",SUMIFS(FichaTecnica_QtdGML,FichaTecnica_Produto,$A71)) | E71: =IF($A71="","",SUMIFS(FichaTecnica_CustoTotal,FichaTecnica_Produto,$A71)) | F71: =IF($A71="","",IFERROR($E71/(1-Perdas),$E71)) | G71: =IF($A71="","",IFERROR(INDEX(Rateio_CustoFixoPorVendaLinha,MATCH(LojaSelecionada,Rateio_LojasHeader,0)),0)) | H71: =IF($A71="","",$F71+$G71) | I71: =IF($A71="","",IFERROR($H71/(1-MargemLiquidaDesejada-Impostos-TaxaCartao-Comissao),"Ajustar parâmetros")) | J71: =IF(OR($A71="",$C71=""),"",IFERROR($F71/$C71,"")) | K71: =IF(OR($A71="",$C71=""),"",IFERROR(($C71-$H71-$C71*(Impostos+TaxaCartao+Comissao))/$C71,"")) | L71: =IF(OR($A71="",$C71=""),"",$C71-$H71-$C71*(Impostos+TaxaCartao+Comissao)) | M71: =IF(OR($A71="",$C71="",NOT(ISNUMBER($I71))),"",$C71-$I71) | N71: =IF(OR($A71="",$K71=""),"",IF($K71>=MargemLiquidaDesejada,"🟢 Margem Saudável",IF($K71>=MargemLiquidaDesejada*0.8,"🟡 Atenção","🔴 Abaixo da Meta")))
D72: =IF($A72="","",SUMIFS(FichaTecnica_QtdGML,FichaTecnica_Produto,$A72)) | E72: =IF($A72="","",SUMIFS(FichaTecnica_CustoTotal,FichaTecnica_Produto,$A72)) | F72: =IF($A72="","",IFERROR($E72/(1-Perdas),$E72)) | G72: =IF($A72="","",IFERROR(INDEX(Rateio_CustoFixoPorVendaLinha,MATCH(LojaSelecionada,Rateio_LojasHeader,0)),0)) | H72: =IF($A72="","",$F72+$G72) | I72: =IF($A72="","",IFERROR($H72/(1-MargemLiquidaDesejada-Impostos-TaxaCartao-Comissao),"Ajustar parâmetros")) | J72: =IF(OR($A72="",$C72=""),"",IFERROR($F72/$C72,"")) | K72: =IF(OR($A72="",$C72=""),"",IFERROR(($C72-$H72-$C72*(Impostos+TaxaCartao+Comissao))/$C72,"")) | L72: =IF(OR($A72="",$C72=""),"",$C72-$H72-$C72*(Impostos+TaxaCartao+Comissao)) | M72: =IF(OR($A72="",$C72="",NOT(ISNUMBER($I72))),"",$C72-$I72) | N72: =IF(OR($A72="",$K72=""),"",IF($K72>=MargemLiquidaDesejada,"🟢 Margem Saudável",IF($K72>=MargemLiquidaDesejada*0.8,"🟡 Atenção","🔴 Abaixo da Meta")))
D73: =IF($A73="","",SUMIFS(FichaTecnica_QtdGML,FichaTecnica_Produto,$A73)) | E73: =IF($A73="","",SUMIFS(FichaTecnica_CustoTotal,FichaTecnica_Produto,$A73)) | F73: =IF($A73="","",IFERROR($E73/(1-Perdas),$E73)) | G73: =IF($A73="","",IFERROR(INDEX(Rateio_CustoFixoPorVendaLinha,MATCH(LojaSelecionada,Rateio_LojasHeader,0)),0)) | H73: =IF($A73="","",$F73+$G73) | I73: =IF($A73="","",IFERROR($H73/(1-MargemLiquidaDesejada-Impostos-TaxaCartao-Comissao),"Ajustar parâmetros")) | J73: =IF(OR($A73="",$C73=""),"",IFERROR($F73/$C73,"")) | K73: =IF(OR($A73="",$C73=""),"",IFERROR(($C73-$H73-$C73*(Impostos+TaxaCartao+Comissao))/$C73,"")) | L73: =IF(OR($A73="",$C73=""),"",$C73-$H73-$C73*(Impostos+TaxaCartao+Comissao)) | M73: =IF(OR($A73="",$C73="",NOT(ISNUMBER($I73))),"",$C73-$I73) | N73: =IF(OR($A73="",$K73=""),"",IF($K73>=MargemLiquidaDesejada,"🟢 Margem Saudável",IF($K73>=MargemLiquidaDesejada*0.8,"🟡 Atenção","🔴 Abaixo da Meta")))
D74: =IF($A74="","",SUMIFS(FichaTecnica_QtdGML,FichaTecnica_Produto,$A74)) | E74: =IF($A74="","",SUMIFS(FichaTecnica_CustoTotal,FichaTecnica_Produto,$A74)) | F74: =IF($A74="","",IFERROR($E74/(1-Perdas),$E74)) | G74: =IF($A74="","",IFERROR(INDEX(Rateio_CustoFixoPorVendaLinha,MATCH(LojaSelecionada,Rateio_LojasHeader,0)),0)) | H74: =IF($A74="","",$F74+$G74) | I74: =IF($A74="","",IFERROR($H74/(1-MargemLiquidaDesejada-Impostos-TaxaCartao-Comissao),"Ajustar parâmetros")) | J74: =IF(OR($A74="",$C74=""),"",IFERROR($F74/$C74,"")) | K74: =IF(OR($A74="",$C74=""),"",IFERROR(($C74-$H74-$C74*(Impostos+TaxaCartao+Comissao))/$C74,"")) | L74: =IF(OR($A74="",$C74=""),"",$C74-$H74-$C74*(Impostos+TaxaCartao+Comissao)) | M74: =IF(OR($A74="",$C74="",NOT(ISNUMBER($I74))),"",$C74-$I74) | N74: =IF(OR($A74="",$K74=""),"",IF($K74>=MargemLiquidaDesejada,"🟢 Margem Saudável",IF($K74>=MargemLiquidaDesejada*0.8,"🟡 Atenção","🔴 Abaixo da Meta")))
... D90: =IF($A90="","",SUMIFS(FichaTecnica_QtdGML,FichaTecnica_Produto,$A90)) | E90: =IF($A90="","",SUMIFS(FichaTecnica_CustoTotal,FichaTecnica_Produto,$A90)) | F90: =IF($A90="","",IFERROR($E90/(1-Perdas),$E90)) | G90: =IF($A90="","",IFERROR(INDEX(Rateio_CustoFixoPorVendaLinha,MATCH(LojaSelecionada,Rateio_LojasHeader,0)),0)) | H90: =IF($A90="","",$F90+$G90) | I90: =IF($A90="","",IFERROR($H90/(1-MargemLiquidaDesejada-Impostos-TaxaCartao-Comissao),"Ajustar parâmetros")) | J90: =IF(OR($A90="",$C90=""),"",IFERROR($F90/$C90,"")) | K90: =IF(OR($A90="",$C90=""),"",IFERROR(($C90-$H90-$C90*(Impostos+TaxaCartao+Comissao))/$C90,"")) | L90: =IF(OR($A90="",$C90=""),"",$C90-$H90-$C90*(Impostos+TaxaCartao+Comissao)) | M90: =IF(OR($A90="",$C90="",NOT(ISNUMBER($I90))),"",$C90-$I90) | N90: =IF(OR($A90="",$K90=""),"",IF($K90>=MargemLiquidaDesejada,"🟢 Margem Saudável",IF($K90>=MargemLiquidaDesejada*0.8,"🟡 Atenção","🔴 Abaixo da Meta")))

Sheet Rateio
A1: 🏠 RATEIO — Custos Fixos por Loja/Quiosque
A2: Uma coluna por loja. Como matéria-prima, coberturas e embalagens têm o mesmo preço em todas as lojas (compra centralizada da franquia), só o que muda de loja para loja é esta tabela. Renomeie os cabeçalhos (linha 4) com o nome de cada loja/quiosque — a lista em Configurações acompanha automaticamente.
A4: Item de Custo Fixo (R$/mês) | B4: Loja 1 | C4: Loja 2 | D4: Loja 3 | E4: Loja 4 | F4: Loja 5 | G4: Loja 6
A5: Aluguel | B5: 6505.5
A6: Energia | B6: 300
A7: Água | B7: 200
A8: Internet | B8: 120 | C8: 120 | D8: 120 | E8: 120 | F8: 120
A9: Marketing / Royalties de Franquia | B9: 0 | C9: 0 | D9: 0 | E9: 0 | F9: 0
A10: Sistema | B10: 383 | C10: 383 | D10: 383 | E10: 383 | F10: 383
A11: Contabilidade | B11: 1500 | C11: 1500 | D11: 1500 | E11: 1500 | F11: 1500
A12: Funcionários (Folha + Encargos) | B12: 17661.3
A13: Pró-labore | B13: 0
A14: Outros | B14: 0
A22: Total de Custos Fixos Mensais (R$) | B22: =SUM(B5:B20) -> 26669.8 | C22: =SUM(C5:C20) -> 2003 | D22: =SUM(D5:D20) -> 2003 | E22: =SUM(E5:E20) -> 2003 | F22: =SUM(F5:F20) -> 2003 | G22: =SUM(G5:G20) -> 0
A24: Volume Médio Mensal de Vendas (unid) | B24: 3600
A26: Custo Fixo Rateado por Venda (R$) | B26: =IFERROR(B22/B24,0) -> 7.4082778 | C26: =IFERROR(C22/C24,0) -> 0 | D26: =IFERROR(D22/D24,0) -> 0 | E26: =IFERROR(E22/E24,0) -> 0 | F26: =IFERROR(F22/F24,0) -> 0 | G26: =IFERROR(G22/G24,0) -> 0

Sheet Precificacao
A1: 🧮 PRECIFICAÇÃO — Calculadora de Preço Ideal
A2: Escolha um produto e informe a margem desejada e o CMV máximo aceitável. Usa o custo fixo da Loja Ativa definida em Configurações.
A4: Entradas | B4: Valor | C4: Observação
A5: Produto | B5: Açaí em Ondas 200ml | C5: Selecione na lista (mesmos produtos da aba Receitas).
A6: Margem Líquida Desejada (%) | B6: 0.15 | C6: Pré-preenchido com a meta de Configurações — pode ser sobrescrito para simular outra meta.
A7: CMV Máximo Aceitável (%) | B7: 0.35 | C7: Limite de referência para alertar se o CMV do produto está alto.
A9: Resultado | B9: Valor | C9: Observação
A10: Custo Insumos c/ Perdas (R$) | B10: =IFERROR(INDEX(Receitas_CustoInsumosPerdas,MATCH($B$5,Receitas_Produto,0)),0) -> 4.310341 | C10: Vem direto da aba Receitas.
A11: Custo Fixo Rateado (R$) — Loja Ativa | B11: =IFERROR(INDEX(Receitas_CustoFixo,MATCH($B$5,Receitas_Produto,0)),0) -> 7.4082778 | C11: Da loja selecionada em Configurações.
A12: Custo Total Unitário (R$) | B12: =B10+B11 -> 11.718619
A13: Preço Ideal (R$) | B13: =IFERROR(B12/(1-$B$6-Impostos-TaxaCartao-Comissao),"Ajustar parâmetros") -> 18.168401 | C13: Preço que garante a margem desejada após impostos, cartão e comissão.
A14: CMV Atual (%) | B14: =IF(ISNUMBER(B13),IFERROR(B10/B13,""),"") -> 0.23724383 | C14: Comparar com o CMV Máximo Aceitável informado acima.
A15: Markup | B15: =IF(ISNUMBER(B13),IFERROR(B13/B10,""),"") -> 4.2150728
A16: Lucro Bruto (R$) | B16: =IF(ISNUMBER(B13),B13-B10,"") -> 13.85806 | C16: Preço Ideal − Custo de Insumos.
A17: Lucro Líquido (R$) | B17: =IF(ISNUMBER(B13),B13-B12-B13*(Impostos+TaxaCartao+Comissao),"") -> 2.7252602 | C17: Após custo fixo, impostos, cartão e comissão.
A18: Margem Líquida Obtida (%) | B18: =IF(ISNUMBER(B13),IFERROR(B17/B13,""),"") -> 0.15
A19: Status do CMV | B19: =IF(ISNUMBER(B14),IF(B14<=$B$7,"🟢 Dentro do limite","🔴 Acima do CMV máximo"),"") -> 🟢 Dentro do limite

Sheet Dashboard
A1: 📊 DASHBOARD — Visão Gerencial de CMV, Margem e Rentabilidade
A2: Indicadores da Loja Ativa (Configurações), atualizados a partir da aba Receitas.
A4: CMV Médio | D4: Margem Líquida Média | G4: Produto c/ Maior Margem | J4: Produto c/ Menor Margem
A5: =IFERROR(AVERAGEIF(Receitas_Produto,"<>",Receitas_CMV),"") -> 0.26758324 | D5: =IFERROR(AVERAGEIF(Receitas_Produto,"<>",Receitas_Margem),"") -> 0.012822255 | G5: =IFERROR(INDEX(Receitas_Produto,MATCH(MAX(Receitas_Margem),Receitas_Margem,0)),"") -> Protein Shake | J5: =IFERROR(INDEX(Receitas_Produto,MATCH(MIN(Receitas_Margem),Receitas_Margem,0)),"") -> Refrigerante Lata 350ml
A9: Participação por Categoria de Insumo
A10: Categoria | B10: Custo Total (R$)
A11: Bases (Produção Própria) | B11: =SUMIFS(FichaTecnica_CustoTotal,FichaTecnica_Categoria,"Bases (Produção Própria)") -> 195.03
A12: Coberturas (30g) | B12: =SUMIFS(FichaTecnica_CustoTotal,FichaTecnica_Categoria,"Coberturas (30g)") -> 43.788438
A13: Linha Premium (Comprada) | B13: =SUMIFS(FichaTecnica_CustoTotal,FichaTecnica_Categoria,"Linha Premium (Comprada)") -> 103
A14: Embalagens | B14: =SUMIFS(FichaTecnica_CustoTotal,FichaTecnica_Categoria,"Embalagens") -> 9.85284
A15: Consumíveis | B15: =SUMIFS(FichaTecnica_CustoTotal,FichaTecnica_Categoria,"Consumíveis") -> 4.1272
A16: Bebidas | B16: =SUMIFS(FichaTecnica_CustoTotal,FichaTecnica_Categoria,"Bebidas") -> 0
A17: Limpeza | B17: =SUMIFS(FichaTecnica_CustoTotal,FichaTecnica_Categoria,"Limpeza") -> 0
A19: Estrutura de Custo Total (todos os produtos)
A20: Componente | B20: Total (R$)
A21: Insumos (c/ Perdas) | B21: =SUMIF(Receitas_Produto,"<>",Receitas_CustoInsumosPerdas) -> 366.80256
A22: Custo Fixo Rateado | B22: =SUMIF(Receitas_Produto,"<>",Receitas_CustoFixo) -> 429.68011
A24: Margem e Lucro por Produto
A25: Produto | B25: Margem Real (%) | C25: CMV Real (%) | D25: Preço Praticado (R$) | E25: Lucro Líquido Real (R$)
A26: =Receitas!A5 -> Açaí em Ondas 200ml | B26: =Receitas!K5 -> 0.1015906 | C26: =Receitas!J5 -> 0.25504976 | D26: =Receitas!C5 -> 16.9 | E26: =Receitas!L5 -> 1.7168812
A27: =Receitas!A6 -> Açaí em Ondas 300ml | B27: =Receitas!K6 -> 0.20957794 | C27: =Receitas!J6 -> 0.26191648 | D27: =Receitas!C6 -> 22.9 | E27: =Receitas!L6 -> 4.7993348
A28: =Receitas!A7 -> Açaí em Ondas 500ml | B28: =Receitas!K7 -> 0.22940643 | C28: =Receitas!J7 -> 0.31782508 | D28: =Receitas!C7 -> 29.9 | E28: =Receitas!L7 -> 6.8592524
A29: =Receitas!A8 -> Fast Classic 200ml | B29: =Receitas!K8 -> 0.040192447 | C29: =Receitas!J8 -> 0.31644792 | D29: =Receitas!C8 -> 16.9 | E29: =Receitas!L8 -> 0.67925236
A30: =Receitas!A9 -> Fast Classic 300ml | B30: =Receitas!K9 -> 0.16426664 | C30: =Receitas!J9 -> 0.30722778 | D30: =Receitas!C9 -> 22.9 | E30: =Receitas!L9 -> 3.761706
A31: =Receitas!A10 -> Fast Classic 500ml | B31: =Receitas!K10 -> 0.19470313 | C31: =Receitas!J10 -> 0.35252839 | D31: =Receitas!C10 -> 29.9 | E31: =Receitas!L10 -> 5.8216235
A32: =Receitas!A11 -> Power 200ml | B32: =Receitas!K11 -> 0.060725602 | C32: =Receitas!J11 -> 0.29591477 | D32: =Receitas!C11 -> 16.9 | E32: =Receitas!L11 -> 1.0262627
A33: =Receitas!A12 -> Power 300ml | B33: =Receitas!K12 -> 0.17941992 | C33: =Receitas!J12 -> 0.2920745 | D33: =Receitas!C12 -> 22.9 | E33: =Receitas!L12 -> 4.1087163
A34: =Receitas!A13 -> Power 500ml | B34: =Receitas!K13 -> 0.20630882 | C34: =Receitas!J13 -> 0.34092269 | D34: =Receitas!C13 -> 29.9 | E34: =Receitas!L13 -> 6.1686338
A35: =Receitas!A14 -> Choco Nuts 200ml | B35: =Receitas!K14 -> 0.018868148 | C35: =Receitas!J14 -> 0.33777222 | D35: =Receitas!C14 -> 16.9 | E35: =Receitas!L14 -> 0.31887171
A36: =Receitas!A15 -> Choco Nuts 300ml | B36: =Receitas!K15 -> 0.14852949 | C36: =Receitas!J15 -> 0.32296493 | D36: =Receitas!C15 -> 22.9 | E36: =Receitas!L15 -> 3.4013253
A37: =Receitas!A16 -> Choco Nuts 500ml | B37: =Receitas!K16 -> 0.18265026 | C37: =Receitas!J16 -> 0.36458125 | D37: =Receitas!C16 -> 29.9 | E37: =Receitas!L16 -> 5.4612428
... A83: =Receitas!A62 -> Suco de Açaí 200ml | B83: =Receitas!K62 -> -0.43971296 | C83: =Receitas!J62 -> 0 | D83: =Receitas!C62 -> 6 | E83: =Receitas!L62 -> -2.6382778

Sheet Simulador
A1: 🔄 SIMULADOR — Impacto de Variação de Preços no CMV e na Margem
A2: Escolha um produto e teste novos preços para Açaí, Banana, Whey Protein e a embalagem principal (copo) usada nele. Recalcula o novo CMV, a nova margem e o novo preço ideal na hora.
A4: Produto a simular | B4: Açaí em Ondas 200ml
A6: Insumo | B6: Preço Atual (R$/g,ml,un) | C6: Novo Preço (simulado) | D6: Observação
A7: Açaí | B7: =IFERROR(INDEX(Insumos_CustoUnit,MATCH("Açaí",Insumos_Ingrediente,0)),0) -> 0.0165 | C7: =B7 -> 0.0165
A8: Banana | B8: =IFERROR(INDEX(Insumos_CustoUnit,MATCH("Banana",Insumos_Ingrediente,0)),0) -> 0.0023076923 | C8: =B8 -> 0.0023076923
A9: Whey Protein | B9: =IFERROR(INDEX(Insumos_CustoUnit,MATCH("Whey Protein",Insumos_Ingrediente,0)),0) -> 0 | C9: =B9 -> 0
A10: Embalagem Principal (copo) | B10: =IFERROR(SUMPRODUCT((FichaTecnica_Produto=$B$4)*(FichaTecnica_FlagEmbalagem=1)*FichaTecnica_CustoUnit)/SUMPRODUCT((FichaTecnica_Produto=$B$4)*(FichaTecnica_FlagEmbalagem=1)),0) -> 0.1668 | C10: =B10 -> 0.1668 | D10: Aplica-se ao copo (200/300/500ml ou Milkshake) usado no produto selecionado.
A12: Resultado da Simulação | B12: Antes | C12: Depois (simulado) | D12: Variação
A13: Custo Insumos c/ Perdas (R$) | B13: =IFERROR(INDEX(Receitas_CustoInsumosPerdas,MATCH($B$4,Receitas_Produto,0)),0) -> 4.310341 | C13: =IFERROR(SUMPRODUCT((FichaTecnica_Produto=$B$4)*(FichaTecnica_CustoUnit*FichaTecnica_Qtd+FichaTecnica_FlagAcai*FichaTecnica_Qtd*($C$7-FichaTecnica_CustoUnit)+FichaTecnica_FlagBanana*FichaTecnica_Qtd*($C$8-FichaTecnica_CustoUnit)+FichaTecnica_FlagWhey*FichaTecnica_Qtd*($C$9-FichaTecnica_CustoUnit)+FichaTecnica_FlagEmbalagem*FichaTecnica_Qtd*($C$10-FichaTecnica_CustoUnit)))/(1-Perdas),0) -> 4.310341 | D13: =C13-B13 -> 0
A14: Custo Fixo Rateado (R$) — Loja Ativa | B14: =IFERROR(INDEX(Receitas_CustoFixo,MATCH($B$4,Receitas_Produto,0)),0) -> 7.4082778 | C14: =B14 -> 7.4082778 | D14: =C14-B14 -> 0
A15: Custo Total Unitário (R$) | B15: =B13+B14 -> 11.718619 | C15: =C13+C14 -> 11.718619 | D15: =C15-B15 -> 0
A16: Preço Ideal (R$) | B16: =IFERROR(B15/(1-MargemLiquidaDesejada-Impostos-TaxaCartao-Comissao),0) -> 18.168401 | C16: =IFERROR(C15/(1-MargemLiquidaDesejada-Impostos-TaxaCartao-Comissao),0) -> 18.168401 | D16: =C16-B16 -> 0
A17: CMV (%) | B17: =IFERROR(B13/B16,"") -> 0.23724383 | C17: =IFERROR(C13/C16,"") -> 0.23724383 | D17: =IF(OR(B17="",C17=""),"",C17-B17) -> 0
A18: Margem Líquida (%) | B18: =IFERROR((B16-B15-B16*(Impostos+TaxaCartao+Comissao))/B16,"") -> 0.15 | C18: =IFERROR((C16-C15-C16*(Impostos+TaxaCartao+Comissao))/C16,"") -> 0.15 | D18: =IF(OR(B18="",C18=""),"",C18-B18) -> 0

Sheet Listas
A1: Produtos | B1: Categorias_Insumo | C1: Status
A2: Açaí em Ondas 200ml | B2: Bases (Produção Própria) | C2: Ativo
A3: Açaí em Ondas 300ml | B3: Coberturas (30g) | C3: Inativo
A4: Açaí em Ondas 500ml | B4: Linha Premium (Comprada)
A5: Fast Classic 200ml | B5: Embalagens
A6: Fast Classic 300ml | B6: Consumíveis
A7: Fast Classic 500ml | B7: Bebidas
A8: Power 200ml | B8: Limpeza
A9: Power 300ml
A10: Power 500ml
A11: Choco Nuts 200ml
A12: Choco Nuts 300ml
A13: Choco Nuts 500ml
A14: Trupe Fast 200ml
A15: Trupe Fast 300ml
A16: Trupe Fast 500ml
A17: Berry 200ml
A18: Berry 300ml
A19: Berry 500ml
A20: Granola Fit 200ml
... A59: Suco de Açaí 200ml

Sheet Linha Premium
A1: 🥤 LINHA PREMIUM — Potes Prontos (Fábrica) — Preço x Custo por Tamanho
A2: Potes comprados prontos direto da fábrica. Preencha o custo de compra na aba Insumos (categoria 'Linha Premium (Comprada)').
A4: Produto | B4: 250ml | F4: 500ml
B5: Preço (R$) | C5: Custo Total (R$) | D5: CMV (%) | E5: Margem (%) | F5: Preço (R$) | G5: Custo Total (R$) | H5: CMV (%) | I5: Margem (%)
A6: Açaí Zero Açúcar | B6: =IFERROR(INDEX(Receitas_PrecoPraticado,MATCH("Açaí Zero Açúcar 250ml",Receitas_Produto,0)),"") -> 23 | C6: =IFERROR(INDEX(Receitas_CustoTotalUnit,MATCH("Açaí Zero Açúcar 250ml",Receitas_Produto,0)),"") -> 19.876113 | D6: =IFERROR(INDEX(Receitas_CMV,MATCH("Açaí Zero Açúcar 250ml",Receitas_Produto,0)),"") -> 0.54207978 | E6: =IFERROR(INDEX(Receitas_Margem,MATCH("Açaí Zero Açúcar 250ml",Receitas_Produto,0)),"") -> -0.069178819 | F6: =IFERROR(INDEX(Receitas_PrecoPraticado,MATCH("Açaí Zero Açúcar 500ml",Receitas_Produto,0)),"") -> 38 | G6: =IFERROR(INDEX(Receitas_CustoTotalUnit,MATCH("Açaí Zero Açúcar 500ml",Receitas_Produto,0)),"") -> 23.999824 | H6: =IFERROR(INDEX(Receitas_CMV,MATCH("Açaí Zero Açúcar 500ml",Receitas_Produto,0)),"") -> 0.43661964 | I6: =IFERROR(INDEX(Receitas_Margem,MATCH("Açaí Zero Açúcar 500ml",Receitas_Produto,0)),"") -> 0.16342568
A7: Açaí Puro | B7: =IFERROR(INDEX(Receitas_PrecoPraticado,MATCH("Açaí Puro 250ml",Receitas_Produto,0)),"") -> 18 | C7: =IFERROR(INDEX(Receitas_CustoTotalUnit,MATCH("Açaí Puro 250ml",Receitas_Produto,0)),"") -> 17.814257 | D7: =IFERROR(INDEX(Receitas_CMV,MATCH("Açaí Puro 250ml",Receitas_Produto,0)),"") -> 0.57810997 | E7: =IFERROR(INDEX(Receitas_Margem,MATCH("Açaí Puro 250ml",Receitas_Produto,0)),"") -> -0.19468095 | F7: =IFERROR(INDEX(Receitas_PrecoPraticado,MATCH("Açaí Puro 500ml",Receitas_Produto,0)),"") -> 27.5 | G7: =IFERROR(INDEX(Receitas_CustoTotalUnit,MATCH("Açaí Puro 500ml",Receitas_Produto,0)),"") -> 22.968896 | H7: =IFERROR(INDEX(Receitas_CMV,MATCH("Açaí Puro 500ml",Receitas_Produto,0)),"") -> 0.56584067 | I7: =IFERROR(INDEX(Receitas_Margem,MATCH("Açaí Puro 500ml",Receitas_Produto,0)),"") -> -0.040232594
A8: Açaí Banana | B8: =IFERROR(INDEX(Receitas_PrecoPraticado,MATCH("Açaí Banana 250ml",Receitas_Produto,0)),"") -> 18 | C8: =IFERROR(INDEX(Receitas_CustoTotalUnit,MATCH("Açaí Banana 250ml",Receitas_Produto,0)),"") -> 17.814257 | D8: =IFERROR(INDEX(Receitas_CMV,MATCH("Açaí Banana 250ml",Receitas_Produto,0)),"") -> 0.57810997 | E8: =IFERROR(INDEX(Receitas_Margem,MATCH("Açaí Banana 250ml",Receitas_Produto,0)),"") -> -0.19468095 | F8: =IFERROR(INDEX(Receitas_PrecoPraticado,MATCH("Açaí Banana 500ml",Receitas_Produto,0)),"") -> 27.5 | G8: =IFERROR(INDEX(Receitas_CustoTotalUnit,MATCH("Açaí Banana 500ml",Receitas_Produto,0)),"") -> 22.968896 | H8: =IFERROR(INDEX(Receitas_CMV,MATCH("Açaí Banana 500ml",Receitas_Produto,0)),"") -> 0.56584067 | I8: =IFERROR(INDEX(Receitas_Margem,MATCH("Açaí Banana 500ml",Receitas_Produto,0)),"") -> -0.040232594
A9: Açaí Morango | B9: =IFERROR(INDEX(Receitas_PrecoPraticado,MATCH("Açaí Morango 250ml",Receitas_Produto,0)),"") -> 18 | C9: =IFERROR(INDEX(Receitas_CustoTotalUnit,MATCH("Açaí Morango 250ml",Receitas_Produto,0)),"") -> 17.814257 | D9: =IFERROR(INDEX(Receitas_CMV,MATCH("Açaí Morango 250ml",Receitas_Produto,0)),"") -> 0.57810997 | E9: =IFERROR(INDEX(Receitas_Margem,MATCH("Açaí Morango 250ml",Receitas_Produto,0)),"") -> -0.19468095 | F9: =IFERROR(INDEX(Receitas_PrecoPraticado,MATCH("Açaí Morango 500ml",Receitas_Produto,0)),"") -> 27.5 | G9: =IFERROR(INDEX(Receitas_CustoTotalUnit,MATCH("Açaí Morango 500ml",Receitas_Produto,0)),"") -> 22.968896 | H9: =IFERROR(INDEX(Receitas_CMV,MATCH("Açaí Morango 500ml",Receitas_Produto,0)),"") -> 0.56584067 | I9: =IFERROR(INDEX(Receitas_Margem,MATCH("Açaí Morango 500ml",Receitas_Produto,0)),"") -> -0.040232594

Sheet Linha Tradicional
A1: 🍨 LINHA TRADICIONAL — Açaí e Cupuaçu Puros — Preço x Custo por Tamanho
A2: Sem coberturas, só a base. Mesma comparação P/M/G das outras linhas.
A4: Produto | B4: 200ml | F4: 300ml | J4: 500ml
B5: Preço (R$) | C5: Custo Total (R$) | D5: CMV (%) | E5: Margem (%) | F5: Preço (R$) | G5: Custo Total (R$) | H5: CMV (%) | I5: Margem (%) | J5: Preço (R$) | K5: Custo Total (R$) | L5: CMV (%) | M5: Margem (%)
A6: Açaí Tradicional | B6: =IFERROR(INDEX(Receitas_PrecoPraticado,MATCH("Açaí Tradicional 200ml",Receitas_Produto,0)),"") -> 16.9 | C6: =IFERROR(INDEX(Receitas_CustoTotalUnit,MATCH("Açaí Tradicional 200ml",Receitas_Produto,0)),"") -> 10.653536 | D6: =IFERROR(INDEX(Receitas_CMV,MATCH("Açaí Tradicional 200ml",Receitas_Produto,0)),"") -> 0.19202708 | E6: =IFERROR(INDEX(Receitas_Margem,MATCH("Açaí Tradicional 200ml",Receitas_Produto,0)),"") -> 0.16461328 | F6: =IFERROR(INDEX(Receitas_PrecoPraticado,MATCH("Açaí Tradicional 300ml",Receitas_Produto,0)),"") -> 22.9 | G6: =IFERROR(INDEX(Receitas_CustoTotalUnit,MATCH("Açaí Tradicional 300ml",Receitas_Produto,0)),"") -> 12.341082 | H6: =IFERROR(INDEX(Receitas_CMV,MATCH("Açaí Tradicional 300ml",Receitas_Produto,0)),"") -> 0.21540629 | I6: =IFERROR(INDEX(Receitas_Margem,MATCH("Açaí Tradicional 300ml",Receitas_Produto,0)),"") -> 0.25608813 | J6: =IFERROR(INDEX(Receitas_PrecoPraticado,MATCH("Açaí Tradicional 500ml",Receitas_Produto,0)),"") -> 29.9 | K6: =IFERROR(INDEX(Receitas_CustoTotalUnit,MATCH("Açaí Tradicional 500ml",Receitas_Produto,0)),"") -> 15.846164 | L6: =IFERROR(INDEX(Receitas_CMV,MATCH("Açaí Tradicional 500ml",Receitas_Produto,0)),"") -> 0.28220357 | M6: =IFERROR(INDEX(Receitas_Margem,MATCH("Açaí Tradicional 500ml",Receitas_Produto,0)),"") -> 0.26502795
A7: Cupuaçu Tradicional | B7: =IFERROR(INDEX(Receitas_PrecoPraticado,MATCH("Cupuaçu Tradicional 200ml",Receitas_Produto,0)),"") -> 16.9 | C7: =IFERROR(INDEX(Receitas_CustoTotalUnit,MATCH("Cupuaçu Tradicional 200ml",Receitas_Produto,0)),"") -> 10.653536 | D7: =IFERROR(INDEX(Receitas_CMV,MATCH("Cupuaçu Tradicional 200ml",Receitas_Produto,0)),"") -> 0.19202708 | E7: =IFERROR(INDEX(Receitas_Margem,MATCH("Cupuaçu Tradicional 200ml",Receitas_Produto,0)),"") -> 0.16461328 | F7: =IFERROR(INDEX(Receitas_PrecoPraticado,MATCH("Cupuaçu Tradicional 300ml",Receitas_Produto,0)),"") -> 22.9 | G7: =IFERROR(INDEX(Receitas_CustoTotalUnit,MATCH("Cupuaçu Tradicional 300ml",Receitas_Produto,0)),"") -> 12.341082 | H7: =IFERROR(INDEX(Receitas_CMV,MATCH("Cupuaçu Tradicional 300ml",Receitas_Produto,0)),"") -> 0.21540629 | I7: =IFERROR(INDEX(Receitas_Margem,MATCH("Cupuaçu Tradicional 300ml",Receitas_Produto,0)),"") -> 0.25608813 | J7: =IFERROR(INDEX(Receitas_PrecoPraticado,MATCH("Cupuaçu Tradicional 500ml",Receitas_Produto,0)),"") -> 29.9 | K7: =IFERROR(INDEX(Receitas_CustoTotalUnit,MATCH("Cupuaçu Tradicional 500ml",Receitas_Produto,0)),"") -> 15.846164 | L7: =IFERROR(INDEX(Receitas_CMV,MATCH("Cupuaçu Tradicional 500ml",Receitas_Produto,0)),"") -> 0.28220357 | M7: =IFERROR(INDEX(Receitas_Margem,MATCH("Cupuaçu Tradicional 500ml",Receitas_Produto,0)),"") -> 0.26502795

Sheet Toppings
A1: 🍫 TOPPINGS — Acompanhamentos, Caldas Especiais e Adicionais Premium
A2: Fornecedor, Unidade e Preço Kg/L vêm direto da aba Insumos — preencha lá de acordo com a nota fiscal. Valor Final é o preço cobrado do cliente pela porção (30g/30ml) — ajuste na coluna azul.
A4: Acompanhamentos — porção vendida a R$ 3,00
A5: Produto | B5: Fornecedor | C5: Unidade | D5: Preço Kg/L (R$) | E5: Porção | F5: Valor Final (R$)
A6: Leite em pó | B6: =IFERROR(IF(INDEX(Insumos_Fornecedor,MATCH("Leite em pó",Insumos_Ingrediente,0))=0,"",INDEX(Insumos_Fornecedor,MATCH("Leite em pó",Insumos_Ingrediente,0))),"") | C6: =IFERROR(INDEX(Insumos_Unidade,MATCH("Leite em pó",Insumos_Ingrediente,0)),"") -> g | D6: =IFERROR(IF($C6="un",INDEX(Insumos_CustoUnit,MATCH("Leite em pó",Insumos_Ingrediente,0)),INDEX(Insumos_CustoUnit,MATCH("Leite em pó",Insumos_Ingrediente,0))*1000),0) -> 33.55 | E6: =IF($C6="g","30g",IF($C6="ml","30ml","1 unidade")) -> 30g | F6: 3
A7: Banana | B7: =IFERROR(IF(INDEX(Insumos_Fornecedor,MATCH("Banana",Insumos_Ingrediente,0))=0,"",INDEX(Insumos_Fornecedor,MATCH("Banana",Insumos_Ingrediente,0))),"") | C7: =IFERROR(INDEX(Insumos_Unidade,MATCH("Banana",Insumos_Ingrediente,0)),"") -> g | D7: =IFERROR(IF($C7="un",INDEX(Insumos_CustoUnit,MATCH("Banana",Insumos_Ingrediente,0)),INDEX(Insumos_CustoUnit,MATCH("Banana",Insumos_Ingrediente,0))*1000),0) -> 2.3076923 | E7: =IF($C7="g","30g",IF($C7="ml","30ml","1 unidade")) -> 30g | F7: 3
A8: Morango | B8: =IFERROR(IF(INDEX(Insumos_Fornecedor,MATCH("Morango",Insumos_Ingrediente,0))=0,"",INDEX(Insumos_Fornecedor,MATCH("Morango",Insumos_Ingrediente,0))),"") | C8: =IFERROR(INDEX(Insumos_Unidade,MATCH("Morango",Insumos_Ingrediente,0)),"") -> g | D8: =IFERROR(IF($C8="un",INDEX(Insumos_CustoUnit,MATCH("Morango",Insumos_Ingrediente,0)),INDEX(Insumos_CustoUnit,MATCH("Morango",Insumos_Ingrediente,0))*1000),0) -> 16.5 | E8: =IF($C8="g","30g",IF($C8="ml","30ml","1 unidade")) -> 30g | F8: 5
A9: Granola | B9: =IFERROR(IF(INDEX(Insumos_Fornecedor,MATCH("Granola",Insumos_Ingrediente,0))=0,"",INDEX(Insumos_Fornecedor,MATCH("Granola",Insumos_Ingrediente,0))),"") | C9: =IFERROR(INDEX(Insumos_Unidade,MATCH("Granola",Insumos_Ingrediente,0)),"") -> g | D9: =IFERROR(IF($C9="un",INDEX(Insumos_CustoUnit,MATCH("Granola",Insumos_Ingrediente,0)),INDEX(Insumos_CustoUnit,MATCH("Granola",Insumos_Ingrediente,0))*1000),0) -> 20 | E9: =IF($C9="g","30g",IF($C9="ml","30ml","1 unidade")) -> 30g | F9: 3
A10: Leite condensado | B10: =IFERROR(IF(INDEX(Insumos_Fornecedor,MATCH("Leite condensado",Insumos_Ingrediente,0))=0,"",INDEX(Insumos_Fornecedor,MATCH("Leite condensado",Insumos_Ingrediente,0))),"") | C10: =IFERROR(INDEX(Insumos_Unidade,MATCH("Leite condensado",Insumos_Ingrediente,0)),"") -> g | D10: =IFERROR(IF($C10="un",INDEX(Insumos_CustoUnit,MATCH("Leite condensado",Insumos_Ingrediente,0)),INDEX(Insumos_CustoUnit,MATCH("Leite condensado",Insumos_Ingrediente,0))*1000),0) -> 12.13 | E10: =IF($C10="g","30g",IF($C10="ml","30ml","1 unidade")) -> 30g | F10: 3
A11: Paçoca | B11: =IFERROR(IF(INDEX(Insumos_Fornecedor,MATCH("Paçoca",Insumos_Ingrediente,0))=0,"",INDEX(Insumos_Fornecedor,MATCH("Paçoca",Insumos_Ingrediente,0))),"") | C11: =IFERROR(INDEX(Insumos_Unidade,MATCH("Paçoca",Insumos_Ingrediente,0)),"") -> g | D11: =IFERROR(IF($C11="un",INDEX(Insumos_CustoUnit,MATCH("Paçoca",Insumos_Ingrediente,0)),INDEX(Insumos_CustoUnit,MATCH("Paçoca",Insumos_Ingrediente,0))*1000),0) -> 22.33 | E11: =IF($C11="g","30g",IF($C11="ml","30ml","1 unidade")) -> 30g | F11: 3
A12: Aveia | B12: =IFERROR(IF(INDEX(Insumos_Fornecedor,MATCH("Aveia",Insumos_Ingrediente,0))=0,"",INDEX(Insumos_Fornecedor,MATCH("Aveia",Insumos_Ingrediente,0))),"") | C12: =IFERROR(INDEX(Insumos_Unidade,MATCH("Aveia",Insumos_Ingrediente,0)),"") -> g | D12: =IFERROR(IF($C12="un",INDEX(Insumos_CustoUnit,MATCH("Aveia",Insumos_Ingrediente,0)),INDEX(Insumos_CustoUnit,MATCH("Aveia",Insumos_Ingrediente,0))*1000),0) -> 0 | E12: =IF($C12="g","30g",IF($C12="ml","30ml","1 unidade")) -> 30g | F12: 3
A13: Ovomaltine | B13: =IFERROR(IF(INDEX(Insumos_Fornecedor,MATCH("Ovomaltine",Insumos_Ingrediente,0))=0,"",INDEX(Insumos_Fornecedor,MATCH("Ovomaltine",Insumos_Ingrediente,0))),"") | C13: =IFERROR(INDEX(Insumos_Unidade,MATCH("Ovomaltine",Insumos_Ingrediente,0)),"") -> g | D13: =IFERROR(IF($C13="un",INDEX(Insumos_CustoUnit,MATCH("Ovomaltine",Insumos_Ingrediente,0)),INDEX(Insumos_CustoUnit,MATCH("Ovomaltine",Insumos_Ingrediente,0))*1000),0) -> 53.2 | E13: =IF($C13="g","30g",IF($C13="ml","30ml","1 unidade")) -> 30g | F13: 3
A14: Amendoim Granulado | B14: =IFERROR(IF(INDEX(Insumos_Fornecedor,MATCH("Amendoim Granulado",Insumos_Ingrediente,0))=0,"",INDEX(Insumos_Fornecedor,MATCH("Amendoim Granulado",Insumos_Ingrediente,0))),"") | C14: =IFERROR(INDEX(Insumos_Unidade,MATCH("Amendoim Granulado",Insumos_Ingrediente,0)),"") -> g | D14: =IFERROR(IF($C14="un",INDEX(Insumos_CustoUnit,MATCH("Amendoim Granulado",Insumos_Ingrediente,0)),INDEX(Insumos_CustoUnit,MATCH("Amendoim Granulado",Insumos_Ingrediente,0))*1000),0) -> 20.34 | E14: =IF($C14="g","30g",IF($C14="ml","30ml","1 unidade")) -> 30g | F14: 3
A15: Pastilha de Chocolate | B15: =IFERROR(IF(INDEX(Insumos_Fornecedor,MATCH("Pastilha de Chocolate",Insumos_Ingrediente,0))=0,"",INDEX(Insumos_Fornecedor,MATCH("Pastilha de Chocolate",Insumos_Ingrediente,0))),"") | C15: =IFERROR(INDEX(Insumos_Unidade,MATCH("Pastilha de Chocolate",Insumos_Ingrediente,0)),"") -> g | D15: =IFERROR(IF($C15="un",INDEX(Insumos_CustoUnit,MATCH("Pastilha de Chocolate",Insumos_Ingrediente,0)),INDEX(Insumos_CustoUnit,MATCH("Pastilha de Chocolate",Insumos_Ingrediente,0))*1000),0) -> 29.59 | E15: =IF($C15="g","30g",IF($C15="ml","30ml","1 unidade")) -> 30g | F15: 3
A16: Canudo Wafer | B16: =IFERROR(IF(INDEX(Insumos_Fornecedor,MATCH("Canudo Wafer",Insumos_Ingrediente,0))=0,"",INDEX(Insumos_Fornecedor,MATCH("Canudo Wafer",Insumos_Ingrediente,0))),"") | C16: =IFERROR(INDEX(Insumos_Unidade,MATCH("Canudo Wafer",Insumos_Ingrediente,0)),"") -> un | D16: =IFERROR(IF($C16="un",INDEX(Insumos_CustoUnit,MATCH("Canudo Wafer",Insumos_Ingrediente,0)),INDEX(Insumos_CustoUnit,MATCH("Canudo Wafer",Insumos_Ingrediente,0))*1000),0) -> 0 | E16: =IF($C16="g","30g",IF($C16="ml","30ml","1 unidade")) -> 1 unidade | F16: 3
A18: Caldas Especiais — porção vendida a R$ 5,00
A19: Produto | B19: Fornecedor | C19: Unidade | D19: Preço Kg/L (R$) | E19: Porção | F19: Valor Final (R$)
A20: Calda de Morango | B20: =IFERROR(IF(INDEX(Insumos_Fornecedor,MATCH("Calda de Morango",Insumos_Ingrediente,0))=0,"",INDEX(Insumos_Fornecedor,MATCH("Calda de Morango",Insumos_Ingrediente,0))),"") | C20: =IFERROR(INDEX(Insumos_Unidade,MATCH("Calda de Morango",Insumos_Ingrediente,0)),"") -> ml | D20: =IFERROR(IF($C20="un",INDEX(Insumos_CustoUnit,MATCH("Calda de Morango",Insumos_Ingrediente,0)),INDEX(Insumos_CustoUnit,MATCH("Calda de Morango",Insumos_Ingrediente,0))*1000),0) -> 0 | E20: =IF($C20="g","30g",IF($C20="ml","30ml","1 unidade")) -> 30ml | F20: 5
A21: Calda de Maracujá | B21: =IFERROR(IF(INDEX(Insumos_Fornecedor,MATCH("Calda de Maracujá",Insumos_Ingrediente,0))=0,"",INDEX(Insumos_Fornecedor,MATCH("Calda de Maracujá",Insumos_Ingrediente,0))),"") | C21: =IFERROR(INDEX(Insumos_Unidade,MATCH("Calda de Maracujá",Insumos_Ingrediente,0)),"") -> ml | D21: =IFERROR(IF($C21="un",INDEX(Insumos_CustoUnit,MATCH("Calda de Maracujá",Insumos_Ingrediente,0)),INDEX(Insumos_CustoUnit,MATCH("Calda de Maracujá",Insumos_Ingrediente,0))*1000),0) -> 0 | E21: =IF($C21="g","30g",IF($C21="ml","30ml","1 unidade")) -> 30ml | F21: 5
A22: Calda de Avelã | B22: =IFERROR(IF(INDEX(Insumos_Fornecedor,MATCH("Calda de Avelã",Insumos_Ingrediente,0))=0,"",INDEX(Insumos_Fornecedor,MATCH("Calda de Avelã",Insumos_Ingrediente,0))),"") | C22: =IFERROR(INDEX(Insumos_Unidade,MATCH("Calda de Avelã",Insumos_Ingrediente,0)),"") -> ml | D22: =IFERROR(IF($C22="un",INDEX(Insumos_CustoUnit,MATCH("Calda de Avelã",Insumos_Ingrediente,0)),INDEX(Insumos_CustoUnit,MATCH("Calda de Avelã",Insumos_Ingrediente,0))*1000),0) -> 0 | E22: =IF($C22="g","30g",IF($C22="ml","30ml","1 unidade")) -> 30ml | F22: 5
A23: Mel | B23: =IFERROR(IF(INDEX(Insumos_Fornecedor,MATCH("Mel",Insumos_Ingrediente,0))=0,"",INDEX(Insumos_Fornecedor,MATCH("Mel",Insumos_Ingrediente,0))),"") | C23: =IFERROR(INDEX(Insumos_Unidade,MATCH("Mel",Insumos_Ingrediente,0)),"") -> ml | D23: =IFERROR(IF($C23="un",INDEX(Insumos_CustoUnit,MATCH("Mel",Insumos_Ingrediente,0)),INDEX(Insumos_CustoUnit,MATCH("Mel",Insumos_Ingrediente,0))*1000),0) -> 0 | E23: =IF($C23="g","30g",IF($C23="ml","30ml","1 unidade")) -> 30ml | F23: 5
A25: Adicionais Premium — porção vendida a R$ 7,00
A26: Produto | B26: Fornecedor | C26: Unidade | D26: Preço Kg/L (R$) | E26: Porção | F26: Valor Final (R$)
A27: Whey Protein | B27: =IFERROR(IF(INDEX(Insumos_Fornecedor,MATCH("Whey Protein",Insumos_Ingrediente,0))=0,"",INDEX(Insumos_Fornecedor,MATCH("Whey Protein",Insumos_Ingrediente,0))),"") | C27: =IFERROR(INDEX(Insumos_Unidade,MATCH("Whey Protein",Insumos_Ingrediente,0)),"") -> g | D27: =IFERROR(IF($C27="un",INDEX(Insumos_CustoUnit,MATCH("Whey Protein",Insumos_Ingrediente,0)),INDEX(Insumos_CustoUnit,MATCH("Whey Protein",Insumos_Ingrediente,0))*1000),0) -> 0 | E27: =IF($C27="g","30g",IF($C27="ml","30ml","1 unidade")) -> 30g | F27: 7
A28: Nutella | B28: =IFERROR(IF(INDEX(Insumos_Fornecedor,MATCH("Nutella",Insumos_Ingrediente,0))=0,"",INDEX(Insumos_Fornecedor,MATCH("Nutella",Insumos_Ingrediente,0))),"") | C28: =IFERROR(INDEX(Insumos_Unidade,MATCH("Nutella",Insumos_Ingrediente,0)),"") -> g | D28: =IFERROR(IF($C28="un",INDEX(Insumos_CustoUnit,MATCH("Nutella",Insumos_Ingrediente,0)),INDEX(Insumos_CustoUnit,MATCH("Nutella",Insumos_Ingrediente,0))*1000),0) -> 0 | E28: =IF($C28="g","30g",IF($C28="ml","30ml","1 unidade")) -> 30g | F28: 7
A29: Pasta de Amendoim | B29: =IFERROR(IF(INDEX(Insumos_Fornecedor,MATCH("Pasta de Amendoim",Insumos_Ingrediente,0))=0,"",INDEX(Insumos_Fornecedor,MATCH("Pasta de Amendoim",Insumos_Ingrediente,0))),"") | C29: =IFERROR(INDEX(Insumos_Unidade,MATCH("Pasta de Amendoim",Insumos_Ingrediente,0)),"") -> g | D29: =IFERROR(IF($C29="un",INDEX(Insumos_CustoUnit,MATCH("Pasta de Amendoim",Insumos_Ingrediente,0)),INDEX(Insumos_CustoUnit,MATCH("Pasta de Amendoim",Insumos_Ingrediente,0))*1000),0) -> 0 | E29: =IF($C29="g","30g",IF($C29="ml","30ml","1 unidade")) -> 30g | F29: 7

Sheet Milkshakes
A1: 🥤 MILKSHAKES — Preço x Custo
A2: Cada sabor é uma linha — tamanho único no cardápio atual. Preço, custo, CMV e margem vêm da aba Receitas.
A4: Produto | B4: Tamanho Único
B5: Preço (R$) | C5: Custo Total (R$) | D5: CMV (%) | E5: Margem (%)
A6: Milkshake Morango | B6: =IFERROR(INDEX(Receitas_PrecoPraticado,MATCH("Milkshake Morango",Receitas_Produto,0)),"") -> 18 | C6: =IFERROR(INDEX(Receitas_CustoTotalUnit,MATCH("Milkshake Morango",Receitas_Produto,0)),"") -> 10.334979 | D6: =IFERROR(INDEX(Receitas_CMV,MATCH("Milkshake Morango",Receitas_Produto,0)),"") -> 0.1625945 | E6: =IFERROR(INDEX(Receitas_Margem,MATCH("Milkshake Morango",Receitas_Produto,0)),"") -> 0.22083451
A7: Milkshake Maracujá | B7: =IFERROR(INDEX(Receitas_PrecoPraticado,MATCH("Milkshake Maracujá",Receitas_Produto,0)),"") -> 18 | C7: =IFERROR(INDEX(Receitas_CustoTotalUnit,MATCH("Milkshake Maracujá",Receitas_Produto,0)),"") -> 10.334979 | D7: =IFERROR(INDEX(Receitas_CMV,MATCH("Milkshake Maracujá",Receitas_Produto,0)),"") -> 0.1625945 | E7: =IFERROR(INDEX(Receitas_Margem,MATCH("Milkshake Maracujá",Receitas_Produto,0)),"") -> 0.22083451
A8: Milkshake Leite em Pó com Nutella | B8: =IFERROR(INDEX(Receitas_PrecoPraticado,MATCH("Milkshake Leite em Pó com Nutella",Receitas_Produto,0)),"") -> 20 | C8: =IFERROR(INDEX(Receitas_CustoTotalUnit,MATCH("Milkshake Leite em Pó com Nutella",Receitas_Produto,0)),"") -> 11.372608 | D8: =IFERROR(INDEX(Receitas_CMV,MATCH("Milkshake Leite em Pó com Nutella",Receitas_Produto,0)),"") -> 0.19821649 | E8: =IFERROR(INDEX(Receitas_Margem,MATCH("Milkshake Leite em Pó com Nutella",Receitas_Produto,0)),"") -> 0.22636962
A9: Milkshake Crocante com Ovomaltine | B9: =IFERROR(INDEX(Receitas_PrecoPraticado,MATCH("Milkshake Crocante com Ovomaltine",Receitas_Produto,0)),"") -> 20 | C9: =IFERROR(INDEX(Receitas_CustoTotalUnit,MATCH("Milkshake Crocante com Ovomaltine",Receitas_Produto,0)),"") -> 11.98034 | D9: =IFERROR(INDEX(Receitas_CMV,MATCH("Milkshake Crocante com Ovomaltine",Receitas_Produto,0)),"") -> 0.22860309 | E9: =IFERROR(INDEX(Receitas_Margem,MATCH("Milkshake Crocante com Ovomaltine",Receitas_Produto,0)),"") -> 0.19598302
A10: Power Shake | B10: =IFERROR(INDEX(Receitas_PrecoPraticado,MATCH("Power Shake",Receitas_Produto,0)),"") -> 22 | C10: =IFERROR(INDEX(Receitas_CustoTotalUnit,MATCH("Power Shake",Receitas_Produto,0)),"") -> 11.644154 | D10: =IFERROR(INDEX(Receitas_CMV,MATCH("Power Shake",Receitas_Produto,0)),"") -> 0.19253983 | E10: =IFERROR(INDEX(Receitas_Margem,MATCH("Power Shake",Receitas_Produto,0)),"") -> 0.26572027
A11: Protein Shake | B11: =IFERROR(INDEX(Receitas_PrecoPraticado,MATCH("Protein Shake",Receitas_Produto,0)),"") -> 24 | C11: =IFERROR(INDEX(Receitas_CustoTotalUnit,MATCH("Protein Shake",Receitas_Produto,0)),"") -> 10.334979 | D11: =IFERROR(INDEX(Receitas_CMV,MATCH("Protein Shake",Receitas_Produto,0)),"") -> 0.12194588 | E11: =IFERROR(INDEX(Receitas_Margem,MATCH("Protein Shake",Receitas_Produto,0)),"") -> 0.36437588

Sheet Bebidas
A1: 🥤 BEBIDAS — Preço x Custo de Revenda
A2: Itens de revenda simples: o preço de compra vem da aba Insumos (categoria Bebidas).
A4: Produto | B4: Tamanho Único
B5: Preço (R$) | C5: Custo Total (R$) | D5: CMV (%) | E5: Margem (%)
A6: Água sem Gás 500ml | B6: =IFERROR(INDEX(Receitas_PrecoPraticado,MATCH("Água sem Gás 500ml",Receitas_Produto,0)),"") -> 4 | C6: =IFERROR(INDEX(Receitas_CustoTotalUnit,MATCH("Água sem Gás 500ml",Receitas_Produto,0)),"") -> 7.4082778 | D6: =IFERROR(INDEX(Receitas_CMV,MATCH("Água sem Gás 500ml",Receitas_Produto,0)),"") -> 0 | E6: =IFERROR(INDEX(Receitas_Margem,MATCH("Água sem Gás 500ml",Receitas_Produto,0)),"") -> -1.0570694
A7: Água com Gás 500ml | B7: =IFERROR(INDEX(Receitas_PrecoPraticado,MATCH("Água com Gás 500ml",Receitas_Produto,0)),"") -> 4.5 | C7: =IFERROR(INDEX(Receitas_CustoTotalUnit,MATCH("Água com Gás 500ml",Receitas_Produto,0)),"") -> 7.4082778 | D7: =IFERROR(INDEX(Receitas_CMV,MATCH("Água com Gás 500ml",Receitas_Produto,0)),"") -> 0 | E7: =IFERROR(INDEX(Receitas_Margem,MATCH("Água com Gás 500ml",Receitas_Produto,0)),"") -> -0.85128395
A8: Água de Coco 200ml | B8: =IFERROR(INDEX(Receitas_PrecoPraticado,MATCH("Água de Coco 200ml",Receitas_Produto,0)),"") -> 3.5 | C8: =IFERROR(INDEX(Receitas_CustoTotalUnit,MATCH("Água de Coco 200ml",Receitas_Produto,0)),"") -> 7.4082778 | D8: =IFERROR(INDEX(Receitas_CMV,MATCH("Água de Coco 200ml",Receitas_Produto,0)),"") -> 0 | E8: =IFERROR(INDEX(Receitas_Margem,MATCH("Água de Coco 200ml",Receitas_Produto,0)),"") -> -1.3216508
A9: Refrigerante Lata 350ml | B9: =IFERROR(INDEX(Receitas_PrecoPraticado,MATCH("Refrigerante Lata 350ml",Receitas_Produto,0)),"") -> 3 | C9: =IFERROR(INDEX(Receitas_CustoTotalUnit,MATCH("Refrigerante Lata 350ml",Receitas_Produto,0)),"") -> 7.4082778 | D9: =IFERROR(INDEX(Receitas_CMV,MATCH("Refrigerante Lata 350ml",Receitas_Produto,0)),"") -> 0 | E9: =IFERROR(INDEX(Receitas_Margem,MATCH("Refrigerante Lata 350ml",Receitas_Produto,0)),"") -> -1.6744259
A10: Refrigerante 600ml | B10: =IFERROR(INDEX(Receitas_PrecoPraticado,MATCH("Refrigerante 600ml",Receitas_Produto,0)),"") -> 5 | C10: =IFERROR(INDEX(Receitas_CustoTotalUnit,MATCH("Refrigerante 600ml",Receitas_Produto,0)),"") -> 7.4082778 | D10: =IFERROR(INDEX(Receitas_CMV,MATCH("Refrigerante 600ml",Receitas_Produto,0)),"") -> 0 | E10: =IFERROR(INDEX(Receitas_Margem,MATCH("Refrigerante 600ml",Receitas_Produto,0)),"") -> -0.68665556
A11: Isotônico 500ml | B11: =IFERROR(INDEX(Receitas_PrecoPraticado,MATCH("Isotônico 500ml",Receitas_Produto,0)),"") -> 6 | C11: =IFERROR(INDEX(Receitas_CustoTotalUnit,MATCH("Isotônico 500ml",Receitas_Produto,0)),"") -> 7.4082778 | D11: =IFERROR(INDEX(Receitas_CMV,MATCH("Isotônico 500ml",Receitas_Produto,0)),"") -> 0 | E11: =IFERROR(INDEX(Receitas_Margem,MATCH("Isotônico 500ml",Receitas_Produto,0)),"") -> -0.43971296
A12: Suco Natural 300ml | B12: =IFERROR(INDEX(Receitas_PrecoPraticado,MATCH("Suco Natural 300ml",Receitas_Produto,0)),"") -> 8 | C12: =IFERROR(INDEX(Receitas_CustoTotalUnit,MATCH("Suco Natural 300ml",Receitas_Produto,0)),"") -> 7.4082778 | D12: =IFERROR(INDEX(Receitas_CMV,MATCH("Suco Natural 300ml",Receitas_Produto,0)),"") -> 0 | E12: =IFERROR(INDEX(Receitas_Margem,MATCH("Suco Natural 300ml",Receitas_Produto,0)),"") -> -0.13103472
A13: Suco de Açaí 200ml | B13: =IFERROR(INDEX(Receitas_PrecoPraticado,MATCH("Suco de Açaí 200ml",Receitas_Produto,0)),"") -> 6 | C13: =IFERROR(INDEX(Receitas_CustoTotalUnit,MATCH("Suco de Açaí 200ml",Receitas_Produto,0)),"") -> 7.4082778 | D13: =IFERROR(INDEX(Receitas_CMV,MATCH("Suco de Açaí 200ml",Receitas_Produto,0)),"") -> 0 | E13: =IFERROR(INDEX(Receitas_Margem,MATCH("Suco de Açaí 200ml",Receitas_Produto,0)),"") -> -0.43971296
